Workbook

Sheet ROP 2024
B1: TVM PR & IC KW | D1: MARKET PLAN | G1: YEARS until 2018 | H1: YEAR 2017 | I1: 42370 | J1: 42401 | K1: 42430 | L1: 42461 | M1: 42491 | N1: 42522 | O1: 42552 | P1: 42583 | Q1: 42614 | R1: 42644 | S1: 42675 | T1: 42705 | U1: 2017 YEAR TO DATE | W1: TOTAL ACTUAL
B4: SALES OF TICKETS PR *) | D4: 82265384 | G4: 72392298 | H4: 16387948 | V4: =SUM(I4:T4) -> 0 | W4: =V4+G4+H4 -> 88780245
B5: SALES LEASE AGREEMENT / OTHER SALES | D5: 1485687.9 | G5: 1555442.1 | H5: 0 | V5: =SUM(I5:T5) -> 0 | W5: =V5+G5+H5 -> 1555442.1
B6: IC PROVISION | D6: 4126711 | G6: 2696236.7 | H6: 848927.59 | V6: =SUM(I6:T6) -> 0 | W6: =V6+G6+H6 -> 3545164.3
B7: SALES OF TICKETS KW *) | G7: 8791465.6 | H7: 2796298.5 | V7: =SUM(I7:T7) -> 0 | W7: =V7+G7+H7 -> 11587764
B8: SALES OF ARRIVA RP (FLAT FEE / TVM) | G8: 142480.79 | H8: 19171.89 | V8: =SUM(I8:T8) -> 0 | W8: =V8+G8+H8 -> 161652.68
B9: SALES LEASE AGREEMENT / OTHER SALES
B10: SALES, GROSS | D10: 87877783 | G10: =SUM(G4:G9) -> 85577923 | H10: =SUM(H4:H9) -> 20052346 | V10: =SUM(V4:V9) -> 0 | W10: =SUM(W4:W9) -> 1.0563027e+08
B12: PURCHASE COSTS OF TICKETS PR **) | D12: 72539556 | G12: 61293730 | H12: 13830056 | V12: =SUM(I12:T12) -> 0 | W12: =V12+G12+H12 -> 75123786
B13: PURCHASE COSTS OF TICKETS KW **) | G13: 8100569.3 | H13: 2583838.1 | V13: =SUM(I13:T13) -> 0 | W13: =V13+G13+H13 -> 10684407
B14: SALES, NET | D14: 15338227 | G14: =(G10-G12-G13) -> 16183624 | H14: =(H10-H12-H13) -> 3638451.3 | V14: =(V10-V12-V13) -> 0 | W14: =(W10-W12-W13) -> 19822075
B15: Margin | D15: 0.17454044 | G15: =IF(G10<>0,G14/G10,"") -> 0.1891098 | H15: =IF(H10<>0,H14/H10,"") -> 0.18144767 | V15: =IF(V10<>0,V14/V10,"") | W15: =IF(W10<>0,W14/W10,"") -> 0.18765526
B17: DEPRECIATION (8 years, of initial investment, calculatory) | D17: 4982793 | G17: 3507538.9 | H17: 578795.52 | V17: =SUM(I17:T17) -> 0 | W17: =V17+G17+H17 -> 4086334.4
D18: 0 | G18: 0 | H18: 0 | V18: =SUM(I18:T18) -> 0 | W18: =V18+G18 -> 0
B19: MATERIAL & EQUIPMENT | D19: 379002 | G19: 364470.01 | H19: 97555.27 | V19: =SUM(I19:T19) -> 0 | W19: =V19+G19+H19 -> 462025.28
B20: thereof internal | D20: 189501 | G20: 72282.07 | H20: 4107.8 | V20: =SUM(I20:T20) -> 0 | W20: =V20+G20+H20 -> 76389.87
B21: thereof external | D21: 189501 | G21: 292187.94 | H21: 93447.47 | V21: =SUM(I21:T21) -> 0 | W21: =V21+G21+H21 -> 385635.41
B22: BURDEN COSTS MATERIAL 8,5% | C22: 0.1 | D22: 32215.17 | G22: 34950.373 | H22: 9755.527 | V22: =SUM(I22:T22) -> 0 | W22: =V22+G22+H22 -> 44705.9
B23: ="INTEREST ("&#REF!*100&"% rate, 8 years, calculatory)" -> #REF! | C23: 0.04 | D23: 828552.87 | G23: 808396.11 | H23: 41050.464 | V23: =SUM(I23:T23) -> 0 | W23: =V23+G23+H23 -> 849446.57
B24: SUBCONTRACTOR | D24: 3388674 | G24: 3498124.5 | H24: 839003.81 | V24: =SUM(I24:T24) -> 0 | W24: =V24+G24+H24 -> 4337128.3
B25: thereof internal | D25: 15000 | G25: 50672 | H25: 0 | V25: =SUM(I25:T25) -> 0 | W25: =V25+G25+H25 -> 50672
B26: thereof external | D26: 3373674 | G26: 3447452.5 | H26: 839003.81 | V26: =SUM(I26:T26) -> 0 | W26: =V26+G26+H26 -> 4286456.3
B27: HANDLING FEE SUBCON 15% | C27: 0.15 | D27: 508301.1 | G27: 524718.68 | H27: 125850.57 | V27: =SUM(I27:T27) -> 0 | W27: =V27+G27+H27 -> 650569.25
B28: LABOR COSTS | D28: 810549 | G28: 1655476.5 | H28: 336746.1 | V28: =SUM(I28:T28) -> 0 | W28: =V28+G28+H28 -> 1992222.6
B29: BURDEN COSTS LABOR 11,5% | C29: 0.14 | D29: 93213.135 | G29: 209573.3 | H29: 47144.454 | V29: =SUM(I29:T29) -> 0 | W29: =V29+G29+H29 -> 256717.75
B30: SUBTOTAL Cost of Products Sold | D30: 11023300 | G30: =SUM(G17:G19,G22:G24,G27:G29) -> 10603248 | H30: =SUM(H17:H19,H22:H24,H27:H29) -> 2075901.7 | V30: =SUM(V17:V19,V22:V24,V27:V29) -> 0 | W30: =SUM(W17:W19,W22:W24,W27:W29) -> 12679150
B31: DIVISION ALLOCATION RATE 15% | C31: 0.15 | D31: 944665.85 | G31: 969428.92 | H31: =SUM(H17,H19,H22,H28:H29)*$C$31 -> 160499.53 | V31: =SUM(I31:T31) -> 0 | W31: =V31+G31+H31 -> 1129928.4
H32: 0 | V32: =SUM(I32:T32) -> 0 | W32: =V32+G32+H32 -> 0
B33: OTHER DIRECT PROJECT COSTS: | H33: 0 | V33: =SUM(I33:T33) -> 0 | W33: =V33+G33+H33 -> 0
B34: TRAVEL | D34: 239094 | G34: 452673.42 | H34: 89508.43 | V34: =SUM(I34:T34) -> 0 | W34: =V34+G34+H34 -> 542181.85
B35: AGENTS/COMMISSION (calculatory) | D35: 1531302.3 | G35: 986353.85 | H35: 112800 | V35: =SUM(I35:T35) -> 0 | W35: =V35+G35+H35 -> 1099153.9
B36: OTHER | D36: 179047 | G36: 545122.89 | H36: 62568.5 | V36: =SUM(I36:T36) -> 0 | W36: =V36+G36+H36 -> 607691.39
B37: LDs | G37: 0 | V37: =SUM(I37:T37) -> 0 | W37: =V37+G37+H37 -> 0
B38: SALES TAX (payable) | H38: 0 | V38: =SUM(I38:T38) -> 0 | W38: =V38+G38 -> 0
B39: RISK BUDGET | G39: 0 | H39: 0 | V39: =SUM(I39:T39) -> 0 | W39: =V39+G39+H39 -> 0
V40: =SUM(I40:T40) -> 0 | W40: =V40+G40+H40 -> 0
B41: CONSOLIDATION DIFFERENCE | G41: 0 | H41: 0 | V41: =SUM(I41:T41) -> 0 | W41: =V41+G41+H41 -> 0
B42: ACCRUALS | G42: 0 | H42: 0 | V42: =SUM(I42:T42) -> 0 | W42: =V42+G42+H42 -> 0
B43: WIP | G43: 0 | H43: 0 | V43: =SUM(I43:T43) -> 0 | W43: =V43+G43+H43 -> 0
V44: =SUM(I44:T44) -> 0 | W44: =V44+G44+H44 -> 0
B45: PROFIT/LOSS | D45: 1420817.6 | G45: =(G14-SUM(G30:G44)) -> 2626796.2 | H45: =(H14-SUM(H30:H44)) -> 1137173.1 | I45: =(I14-SUM(I30:I44)) -> 0 | J45: =(J14-SUM(J30:J44)) -> 0 | K45: =(K14-SUM(K30:K44)) -> 0 | L45: =(L14-SUM(L30:L44)) -> 0 | M45: =(M14-SUM(M30:M44)) -> 0 | N45: =(N14-SUM(N30:N44)) -> 0 | V45: =(V14-SUM(V30:V44)) -> 0 | W45: =(W14-SUM(W30:W44)) -> 3763969.3
B47: ONE TIME ITEMS included in operating expense | V47: =SUM(I47:T47) -> 0
B48: PROFIT/LOSS (operational) | I48: =+I45+I47 -> 0 | J48: =+J45+J47 -> 0 | K48: =+K45+K47 -> 0 | L48: =+L45+L47 -> 0 | M48: =+M45+M47 -> 0 | N48: =+N45+N47 -> 0 | V48: =SUM(I48:T48) -> 0
B50: CASH FLOW (per period) | D50: 7232163.4 | G50: =G45+G17+G18+G23 -> 6942731.2 | H50: =H45+H17+H18+H23 -> 1757019.1 | I50: 112367.45 | J50: 71795.741 | K50: 103744.71 | L50: 107126.29 | M50: 107894.12 | N50: 161046.25 | V50: =V45+V17+V18+V23 -> 0 | W50: =W45+W17+W18+W23 -> 8699750.3
B52: CASH FLOW (accumulated) | D52: 2249370.4 | G52: =G50-$D$17-$D$18 -> 1959938.2 | H52: =G52+H50 -> 3716957.3 | I52: 3829324.7 | J52: 3901120.5 | K52: 4004865.2 | L52: 4111991.5 | M52: 4219885.6 | N52: 4380931.8 | O52: =N52+O50 -> 4380931.8 | P52: =O52+P50 -> 4380931.8 | Q52: =P52+Q50 -> 4380931.8 | R52: =Q52+R50 -> 4380931.8 | S52: =R52+S50 -> 4380931.8 | T52: =S52+T50 -> 4380931.8 | V52: =T52 -> 4380931.8 | W52: =V52 -> 4380931.8
B54: NON-AMORTIZED INVESTMENT | D54: 0 | G54: =$D$17-G17 -> 1475254.1 | H54: =G54-H17 -> 896458.63 | I54: 868706.47 | J54: 847007.34 | K54: 828119.78 | L54: 813095.93 | M54: 799673.04 | N54: 788317.07 | O54: 788317.07 | P54: 788317.07 | Q54: 788317.07 | R54: 788317.07 | S54: 788317.07 | T54: 788317.07 | V54: =T54 -> 788317.07 | W54: =V54 -> 788317.07
B56: RETURN ON INVESTMENT | D56: 0.28514481 | G56: =G45/$D$17 -> 0.52717345 | H56: =H45/$D$17 -> 0.22822003 | I56: 0.016086336 | J56: 0.0091962709 | K56: 0.016210023 | L56: 0.017701848 | M56: 0.01821513 | N56: 0.029335092 | O56: 0.027396413 | P56: 0.028800301 | Q56: 0.019654987 | R56: 0.022072289 | S56: 0.0092494697 | T56: 0.013616828 | V56: =V45/$D$17 -> 0 | W56: =W45/$D$17 -> 0.75539348
B58: Lokalizacja automatu | I58: 42736 | J58: 42767 | K58: 42795 | L58: 42826 | M58: 42856 | N58: 42887 | O58: 42917 | P58: 42948 | Q58: 42979 | R58: 43009 | S58: 43040 | T58: 43070 | U58: Rok 2018 | V58: Uwagi
B60: ='Profitability of ROP TVMs'!A3 -> 1101 | I60: ='Profitability of ROP TVMs'!AS3 -> 3528.6265
B61: ='Profitability of ROP TVMs'!A4 -> 1102 | I61: ='Profitability of ROP TVMs'!AS4 -> 2266.6347
B62: ='Profitability of ROP TVMs'!A5 -> 1103 | I62: ='Profitability of ROP TVMs'!AS5 -> 2810.4346
B63: ='Profitability of ROP TVMs'!A6 -> 1104 | I63: ='Profitability of ROP TVMs'!AS6 -> 4966.8741
B64: ='Profitability of ROP TVMs'!A7 -> 1105 | I64: ='Profitability of ROP TVMs'!AS7 -> 2277.2994
B65: ='Profitability of ROP TVMs'!A8 -> 1106 | I65: ='Profitability of ROP TVMs'!AS8 -> 2649.8724
B66: ='Profitability of ROP TVMs'!A9 -> 1107 | I66: ='Profitability of ROP TVMs'!AS9 -> 2437.4107
B67: ='Profitability of ROP TVMs'!A10 -> 1108 | I67: ='Profitability of ROP TVMs'!AS10 -> 2392.8495
B68: ='Profitability of ROP TVMs'!A11 -> 1109 | I68: ='Profitability of ROP TVMs'!AS11 -> 2254.9149
B69: ='Profitability of ROP TVMs'!A12 -> 1110 | I69: ='Profitability of ROP TVMs'!AS12 -> 2271.4891
B70: ='Profitability of ROP TVMs'!A13 -> 1111 | I70: ='Profitability of ROP TVMs'!AS13 -> 0
B71: ='Profitability of ROP TVMs'!A14 -> 1112 | I71: ='Profitability of ROP TVMs'!AS14 -> 0
... B159: ='Profitability of ROP TVMs'!A102 -> RAZEM | I159: ='Profitability of ROP TVMs'!AS102 -> 23228.388

Sheet ROP-Michał-2024
A1: Nr aut. | B1: Lokalizacja automatu | D1: 45292 | Q1: 45292 | AT1: 45292 | BH1: 45323 | CK1: 45352 | CY1: 45352 | EB1: 45383 | EP1: 45383 | FS1: 45413 | GG1: 45413 | HJ1: 45444 | HX1: 45444 | JA1: 45474 | JO1: 45474 | KR1: 45505 | LF1: 45505 | MI1: 45536 | MW1: 45536 | NZ1: 45566 | ON1: 45566 | PQ1: 45597 | QE1: 45597 | RH1: 45627 | RV1: 45627 | SY1: TOTAL 2024
C2: Rodzaj automatu | D2: Brutto IC | E2: Brutto PR | F2: Brutto KW | G2: Brutto PP | H2: Brutto Arriva | I2: Brutto SKM | J2: Brutto KMŁ | K2: Brutto KD | L2: Brutto KŚ | M2: Brutto ŁKA | N2: W tym płatności kartowe | O2: W tym płatności gotówką | P2: Ilość biletów | Q2: Brutto Total | R2: Prowizja IC | S2: Prowizja PR | T2: Prowizja KW | U2: Prowizja PP | V2: Prowizja ARP | W2: Prowizja SKM | X2: Prowizja KMŁ | Y2: Prowizja KD | Z2: Prowizja KŚ | AA2: Prowizja ŁKA | AB2: Prowizja Suma | AC2: Czynsz | AD2: Prąd | AE2: Elavon | AF2: Poczta Polska | AG2: Amortyzacja | AH2: Utrzymanie oprogr. Centreo | AI2: Papier | AJ2: Transmisja danych | AK2: Serwis* | AL2: Polisa | AM2: Total TVMs Direct Costs | AN2: Non TVMs project fixed costs | AO2: Project Variable costs | AP2: OH | AQ2: Total Other Project Costs | AR2: Total cost of TVM | AS2: Proift/loss | AT2: Brutto IC | AU2: Brutto PR | AV2: Brutto KW | AW2: Brutto PP | AX2: Brutto Arriva | AY2: Brutto SKM | AZ2: Brutto KMŁ | BA2: Brutto KD | BB2: Brutto KŚ | BC2: Brutto ŁKA | BD2: W tym płatności kartowe | BE2: W tym płatności gotówką | BF2: Ilość biletów | BG2: Rodzaj automatu | BH2: Brutto Total | BI2: Prowizja IC | BJ2: Prowizja PR | BK2: Prowizja KW | BL2: Prowizja PP | BM2: Prowizja ARP | BN2: Prowizja SKM | BO2: Prowizja KMŁ | BP2: Prowizja KD | BQ2: Prowizja KŚ | BR2: Prowizja ŁKA | BS2: Prowizja Suma | BT2: Czynsz | BU2: Prąd | BV2: Elavon | BW2: Poczta Polska | BX2: Amortyzacja | BY2: Utrzymanie oprogr. Centreo | BZ2: Papier | CA2: Transmisja danych | CB2: Serwis* | CC2: Polisa | CD2: Total TVMs Direct Costs | CE2: Non TVMs project fixed costs | CF2: Project Variable costs | CG2: OH | CH2: Total Other Project Costs | CI2: Total cost of TVM | CJ2: Proift/loss | CK2: Brutto IC | CL2: Brutto PR | CM2: Brutto KW | CN2: Brutto PP | CO2: Brutto Arriva | CP2: Brutto SKM | CQ2: Brutto KMŁ | CR2: Brutto KD | CS2: Brutto KŚ | CT2: Brutto ŁKA | CU2: W tym płatności kartowe | CV2: W tym płatności gotówką | CW2: Ilość biletów | CX2: Rodzaj automatu | CY2: Brutto Total | CZ2: Prowizja IC | DA2: Prowizja PR | DB2: Prowizja KW | DC2: Prowizja PP | DD2: Prowizja ARP | DE2: Prowizja SKM | DF2: Prowizja KMŁ | DG2: Prowizja KD | DH2: Prowizja KŚ | DI2: Prowizja ŁKA | DJ2: Prowizja Suma | DK2: Czynsz | DL2: Prąd | DM2: Elavon | DN2: Poczta Polska | DO2: Amortyzacja | DP2: Utrzymanie oprogr. Centreo | DQ2: Papier | DR2: Transmisja danych | DS2: Serwis* | DT2: Polisa | DU2: Total TVMs Direct Costs | DV2: Non TVMs project fixed costs | DW2: Project Variable costs | DX2: OH | DY2: Total Other Project Costs | DZ2: Total cost of TVM | EA2: Proift/loss | EB2: Brutto IC | EC2: Brutto PR | ED2: Brutto KW | EE2: Brutto PP | EF2: Brutto Arriva | EG2: Brutto SKM | EH2: Brutto KMŁ | EI2: Brutto KD | EJ2: Brutto KŚ | EK2: Brutto ŁKA | EL2: W tym płatności kartowe | EM2: W tym płatności gotówką | EN2: Ilość biletów | EO2: Rodzaj automatu | EP2: Brutto Total | EQ2: Prowizja IC | ER2: Prowizja PR | ES2: Prowizja KW | ET2: Prowizja PP | EU2: Prowizja ARP | EV2: Prowizja SKM | EW2: Prowizja KMŁ | EX2: Prowizja KD | EY2: Prowizja KŚ | EZ2: Prowizja ŁKA | FA2: Prowizja Suma | FB2: Czynsz | FC2: Prąd | FD2: Elavon | FE2: Poczta Polska | FF2: Amortyzacja | FG2: Utrzymanie oprogr. Centreo | FH2: Papier | FI2: Transmisja danych | FJ2: Serwis* | FK2: Polisa | FL2: Total TVMs Direct Costs | FM2: Non TVMs project fixed costs | FN2: Project Variable costs | FO2: OH | FP2: Total Other Project Costs | FQ2: Total cost of TVM | FR2: Proift/loss | FS2: Brutto IC | FT2: Brutto PR | FU2: Brutto KW | FV2: Brutto PP | FW2: Brutto Arriva | FX2: Brutto SKM | FY2: Brutto KMŁ | FZ2: Brutto KD | GA2: Brutto KŚ | GB2: Brutto ŁKA | GC2: W tym płatności kartowe | GD2: W tym płatności gotówką | GE2: Ilość biletów | GF2: Rodzaj automatu | GG2: Brutto Total | GH2: Prowizja IC | GI2: Prowizja PR | GJ2: Prowizja KW | GK2: Prowizja PP | GL2: Prowizja ARP | GM2: Prowizja SKM | GN2: Prowizja KMŁ | GO2: Prowizja KD | GP2: Prowizja KŚ | GQ2: Prowizja ŁKA | GR2: Prowizja Suma | GS2: Czynsz | GT2: Prąd | GU2: Elavon | GV2: Poczta Polska | GW2: Amortyzacja | GX2: Utrzymanie oprogr. Centreo | GY2: Papier | GZ2: Transmisja danych | HA2: Serwis* | HB2: Polisa | HC2: Total TVMs Direct Costs | HD2: Non TVMs project fixed costs | HE2: Project Variable costs | HF2: OH | HG2: Total Other Project Costs | HH2: Total cost of TVM | HI2: Proift/loss | HJ2: Brutto IC | HK2: Brutto PR | HL2: Brutto KW | HM2: Brutto PP | HN2: Brutto Arriva | HO2: Brutto SKM | HP2: Brutto KMŁ | HQ2: Brutto KD | HR2: Brutto KŚ | HS2: Brutto ŁKA | HT2: W tym płatności kartowe | HU2: W tym płatności gotówką | HV2: Ilość biletów | HW2: Rodzaj automatu | HX2: Brutto Total | HY2: Prowizja IC | HZ2: Prowizja PR | IA2: Prowizja KW | IB2: Prowizja PP | IC2: Prowizja ARP | ID2: Prowizja SKM | IE2: Prowizja KMŁ | IF2: Prowizja KD | IG2: Prowizja KŚ | IH2: Prowizja ŁKA | II2: Prowizja Suma | IJ2: Czynsz | IK2: Prąd | IL2: Elavon | IM2: Poczta Polska | IN2: Amortyzacja | IO2: Utrzymanie oprogr. Centreo | IP2: Papier | IQ2: Transmisja danych | IR2: Serwis* | IS2: Polisa | IT2: Total TVMs Direct Costs | IU2: Non TVMs project fixed costs | IV2: Project Variable costs | IW2: OH | IX2: Total Other Project Costs | IY2: Total cost of TVM | IZ2: Proift/loss | JA2: Brutto IC | JB2: Brutto PR | JC2: Brutto KW | JD2: Brutto PP | JE2: Brutto Arriva | JF2: Brutto SKM | JG2: Brutto KMŁ | JH2: Brutto KD | JI2: Brutto KŚ | JJ2: Brutto ŁKA | JK2: W tym płatności kartowe | JL2: W tym płatności gotówką | JM2: Ilość biletów | JN2: Rodzaj automatu | JO2: Brutto Total | JP2: Prowizja IC | JQ2: Prowizja PR | JR2: Prowizja KW | JS2: Prowizja PP | JT2: Prowizja ARP | JU2: Prowizja SKM | JV2: Prowizja KMŁ | JW2: Prowizja KD | JX2: Prowizja KŚ | JY2: Prowizja ŁKA | JZ2: Prowizja Suma | KA2: Czynsz | KB2: Prąd | KC2: Elavon | KD2: Poczta Polska | KE2: Amortyzacja | KF2: Utrzymanie oprogr. Centreo | KG2: Papier | KH2: Transmisja danych | KI2: Serwis* | KJ2: Polisa | KK2: Total TVMs Direct Costs | KL2: Non TVMs project fixed costs | KM2: Project Variable costs | KN2: OH | KO2: Total Other Project Costs | KP2: Total cost of TVM | KQ2: Proift/loss | KR2: Brutto IC | KS2: Brutto PR | KT2: Brutto KW | KU2: Brutto PP | KV2: Brutto Arriva | KW2: Brutto SKM | KX2: Brutto KMŁ | KY2: Brutto KD | KZ2: Brutto KŚ | LA2: Brutto ŁKA | LB2: W tym płatności kartowe | LC2: W tym płatności gotówką | LD2: Ilość biletów | LE2: Rodzaj automatu | LF2: Brutto Total | LG2: Prowizja IC | LH2: Prowizja PR | LI2: Prowizja KW | LJ2: Prowizja PP | LK2: Prowizja ARP | LL2: Prowizja SKM | LM2: Prowizja KMŁ | LN2: Prowizja KD | LO2: Prowizja KŚ | LP2: Prowizja ŁKA | LQ2: Prowizja Suma | LR2: Czynsz | LS2: Prąd | LT2: Elavon | LU2: Poczta Polska | LV2: Amortyzacja | LW2: Utrzymanie oprogr. Centreo | LX2: Papier | LY2: Transmisja danych | LZ2: Serwis* | MA2: Polisa | MB2: Total TVMs Direct Costs | MC2: Non TVMs project fixed costs | MD2: Project Variable costs | ME2: OH | MF2: Total Other Project Costs | MG2: Total cost of TVM | MH2: Proift/loss | MI2: Brutto IC | MJ2: Brutto PR | MK2: Brutto KW | ML2: Brutto PP | MM2: Brutto Arriva | MN2: Brutto SKM | MO2: Brutto KMŁ | MP2: Brutto KD | MQ2: Brutto KŚ | MR2: Brutto ŁKA | MS2: W tym płatności kartowe | MT2: W tym płatności gotówką | MU2: Ilość biletów | MV2: Rodzaj automatu | MW2: Brutto Total | MX2: Prowizja IC | MY2: Prowizja PR | MZ2: Prowizja KW | NA2: Prowizja PP | NB2: Prowizja ARP | NC2: Prowizja SKM | ND2: Prowizja KMŁ | NE2: Prowizja KD | NF2: Prowizja KŚ | NG2: Prowizja ŁKA | NH2: Prowizja Suma | NI2: Czynsz | NJ2: Prąd | NK2: Elavon | NL2: Poczta Polska | NM2: Amortyzacja | NN2: Utrzymanie oprogr. Centreo | NO2: Papier | NP2: Transmisja danych | NQ2: Serwis* | NR2: Polisa | NS2: Total TVMs Direct Costs | NT2: Non TVMs project fixed costs | NU2: Project Variable costs | NV2: OH | NW2: Total Other Project Costs | NX2: Total cost of TVM | NY2: Proift/loss | NZ2: Brutto IC | OA2: Brutto PR | OB2: Brutto KW | OC2: Brutto PP | OD2: Brutto Arriva | OE2: Brutto SKM | OF2: Brutto KMŁ | OG2: Brutto KD | OH2: Brutto KŚ | OI2: Brutto ŁKA | OJ2: W tym płatności kartowe | OK2: W tym płatności gotówką | OL2: Ilość biletów | OM2: Rodzaj automatu | ON2: Brutto Total | OO2: Prowizja IC | OP2: Prowizja PR | OQ2: Prowizja KW | OR2: Prowizja PP | OS2: Prowizja ARP | OT2: Prowizja SKM | OU2: Prowizja KMŁ | OV2: Prowizja KD | OW2: Prowizja KŚ | OX2: Prowizja ŁKA | OY2: Prowizja Suma | OZ2: Czynsz | PA2: Prąd | PB2: Elavon | PC2: Poczta Polska | PD2: Amortyzacja | PE2: Utrzymanie oprogr. Centreo | PF2: Papier | PG2: Transmisja danych | PH2: Serwis* | PI2: Polisa | PJ2: Total TVMs Direct Costs | PK2: Non TVMs project fixed costs | PL2: Project Variable costs | PM2: OH | PN2: Total Other Project Costs | PO2: Total cost of TVM | PP2: Proift/loss | PQ2: Brutto IC | PR2: Brutto PR | PS2: Brutto KW | PT2: Brutto PP | PU2: Brutto Arriva | PV2: Brutto SKM | PW2: Brutto KMŁ | PX2: Brutto KD | PY2: Brutto KŚ | PZ2: Brutto ŁKA | QA2: W tym płatności kartowe | QB2: W tym płatności gotówką | QC2: Ilość biletów | QD2: Rodzaj automatu | QE2: Brutto Total | QF2: Prowizja IC | QG2: Prowizja PR | QH2: Prowizja KW | QI2: Prowizja PP | QJ2: Prowizja ARP | QK2: Prowizja SKM | QL2: Prowizja KMŁ | QM2: Prowizja KD | QN2: Prowizja KŚ | QO2: Prowizja ŁKA | QP2: Prowizja Suma | QQ2: Czynsz | QR2: Prąd | QS2: Elavon | QT2: Poczta Polska | QU2: Amortyzacja | QV2: Utrzymanie oprogr. Centreo | QW2: Papier | QX2: Transmisja danych | QY2: Serwis* | QZ2: Polisa | RA2: Total TVMs Direct Costs | RB2: Non TVMs project fixed costs | RC2: Project Variable costs | RD2: OH | RE2: Total Other Project Costs | RF2: Total cost of TVM | RG2: Proift/loss | RH2: Brutto IC | RI2: Brutto PR | RJ2: Brutto KW | RK2: Brutto PP | RL2: Brutto Arriva | RM2: Brutto SKM | RN2: Brutto KMŁ | RO2: Brutto KD | RP2: Brutto KŚ | RQ2: Brutto ŁKA | RR2: W tym płatności kartowe | RS2: W tym płatności gotówką | RT2: Ilość biletów | RU2: Rodzaj automatu | RV2: Brutto Total | RW2: Prowizja IC | RX2: Prowizja PR | RY2: Prowizja KW | RZ2: Prowizja PP | SA2: Prowizja ARP | SB2: Prowizja SKM | SC2: Prowizja KMŁ | SD2: Prowizja KD | SE2: Prowizja KŚ | SF2: Prowizja ŁKA | SG2: Prowizja Suma | SH2: Czynsz | SI2: Prąd | SJ2: Elavon | SK2: Poczta Polska | SL2: Amortyzacja | SM2: Utrzymanie oprogr. Centreo | SN2: Papier | SO2: Transmisja danych | SP2: Serwis* | SQ2: Polisa | SR2: Total TVMs Direct Costs | SS2: Non TVMs project fixed costs | ST2: Project Variable costs | SU2: OH | SV2: Total Other Project Costs | SW2: Total cost of TVM | SX2: Proift/loss | SY2: Brutto Total | SZ2: Prowizja Suma | TA2: Total cost of TVM | TB2: Prowizja Suma | TC2: Uwagi MW | TD2: UWAGI AS | TE2: Rekomendacja
A3: 1101 | B3: 1101_KRA_GL | C3: MOVE S320 | D3: 19509.23 | E3: 12587.13 | F3: 196.25 | G3: 0 | H3: 0 | I3: 0 | J3: 0 | K3: 40 | L3: 2122.08 | M3: 0 | N3: 34454.69 | O3: 0 | P3: 1379 | Q3: =SUM(D3:M3) -> 34454.69 | R3: 1623.98 | S3: 4357.14 | T3: 12.54 | U3: 0 | V3: 0 | W3: 0 | X3: 750 | Y3: 2.78 | Z3: 117.89 | AA3: 0 | AB3: =SUM(R3:AA3) -> 6864.33 | AD3: 276.52 | AE3: =(N3/$N$116)*21028.32 -> 374.61888 | AF3: =(O3/$O$116)*15324.97 -> 0 | AH3: 20 | AJ3: 5 | AK3: =39081.75/95 -> 411.38684 | AM3: =SUM(AC3:AL3) -> 1087.5257 | AN3: =61284.58/95 -> 645.10084 | AO3: 0 | AP3: =(AN3+AO3)*30% -> 193.53025 | AQ3: =SUM(AN3:AP3) -> 838.63109 | AR3: =AM3+AQ3 -> 1926.1568 | AS3: =AB3-AR3 -> 4938.1732 | AT3: 16000.97 | AU3: 12307.76 | AV3: 0 | AW3: 0 | AX3: 0 | AY3: 0 | AZ3: 0 | BA3: 43.8 | BB3: 1755 | BC3: 0 | BD3: 30107.53 | BE3: 0 | BF3: 1292 | BG3: MOVE S320 | BH3: =SUM(AT3:BC3) -> 30107.53 | BI3: 1331.93 | BJ3: 4357.14 | BK3: 0 | BL3: 0 | BM3: 0 | BN3: 0 | BO3: 750 | BP3: 3.04 | BQ3: 97.5 | BR3: 0 | BS3: =SUM(BI3:BR3) -> 6539.61 | BU3: 276.52 | BV3: =(BD3/$BD$116)*21083.85 -> 330.21082 | BW3: =(BE3/$O$116)*12925.76 -> 0 | BY3: 20 | CA3: 5 | CB3: =37537.5/96 -> 391.01562 | CD3: =SUM(BT3:CC3) -> 1022.7464 | CE3: =63860.36/96 -> 665.21208 | CG3: =(CE3+CF3)*30% -> 199.56363 | CH3: =SUM(CE3:CG3) -> 864.77571 | CI3: =CD3+CH3 -> 1887.5221 | CJ3: =BS3-CI3 -> 4652.0879 | CK3: 22187.93 | CL3: 9297.55 | CM3: 0 | CN3: 0 | CO3: 0 | CP3: 0 | CQ3: 13043.52 | CR3: 23.6 | CS3: 1586.68 | CT3: 0 | CU3: 46139.28 | CV3: 0 | CW3: 1895 | CX3: MOVE S320 | CY3: =SUM(CK3:CT3) -> 46139.28 | CZ3: 1846.95 | DA3: 4357.14 | DB3: 0 | DC3: 0 | DD3: 0 | DE3: 0 | DF3: 750 | DG3: 1.64 | DH3: 88.11 | DI3: 0 | DJ3: =SUM(CZ3:DI3) -> 7043.84 | DM3: =(CU3/$CU$116)*24055.75 -> 501.59846 | DN3: =(CV3/$O$116)*16258.02 -> 0 | DP3: 20 | DR3: 5 | DS3: =42418.5/99 -> 428.4697 | DU3: =SUM(DK3:DT3) -> 955.06815 | DV3: =59038.72/99 -> 596.35071 | DX3: =(DV3+DW3)*30% -> 178.90521 | DY3: =SUM(DV3:DX3) -> 775.25592 | DZ3: =DU3+DY3 -> 1730.3241 | EA3: =DJ3-DZ3 -> 5313.5159 | EB3: 14559.71 | EC3: 10885.16 | ED3: 0 | EE3: 0 | EF3: 0 | EG3: 0 | EH3: 14262.2 | EI3: 0 | EJ3: 2111.15 | EK3: 0 | EL3: 41818.22 | EM3: 0 | EN3: 2010 | EO3: MOVE S320 | EP3: =SUM(EB3:EK3) -> 41818.22 | EQ3: 1211.97 | ER3: 4357.14 | ES3: 0 | ET3: 0 | EU3: 0 | EV3: 0 | EW3: 750 | EX3: 0 | EY3: 117.29 | EZ3: 0 | FA3: =SUM(EQ3:EZ3) -> 6436.4 | FB3: 1134.23 | FC3: 276.52 | FD3: =(EL3/$EL$116)*26325.65 -> 466.7771 | FE3: =(EM3/$O$116)*14846.27 -> 0 | FF3: =52000/60 -> 866.66667 | FG3: 20 | FH3: =14375.2/102 -> 140.93333 | FI3: 5 | FJ3: =43317.38/102 -> 424.6802 | FL3: =SUM(FB3:FK3) -> 3334.8073 | FM3: =67770.74/102 -> 664.41902 | FO3: =(FM3+FN3)*30% -> 199.32571 | FP3: =SUM(FM3:FO3) -> 863.74473 | FQ3: =FL3+FP3 -> 4198.552 | FR3: =FA3-FQ3 -> 2237.848 | FS3: 21194.7 | FT3: 15063.19 | FU3: 0 | FV3: 0 | FW3: 0 | FX3: 0 | FY3: 18929.76 | FZ3: 0 | GA3: 3567.38 | GB3: 0 | GC3: 58755.03 | GD3: 0 | GE3: 2715 | GF3: MOVE S320 | GG3: =SUM(FS3:GB3) -> 58755.03 | GH3: 1764.28 | GI3: 4357.14 | GJ3: 0 | GK3: 0 | GL3: 0 | GM3: 0 | GN3: 750 | GO3: 0 | GP3: 198.13 | GQ3: 0 | GR3: =SUM(GH3:GQ3) -> 7069.55 | GS3: 1134.23 | GT3: 276.52 | GU3: =(GC3/$GC$116)*30198.86 -> 651.07886 | GV3: =(GD3/$O$116)*16844.27 -> 0 | GW3: =52000/60 -> 866.66667 | GX3: 20 | GY3: =18860.4/102 -> 184.90588 | GZ3: 5 | HA3: =36564.75/102 -> 358.47794 | HC3: =SUM(GS3:HB3) -> 3496.8793 | HD3: =88425.86/102 -> 866.9202 | HF3: =(HD3+HE3)*30% -> 260.07606 | HG3: =SUM(HD3:HF3) -> 1126.9963 | HH3: =HC3+HG3 -> 4623.8756 | HI3: =GR3-HH3 -> 2445.6744 | HJ3: 24995.47 | HK3: 15777.34 | HL3: 7.8 | HM3: 0 | HN3: 0 | HO3: 0 | HP3: 19587.2 | HQ3: 11.56 | HR3: 2396.51 | HS3: 0 | HT3: 62775.88 | HU3: 0 | HV3: 2924 | HW3: MOVE S320 | HX3: =SUM(HJ3:HS3) -> 62775.88 | HY3: 2080.65 | HZ3: 4357.14 | IA3: 0.5 | IB3: 0 | IC3: 0 | ID3: 0 | IE3: 750 | IF3: 0.8 | IG3: 133.02 | IH3: 0 | II3: =SUM(HY3:IH3) -> 7322.11 | IJ3: 1134.23 | IK3: 276.52 | IL3: =(HT3/$HT$116)*31846.83 -> 695.3971 | IM3: =(HU3/$O$116)*17321.85 -> 0 | IN3: =52000/60 -> 866.66667 | IO3: 20 | IP3: =24366/105 -> 232.05714 | IQ3: 5 | IR3: =46791/105 -> 445.62857 | IT3: =SUM(IJ3:IS3) -> 3675.4995 | IU3: =56573.45/105 -> 538.79476 | IW3: =(IU3+IV3)*30% -> 161.63843 | IX3: =SUM(IU3:IW3) -> 700.43319 | IY3: =IT3+IX3 -> 4375.9327 | IZ3: =II3-IY3 -> 2946.1773 | JA3: 23605.13 | JB3: 13430.65 | JC3: 23.2 | JD3: 0 | JE3: 0 | JF3: 0 | JG3: 21822.71 | JH3: 0 | JI3: 3176.16 | JJ3: 0 | JK3: 62057.85 | JL3: 0 | JM3: 2810 | JN3: MOVE S320 | JO3: =SUM(JA3:JJ3) -> 62057.85 | JP3: 1964.91 | JQ3: 4357.14 | JR3: 1.48 | JS3: 0 | JT3: 0 | JU3: 0 | JV3: 750 | JW3: 0 | JX3: 176.28 | JY3: 0 | JZ3: =SUM(JP3:JY3) -> 7249.81 | KA3: 1134.23 | KB3: 276.52 | KC3: =(JK3/$N$116)*39010.72 -> 1251.7495 | KD3: =(JL3/$O$116)*19244.4 -> 0 | KE3: =52000/60 -> 866.66667 | KF3: 20 | KH3: 5 | KI3: =58143.75/107 -> 543.39953 | KK3: =SUM(KA3:KJ3) -> 4097.5657 | KL3: =53213.34/107 -> 497.32093 | KN3: =(KL3+KM3)*30% -> 149.19628 | KO3: =SUM(KL3:KN3) -> 646.51721 | KP3: =KK3+KO3 -> 4744.0829 | KQ3: =JZ3-KP3 -> 2505.7271 | KR3: 29275.9 | KS3: 16605.75 | KT3: 0 | KU3: 0 | KV3: 0 | KW3: 0 | KX3: 23503.26 | KY3: 123.7 | KZ3: 3051.23 | LA3: 0 | LB3: 72559.84 | LC3: 0 | LD3: 2982 | LE3: MOVE S320 | LF3: =SUM(KR3:LA3) -> 72559.84 | LG3: 2436.94 | LH3: 4357.14 | LI3: 0 | LJ3: 0 | LK3: 0 | LL3: 0 | LM3: 750 | LN3: 8.59 | LO3: 169.35 | LP3: 0 | LQ3: =SUM(LG3:LP3) -> 7722.02 | LR3: 1134.23 | LS3: 264 | LT3: =(LB3/$LB$116)*39133.48 -> 739.75685 | LU3: =(LC3/$O$116)*17015.75 -> 0 | LV3: =52000/60 -> 866.66667 | LW3: 20 | LY3: 5 | LZ3: =54360/107 -> 508.03738 | MB3: =SUM(LR3:MA3) -> 3537.6909 | MC3: =63509.75/107 -> 593.54907 | ME3: =(MC3+MD3)*30% -> 178.06472 | MF3: =SUM(MC3:ME3) -> 771.61379 | MG3: =MB3+MF3 -> 4309.3047 | MH3: =LQ3-MG3 -> 3412.7153 | MI3: 23943.49 | MJ3: 12050.12 | MK3: 0 | ML3: 0 | MM3: 0 | MN3: 0 | MO3: 21215.44 | MP3: 0 | MQ3: 1955.61 | MR3: 0 | MS3: 59164.66 | MT3: 0 | MU3: 2608 | MV3: MOVE S320 | MW3: =SUM(MI3:MR3) -> 59164.66 | MX3: 1993.08 | MY3: 4357.14 | MZ3: 0 | NA3: 0 | NB3: 0 | NC3: 0 | ND3: 750 | NE3: 0 | NF3: 108.64 | NG3: 0 | NH3: =SUM(MX3:NG3) -> 7208.86 | NI3: 1134.23 | NJ3: 264 | NK3: =(MS3/$N$116)*0 -> 0 | NL3: =(MT3/$O$116)*13804.26 -> 0 | NM3: =52000/60 -> 866.66667 | NN3: 20 | NP3: 5 | NQ3: =51195/109 -> 469.6789 | NS3: =SUM(NI3:NR3) -> 2759.5756 | NT3: =78812.25/109 -> 723.04817 | NV3: =(NT3+NU3)*30% -> 216.91445 | NW3: =SUM(NT3:NV3) -> 939.96261 | NX3: =NS3+NW3 -> 3699.5382 | NY3: =NH3-NX3 -> 3509.3218 | NZ3: 21543.12 | OA3: 11947.08 | OB3: 0 | OC3: 0 | OD3: 0 | OE3: 0 | OF3: 21862.42 | OG3: 11.12 | OH3: 2000.44 | OI3: 0 | OJ3: 57364.18 | OK3: =ON3-OJ3 -> 0 | OL3: 2783 | OM3: MOVE S320 | ON3: =SUM(NZ3:OI3) -> 57364.18 | OO3: 1793.27 | OP3: 4357.14 | OQ3: 0 | OR3: 0 | OS3: 0 | OT3: 0 | OU3: 750 | OV3: 0.77 | OW3: 111.14 | OX3: 0 | OY3: =SUM(OO3:OX3) -> 7012.32 | OZ3: 1134.23 | PA3: 264 | PB3: =(OJ3/$OJ$116)*56307.47 -> 1240.4006 | PC3: =(OK3/$O$116)*16757.91 -> 0 | PD3: =52000/60 -> 866.66667 | PE3: 20 | PF3: =3288/100 -> 32.88 | PG3: 5 | PH3: =54472.54/110 -> 495.20491 | PJ3: =SUM(OZ3:PI3) -> 4058.3822 | PK3: =70758.13/110 -> 643.25573 | PM3: =(PK3+PL3)*30% -> 192.97672 | PN3: =SUM(PK3:PM3) -> 836.23245 | PO3: =PJ3+PN3 -> 4894.6146 | PP3: =OY3-PO3 -> 2117.7054 | PQ3: 17457.73 | PR3: 11118.41 | PS3: 0 | PT3: 0 | PU3: 0 | PV3: 0 | PW3: 17458.67 | PX3: 0 | PY3: 1963.77 | PZ3: 11.2 | QA3: 48009.78 | QB3: 0 | QC3: 2415 | QD3: MOVE S320 | QE3: =SUM(PQ3:PZ3) -> 48009.78 | QF3: 1453.2 | QG3: 4357.14 | QH3: 0 | QI3: 0 | QJ3: 0 | QK3: 0 | QL3: 750 | QM3: 0 | QN3: 109.1 | QO3: 0.62 | QP3: =SUM(QF3:QO3) -> 6670.06 | QQ3: 1134.23 | QR3: 264 | QS3: =(QA3/$QA$116)*27743.06 -> 564.35525 | QT3: =(QB3/$O$116)*10429.01 -> 0 | QU3: =52000/60 -> 866.66667 | QV3: 20 | QW3: =2074.8/110 -> 18.861818 | QX3: 5 | QY3: =47096.25/110 -> 428.14773 | RA3: =SUM(QQ3:QZ3) -> 3301.2615 | RB3: =68119.05/110 -> 619.26409 | RD3: =(RB3+RC3)*30% -> 185.77923 | RE3: =SUM(RB3:RD3) -> 805.04332 | RF3: =RA3+RE3 -> 4106.3048 | RG3: =QP3-RF3 -> 2563.7552 | RH3: 22439.51 | RI3: 13094.7 | RJ3: 0 | RK3: 0 | RL3: 0 | RM3: 0 | RN3: 18726.04 | RO3: 0 | RP3: 1695.5 | RQ3: 0 | RR3: 55955.75 | RS3: 0 | RT3: 2503 | RU3: MOVE S320 | RV3: =SUM(RH3:RQ3) -> 55955.75 | RW3: 1867.88 | RX3: 4357.14 | RY3: 0 | RZ3: 0 | SA3: 0 | SB3: 0 | SC3: 750 | SD3: 0 | SE3: 94.2 | SF3: 0 | SG3: 6319.22 | SH3: 1134.23 | SI3: 264 | SJ3: =(RR3/$RR$116)*25115.94 -> 549.8719 | SK3: =(RS3/$O$116)*12319.54 -> 0 | SL3: =52000/60 -> 866.66667 | SM3: 20 | SN3: =56040/113 -> 495.9292 | SO3: 5 | SP3: =48423.75/113 -> 428.52876 | SR3: =SUM(SH3:SQ3) -> 3764.2265 | SS3: =67380.17/113 -> 596.28469 | SU3: =(SS3+ST3)*30% -> 178.88541 | SV3: =SUM(SS3:SU3) -> 775.1701 | SW3: =SR3+SV3 -> 4539.3966 | SX3: =SG3-SW3 -> 1779.8234 | SY3: =Q3+BH3+CY3+EP3+GG3+HX3+JO3+LF3+MW3+ON3+QE3+RV3 -> 629162.69 | SZ3: =AB3+BS3+DJ3+FA3+GR3+II3+JZ3+LQ3+NH3+OY3+QP3+SG3 -> 83458.13 | TA3: =AR3+CI3+DZ3+FQ3+HH3+IY3+KP3+MG3+NX3+PO3+RF3+SW3 -> 45035.605 | TB3: =SZ3-TA3 -> 38422.525 | TF3: Legenda: 1. Do 5 000 PLN 2. 5 001 - 10 000 3. > 10 001 - do relokacji
A4: 1102 | B4: 1102_ZIELON | C4: MOVE S320 | D4: 3004.91 | E4: 7573.64 | F4: 0 | G4: 0 | H4: 0 | I4: 0 | J4: 0 | K4: 104.08 | L4: 0 | M4: 0 | N4: 10682.63 | O4: =Q4-N4 -> 0 | P4: 946 | Q4: =SUM(D4:M4) -> 10682.63 | R4: 250.14 | S4: 4357.14 | T4: 0 | U4: 0 | V4: 0 | W4: 0 | X4: 0 | Y4: 7.23 | Z4: 0 | AA4: 0 | AB4: =SUM(R4:AA4) -> 4614.51 | AE4: =(N4/$N$116)*21028.32 -> 116.15008 | AF4: =(O4/$O$116)*15324.97 -> 0 | AH4: 20 | AJ4: 5 | AK4: =39081.75/95 -> 411.38684 | AM4: =SUM(AC4:AL4) -> 552.53692 | AN4: =61284.58/95 -> 645.10084 | AO4: 0 | AP4: =(AN4+AO4)*30% -> 193.53025 | AQ4: =SUM(AN4:AP4) -> 838.63109 | AR4: =AM4+AQ4 -> 1391.168 | AS4: =AB4-AR4 -> 3223.342 | AT4: 3605.52 | AU4: 8367.5 | AV4: 46.8 | AW4: 0 | AX4: 0 | AY4: 0 | AZ4: 0 | BA4: 73.26 | BB4: 0 | BC4: 0 | BD4: 12093.08 | BE4: =BH4-BD4 -> 0 | BF4: 942 | BG4: MOVE S320 | BH4: =SUM(AT4:BC4) -> 12093.08 | BI4: 300.12 | BJ4: 4357.14 | BK4: 2.99 | BL4: 0 | BM4: 0 | BN4: 0 | BO4: 0 | BP4: 5.09 | BQ4: 0 | BR4: 0 | BS4: =SUM(BI4:BR4) -> 4665.34 | BV4: =(BD4/$BD$116)*21083.85 -> 132.63346 | BW4: =(BE4/$O$116)*12925.76 -> 0 | BY4: 20 | CA4: 5 | CB4: =37537.5/96 -> 391.01562 | CD4: =SUM(BT4:CC4) -> 548.64908 | CE4: =63860.36/96 -> 665.21208 | CG4: =(CE4+CF4)*30% -> 199.56363 | CH4: =SUM(CE4:CG4) -> 864.77571 | CI4: =CD4+CH4 -> 1413.4248 | CJ4: =BS4-CI4 -> 3251.9152 | CK4: 2945.03 | CL4: 9835.59 | CM4: 65.6 | CN4: 0 | CO4: 0 | CP4: 0 | CQ4: 0 | CR4: 1203.42 | CS4: 0 | CT4: 0 | CU4: 14049.64 | CV4: =CY4-CU4 -> 0 | CW4: 1096 | CX4: MOVE S320 | CY4: =SUM(CK4:CT4) -> 14049.64 | CZ4: 245.14 | DA4: 4357.14 | DB4: 4.19 | DC4: 0 | DD4: 0 | DE4: 0 | DF4: 0 | DG4: 83.57 | DH4: 0 | DI4: 0 | DJ4: =SUM(CZ4:DI4) -> 4690.04 | DM4: =(CU4/$CU$116)*24055.75 -> 152.73922 | DN4: =(CV4/$O$116)*16258.02 -> 0 | DP4: 20 | DR4: 5 | DS4: =DS$3 -> 428.4697 | DU4: =SUM(DK4:DT4) -> 606.20892 | DV4: =DV$3 -> 596.35071 | DX4: =(DV4+DW4)*30% -> 178.90521 | DY4: =SUM(DV4:DX4) -> 775.25592 | DZ4: =DU4+DY4 -> 1381.4648 | EA4: =DJ4-DZ4 -> 3308.5752 | EB4: 2810.03 | EC4: 9531 | ED4: 50.53 | EE4: 0 | EF4: 0 | EG4: 0 | EH4: 0 | EI4: 1827.56 | EJ4: 0 | EK4: 0 | EL4: 14219.12 | EM4: =EP4-EL4 -> 0 | EN4: 1080 | EO4: MOVE S320 | EP4: =SUM(EB4:EK4) -> 14219.12 | EQ4: 233.91 | ER4: 4357.14 | ES4: 3.23 | ET4: 0 | EU4: 0 | EV4: 0 | EW4: 0 | EX4: 126.84 | EY4: 0 | EZ4: 0 | FA4: =SUM(EQ4:EZ4) -> 4721.12 | FD4: =(EL4/$EL$116)*26325.65 -> 158.71454 | FE4: =(EM4/$O$116)*14846.27 -> 0 | FF4: =52000/60 -> 866.66667 | FG4: 20 | FH4: =14375.2/102 -> 140.93333 | FI4: 5 | FJ4: =FJ$3 -> 424.6802 | FL4: =SUM(FB4:FK4) -> 1615.9947 | FM4: =FM$3 -> 664.41902 | FO4: =(FM4+FN4)*30% -> 199.32571 | FP4: =SUM(FM4:FO4) -> 863.74473 | FQ4: =FL4+FP4 -> 2479.7395 | FR4: =FA4-FQ4 -> 2241.3805 | FS4: 2996.19 | FT4: 12995.38 | FU4: 0.3 | FV4: 0 | FW4: 0 | FX4: 0 | FY4: 0 | FZ4: 2550.82 | GA4: 0 | GB4: 0 | GC4: 18542.69 | GD4: =GG4-GC4 -> 0 | GE4: 1382 | GF4: MOVE S320 | GG4: =SUM(FS4:GB4) -> 18542.69 | GH4: 249.4 | GI4: 4357.14 | GJ4: 0.02 | GK4: 0 | GL4: 0 | GM4: 0 | GN4: 0 | GO4: 176.71 | GP4: 0 | GQ4: 0 | GR4: =SUM(GH4:GQ4) -> 4783.27 | GU4: =(GC4/$GC$116)*30198.86 -> 205.47608 | GV4: =(GD4/$O$116)*16844.27 -> 0 | GW4: =52000/60 -> 866.66667 | GX4: 20 | GY4: =18860.4/102 -> 184.90588 | GZ4: 5 | HA4: =HA$3 -> 358.47794 | HC4: =SUM(GS4:HB4) -> 1640.5266 | HD4: =HD$3 -> 866.9202 | HF4: =(HD4+HE4)*30% -> 260.07606 | HG4: =SUM(HD4:HF4) -> 1126.9963 | HH4: =HC4+HG4 -> 2767.5228 | HI4: =GR4-HH4 -> 2015.7472 | HJ4: 5532.5 | HK4: 14804.05 | HL4: 0 | HM4: 0 | HN4: 0 | HO4: 0 | HP4: 0 | HQ4: 3062.04 | HR4: 0 | HS4: 0 | HT4: 23398.59 | HU4: =HX4-HT4 -> 0 | HV4: 1486 | HW4: MOVE S320 | HX4: =SUM(HJ4:HS4) -> 23398.59 | HY4: 460.53 | HZ4: 4357.14 | IA4: 0 | IB4: 0 | IC4: 0 | ID4: 0 | IE4: 0 | IF4: 212.64 | IG4: 0 | IH4: 0 | II4: =SUM(HY4:IH4) -> 5030.31 | IL4: =(HT4/$HT$116)*31846.83 -> 259.19687 | IM4: =(HU4/$O$116)*17321.85 -> 0 | IN4: =52000/60 -> 866.66667 | IO4: 20 | IP4: =24366/105 -> 232.05714 | IQ4: 5 | IR4: =IR$3 -> 445.62857 | IT4: =SUM(IJ4:IS4) -> 1828.5493 | IU4: =IU$3 -> 538.79476 | IW4: =(IU4+IV4)*30% -> 161.63843 | IX4: =SUM(IU4:IW4) -> 700.43319 | IY4: =IT4+IX4 -> 2528.9824 | IZ4: =II4-IY4 -> 2501.3276 | JA4: 6865.6 | JB4: 16029.97 | JC4: 71.76 | JD4: 0 | JE4: 0 | JF4: 0 | JG4: 0 | JH4: 3608.09 | JI4: 0 | JJ4: 0 | JK4: 26575.42 | JL4: =JO4-JK4 -> 0 | JM4: 1463 | JN4: MOVE S320 | JO4: =SUM(JA4:JJ4) -> 26575.42 | JP4: 571.5 | JQ4: 4357.14 | JR4: 4.58 | JS4: 0 | JT4: 0 | JU4: 0 | JV4: 0 | JW4: 250.34 | JX4: 0 | JY4: 0 | JZ4: =SUM(JP4:JY4) -> 5183.56 | KC4: =(JK4/$N$116)*39010.72 -> 536.0445 | KD4: =(JL4/$O$116)*19244.4 -> 0 | KE4: =52000/60 -> 866.66667 | KF4: 20 | KH4: 5 | KI4: =KI$3 -> 543.39953 | KK4: =SUM(KA4:KJ4) -> 1971.1107 | KL4: =KL$3 -> 497.32093 | KN4: =(KL4+KM4)*30% -> 149.19628 | KO4: =SUM(KL4:KN4) -> 646.51721 | KP4: =KK4+KO4 -> 2617.6279 | KQ4: =JZ4-KP4 -> 2565.9321 | KR4: 3897.22 | KS4: 12726.13 | KT4: 0.33 | KU4: 0 | KV4: 0 | KW4: 0 | KX4: 0 | KY4: 2710.18 | KZ4: 0 | LA4: 0 | LB4: 19333.86 | LC4: =LF4-LB4 -> 0 | LD4: 1129 | LE4: MOVE S320 | LF4: =SUM(KR4:LA4) -> 19333.86 | LG4: 324.41 | LH4: 4357.14 | LI4: 0.02 | LJ4: 0 | LK4: 0 | LL4: 0 | LM4: 0 | LN4: 188.2 | LO4: 0 | LP4: 0 | LQ4: =SUM(LG4:LP4) -> 4869.77 | LT4: =(LB4/$LB$116)*39133.48 -> 197.11118 | LU4: =(LC4/$O$116)*17015.75 -> 0 | LV4: =52000/60 -> 866.66667 | LW4: 20 | LY4: 5 | LZ4: =LZ$3 -> 508.03738 | MB4: =SUM(LR4:MA4) -> 1596.8152 | MC4: =MC$3 -> 593.54907 | ME4: =(MC4+MD4)*30% -> 178.06472 | MF4: =SUM(MC4:ME4) -> 771.61379 | MG4: =MB4+MF4 -> 2368.429 | MH4: =LQ4-MG4 -> 2501.341 | MI4: 3140.04 | MJ4: 11867.23 | MK4: 23.6 | ML4: 0 | MM4: 0 | MN4: 0 | MO4: 0 | MP4: 2587.64 | MQ4: 0 | MR4: 0 | MS4: 17618.51 | MT4: =MW4-MS4 -> 0 | MU4: 1118 | MV4: MOVE S320 | MW4: =SUM(MI4:MR4) -> 17618.51 | MX4: 261.38 | MY4: 4357.14 | MZ4: 1.51 | NA4: 0 | NB4: 0 | NC4: 0 | ND4: 0 | NE4: 179.69 | NF4: 0 | NG4: 0 | NH4: =SUM(MX4:NG4) -> 4799.72 | NK4: =(MS4/$N$116)*0 -> 0 | NL4: =(MT4/$O$116)*13804.26 -> 0 | NM4: =52000/60 -> 866.66667 | NN4: 20 | NP4: 5 | NQ4: =NQ$3 -> 469.6789 | NS4: =SUM(NI4:NR4) -> 1361.3456 | NT4: =78812.25/109 -> 723.04817 | NV4: =(NT4+NU4)*30% -> 216.91445 | NW4: =SUM(NT4:NV4) -> 939.96261 | NX4: =NS4+NW4 -> 2301.3082 | NY4: =NH4-NX4 -> 2498.4118 | NZ4: 2807.67 | OA4: 11656.4 | OB4: 0 | OC4: 0 | OD4: 0 | OE4: 0 | OF4: 0 | OG4: 2302.7 | OH4: 0 | OI4: 0 | OJ4: 16766.77 | OK4: =ON4-OJ4 -> 0 | OL4: 1122 | OM4: MOVE S320 | ON4: =SUM(NZ4:OI4) -> 16766.77 | OO4: 233.71 | OP4: 4357.14 | OQ4: 0 | OR4: 0 | OS4: 0 | OT4: 0 | OU4: 0 | OV4: 159.84 | OW4: 0 | OX4: 0 | OY4: =SUM(OO4:OX4) -> 4750.69 | PB4: =(OJ4/$OJ$116)*56307.47 -> 362.55224 | PC4: =(OK4/$O$116)*16757.91 -> 0 | PD4: =52000/60 -> 866.66667 | PE4: 20 | PF4: =3288/100 -> 32.88 | PG4: 5 | PH4: =PH$3 -> 495.20491 | PJ4: =SUM(OZ4:PI4) -> 1782.3038 | PK4: =PK$3 -> 643.25573 | PM4: =(PK4+PL4)*30% -> 192.97672 | PN4: =SUM(PK4:PM4) -> 836.23245 | PO4: =PJ4+PN4 -> 2618.5363 | PP4: =OY4-PO4 -> 2132.1537 | PQ4: 3194.22 | PR4: 9621.9 | PS4: 0 | PT4: 0 | PU4: 0 | PV4: 0 | PW4: 0 | PX4: 2130.72 | PY4: 0 | PZ4: 0 | QA4: 14946.84 | QB4: =QE4-QA4 -> 0 | QC4: 1000 | QD4: MOVE S320 | QE4: =SUM(PQ4:PZ4) -> 14946.84 | QF4: 265.88 | QG4: 4357.14 | QH4: 0 | QI4: 0 | QJ4: 0 | QK4: 0 | QL4: 0 | QM4: 147.96 | QN4: 0 | QO4: 0 | QP4: =SUM(QF4:QO4) -> 4770.98 | QS4: =(QA4/$QA$116)*27743.06 -> 175.70019 | QT4: =(QB4/$O$116)*10429.01 -> 0 | QU4: =52000/60 -> 866.66667 | QV4: 20 | QW4: =2074.8/110 -> 18.861818 | QX4: 5 | QY4: =QY$3 -> 428.14773 | RA4: =SUM(QQ4:QZ4) -> 1514.3764 | RB4: =68119.05/110 -> 619.26409 | RD4: =(RB4+RC4)*30% -> 185.77923 | RE4: =SUM(RB4:RD4) -> 805.04332 | RF4: =RA4+RE4 -> 2319.4197 | RG4: =QP4-RF4 -> 2451.5603 | RH4: 3073.98 | RI4: 9290.41 | RJ4: 11.19 | RK4: 0 | RL4: 0 | RM4: 0 | RN4: 0 | RO4: 3264.45 | RP4: 0 | RQ4: 0 | RR4: 15640.03 | RS4: =RV4-RR4 -> 0 | RT4: 1056 | RU4: MOVE S320 | RV4: =SUM(RH4:RQ4) -> 15640.03 | RW4: 255.88 | RX4: 4357.14 | RY4: 0.71 | RZ4: 0 | SA4: 0 | SB4: 0 | SC4: 0 | SD4: 226.7 | SE4: 0 | SF4: 0 | SG4: 4840.43 | SJ4: =(RR4/$RR$116)*25115.94 -> 153.69311 | SK4: =(RS4/$O$116)*12319.54 -> 0 | SL4: =52000/60 -> 866.66667 | SM4: 20 | SN4: =56040/113 -> 495.9292 | SO4: 5 | SP4: =SP$3 -> 428.52876 | SR4: =SUM(SH4:SQ4) -> 1969.8177 | SS4: =SS$3 -> 596.28469 | SU4: =(SS4+ST4)*30% -> 178.88541 | SV4: =SUM(SS4:SU4) -> 775.1701 | SW4: =SR4+SV4 -> 2744.9878 | SX4: =SG4-SW4 -> 2095.4422 | SY4: =Q4+BH4+CY4+EP4+GG4+HX4+JO4+LF4+MW4+ON4+QE4+RV4 -> 203867.18 | SZ4: =AB4+BS4+DJ4+FA4+GR4+II4+JZ4+LQ4+NH4+OY4+QP4+SG4 -> 57719.74 | TA4: =AR4+CI4+DZ4+FQ4+HH4+IY4+KP4+MG4+NX4+PO4+RF4+SW4 -> 26932.611 | TB4: =SZ4-TA4 -> 30787.129
A5: 1103 | B5: 1103_Wroc_GL | C5: MOVE S320 | D5: 5068.1 | E5: 4329.42 | F5: 0 | G5: 0 | H5: 0 | I5: 0 | J5: 0 | K5: 13349.66 | L5: 0 | M5: 0 | N5: 22747.18 | O5: =Q5-N5 -> 0 | P5: 1362 | Q5: =SUM(D5:M5) -> 22747.18 | R5: 421.87 | S5: 4357.14 | T5: 0 | U5: 0 | V5: 0 | W5: 0 | X5: 0 | Y5: 500 | Z5: 0 | AA5: 0 | AB5: =SUM(R5:AA5) -> 5279.01 | AE5: =(N5/$N$116)*21028.32 -> 247.32549 | AF5: =(O5/$O$116)*15324.97 -> 0 | AH5: 20 | AJ5: 5 | AK5: =39081.75/95 -> 411.38684 | AM5: =SUM(AC5:AL5) -> 683.71233 | AN5: =61284.58/95 -> 645.10084 | AO5: 0 | AP5: =(AN5+AO5)*30% -> 193.53025 | AQ5: =SUM(AN5:AP5) -> 838.63109 | AR5: =AM5+AQ5 -> 1522.3434 | AS5: =AB5-AR5 -> 3756.6666 | AT5: 5822.44 | AU5: 4524.2 | AV5: 23.2 | AW5: 0 | AX5: 0 | AY5: 0 | AZ5: 0 | BA5: 11449.43 | BB5: 0 | BC5: 0 | BD5: 21819.27 | BE5: =BH5-BD5 -> 0 | BF5: 1201 | BG5: MOVE S320 | BH5: =SUM(AT5:BC5) -> 21819.27 | BI5: 484.67 | BJ5: 4357.14 | BK5: 1.48 | BL5: 0 | BM5: 0 | BN5: 0 | BO5: 0 | BP5: 500 | BQ5: 0 | BR5: 0 | BS5: =SUM(BI5:BR5) -> 5343.29 | BV5: =(BD5/$BD$116)*21083.85 -> 239.30754 | BW5: =(BE5/$O$116)*12925.76 -> 0 | BY5: 20 | CA5: 5 | CB5: =37537.5/96 -> 391.01562 | CD5: =SUM(BT5:CC5) -> 655.32316 | CE5: =63860.36/96 -> 665.21208 | CG5: =(CE5+CF5)*30% -> 199.56363 | CH5: =SUM(CE5:CG5) -> 864.77571 | CI5: =CD5+CH5 -> 1520.0989 | CJ5: =BS5-CI5 -> 3823.1911 | CK5: 5281.5 | CL5: 4108.62 | CM5: 51.98 | CN5: 0 | CO5: 0 | CP5: 0 | CQ5: 0 | CR5: 12765.15 | CS5: 0 | CT5: 0 | CU5: 22207.25 | CV5: =CY5-CU5 -> 0 | CW5: 1321 | CX5: MOVE S320 | CY5: =SUM(CK5:CT5) -> 22207.25 | CZ5: 439.65 | DA5: 4357.14 | DB5: 3.32 | DC5: 0 | DD5: 0 | DE5: 0 | DF5: 0 | DG5: 500 | DH5: 0 | DI5: 0 | DJ5: =SUM(CZ5:DI5) -> 5300.11 | DM5: =(CU5/$CU$116)*24055.75 -> 241.42384 | DN5: =(CV5/$O$116)*16258.02 -> 0 | DP5: 20 | DR5: 5 | DS5: =DS$3 -> 428.4697 | DU5: =SUM(DK5:DT5) -> 694.89354 | DV5: =DV$3 -> 596.35071 | DX5: =(DV5+DW5)*30% -> 178.90521 | DY5: =SUM(DV5:DX5) -> 775.25592 | DZ5: =DU5+DY5 -> 1470.1495 | EA5: =DJ5-DZ5 -> 3829.9605 | EB5: 5279.64 | EC5: 8643.66 | ED5: 0 | EE5: 0 | EF5: 0 | EG5: 0 | EH5: 0 | EI5: 20899.29 | EJ5: 10.5 | EK5: 0 | EL5: 34833.09 | EM5: =EP5-EL5 -> 0 | EN5: 2218 | EO5: MOVE S320 | EP5: =SUM(EB5:EK5) -> 34833.09 | EQ5: 439.48 | ER5: 4357.14 | ES5: 0 | ET5: 0 | EU5: 0 | EV5: 0 | EW5: 0 | EX5: 500 | EY5: 0.58 | EZ5: 0 | FA5: =SUM(EQ5:EZ5) -> 5297.2 | FD5: =(EL5/$EL$116)*26325.65 -> 388.80872 | FE5: =(EM5/$O$116)*14846.27 -> 0 | FF5: =52000/60 -> 866.66667 | FG5: 20 | FH5: =14375.2/102 -> 140.93333 | FI5: 5 | FJ5: =FJ$3 -> 424.6802 | FL5: =SUM(FB5:FK5) -> 1846.0889 | FM5: =FM$3 -> 664.41902 | FO5: =(FM5+FN5)*30% -> 199.32571 | FP5: =SUM(FM5:FO5) -> 863.74473 | FQ5: =FL5+FP5 -> 2709.8336 | FR5: =FA5-FQ5 -> 2587.3664 | FS5: 6749.64 | FT5: 8207.12 | FU5: 12.5 | FV5: 0 | FW5: 0 | FX5: 0 | FY5: 0 | FZ5: 23446.82 | GA5: 9.5 | GB5: 0 | GC5: 38425.58 | GD5: =GG5-GC5 -> 0 | GE5: 2447 | GF5: MOVE S320 | GG5: =SUM(FS5:GB5) -> 38425.58 | GH5: 561.84 | GI5: 4357.14 | GJ5: 0.8 | GK5: 0 | GL5: 0 | GM5: 0 | GN5: 0 | GO5: 500 | GP5: 0.53 | GQ5: 0 | GR5: =SUM(GH5:GQ5) -> 5420.31 | GU5: =(GC5/$GC$116)*30198.86 -> 425.80325 | GV5: =(GD5/$O$116)*16844.27 -> 0 | GW5: =52000/60 -> 866.66667 | GX5: 20 | GY5: =18860.4/102 -> 184.90588 | GZ5: 5 | HA5: =HA$3 -> 358.47794 | HC5: =SUM(GS5:HB5) -> 1860.8537 | HD5: =HD$3 -> 866.9202 | HF5: =(HD5+HE5)*30% -> 260.07606 | HG5: =SUM(HD5:HF5) -> 1126.9963 | HH5: =HC5+HG5 -> 2987.85 | HI5: =GR5-HH5 -> 2432.46 | HJ5: 9014.14 | HK5: 10080.59 | HL5: 0 | HM5: 0 | HN5: 0 | HO5: 0 | HP5: 0 | HQ5: 25746.15 | HR5: 13.4 | HS5: 0 | HT5: 44854.28 | HU5: =HX5-HT5 -> 0 | HV5: 2817 | HW5: MOVE S320 | HX5: =SUM(HJ5:HS5) -> 44854.28 | HY5: 750.34 | HZ5: 4357.14 | IA5: 0 | IB5: 0 | IC5: 0 | ID5: 0 | IE5: 0 | IF5: 500 | IG5: 0.74 | IH5: 0 | II5: =SUM(HY5:IH5) -> 5608.22 | IL5: =(HT5/$HT$116)*31846.83 -> 496.87135 | IM5: =(HU5/$O$116)*17321.85 -> 0 | IN5: =52000/60 -> 866.66667 | IO5: 20 | IP5: =24366/105 -> 232.05714 | IQ5: 5 | IR5: =IR$3 -> 445.62857 | IT5: =SUM(IJ5:IS5) -> 2066.2237 | IU5: =IU$3 -> 538.79476 | IW5: =(IU5+IV5)*30% -> 161.63843 | IX5: =SUM(IU5:IW5) -> 700.43319 | IY5: =IT5+IX5 -> 2766.6569 | IZ5: =II5-IY5 -> 2841.5631 | JA5: 10188.03 | JB5: 11832.8 | JC5: 63.7 | JD5: 0 | JE5: 0 | JF5: 0 | JG5: 0 | JH5: 28091.9 | JI5: 5.7 | JJ5: 0 | JK5: 50182.13 | JL5: =JO5-JK5 -> 0 | JM5: 3028 | JN5: MOVE S320 | JO5: =SUM(JA5:JJ5) -> 50182.13 | JP5: 848.07 | JQ5: 4357.14 | JR5: 4.07 | JS5: 0 | JT5: 0 | JU5: 0 | JV5: 0 | JW5: 500 | JX5: 0.32 | JY5: 0 | JZ5: =SUM(JP5:JY5) -> 5709.6 | KC5: =(JK5/$N$116)*39010.72 -> 1012.2081 | KD5: =(JL5/$O$116)*19244.4 -> 0 | KE5: =52000/60 -> 866.66667 | KF5: 20 | KH5: 5 | KI5: =KI$3 -> 543.39953 | KK5: =SUM(KA5:KJ5) -> 2447.2743 | KL5: =KL$3 -> 497.32093 | KN5: =(KL5+KM5)*30% -> 149.19628 | KO5: =SUM(KL5:KN5) -> 646.51721 | KP5: =KK5+KO5 -> 3093.7915 | KQ5: =JZ5-KP5 -> 2615.8085 | KR5: 9228.85 | KS5: 10501.58 | KT5: 0 | KU5: 0 | KV5: 0 | KW5: 0 | KX5: 0 | KY5: 26614.04 | KZ5: 36.58 | LA5: 0 | LB5: 46381.05 | LC5: =LF5-LB5 -> 0 | LD5: 2696 | LE5: MOVE S320 | LF5: =SUM(KR5:LA5) -> 46381.05 | LG5: 768.23 | LH5: 4357.14 | LI5: 0 | LJ5: 0 | LK5: 0 | LL5: 0 | LM5: 0 | LN5: 500 | LO5: 2.03 | LP5: 0 | LQ5: =SUM(LG5:LP5) -> 5627.4 | LT5: =(LB5/$LB$116)*39133.48 -> 472.86074 | LU5: =(LC5/$O$116)*17015.75 -> 0 | LV5: =52000/60 -> 866.66667 | LW5: 20 | LY5: 5 | LZ5: =LZ$3 -> 508.03738 | MB5: =SUM(LR5:MA5) -> 1872.5648 | MC5: =MC$3 -> 593.54907 | ME5: =(MC5+MD5)*30% -> 178.06472 | MF5: =SUM(MC5:ME5) -> 771.61379 | MG5: =MB5+MF5 -> 2644.1786 | MH5: =LQ5-MG5 -> 2983.2214 | MI5: 6936.63 | MJ5: 6214.75 | MK5: 50.7 | ML5: 0 | MM5: 0 | MN5: 0 | MO5: 0 | MP5: 15366.45 | MQ5: 0 | MR5: 0 | MS5: 28568.53 | MT5: =MW5-MS5 -> 0 | MU5: 1719 | MV5: MOVE S320 | MW5: =SUM(MI5:MR5) -> 28568.53 | MX5: 577.42 | MY5: 4357.14 | MZ5: 3.24 | NA5: 0 | NB5: 0 | NC5: 0 | ND5: 0 | NE5: 500 | NF5: 0 | NG5: 0 | NH5: =SUM(MX5:NG5) -> 5437.8 | NK5: =(MS5/$N$116)*0 -> 0 | NL5: =(MT5/$O$116)*13804.26 -> 0 | NM5: =52000/60 -> 866.66667 | NN5: 20 | NP5: 5 | NQ5: =NQ$3 -> 469.6789 | NS5: =SUM(NI5:NR5) -> 1361.3456 | NT5: =78812.25/109 -> 723.04817 | NV5: =(NT5+NU5)*30% -> 216.91445 | NW5: =SUM(NT5:NV5) -> 939.96261 | NX5: =NS5+NW5 -> 2301.3082 | NY5: =NH5-NX5 -> 3136.4918 | NZ5: 6437.15 | OA5: 7662.91 | OB5: 18 | OC5: 0 | OD5: 0 | OE5: 0 | OF5: 0 | OG5: 18367.52 | OH5: 0 | OI5: 0 | OJ5: 32485.58 | OK5: =ON5-OJ5 -> 0 | OL5: 2002 | OM5: MOVE S320 | ON5: =SUM(NZ5:OI5) -> 32485.58 | OO5: 535.85 | OP5: 4357.14 | OQ5: 1.15 | OR5: 0 | OS5: 0 | OT5: 0 | OU5: 0 | OV5: 500 | OW5: 0 | OX5: 0 | OY5: =SUM(OO5:OX5) -> 5394.14 | PB5: =(OJ5/$OJ$116)*56307.47 -> 702.44417 | PC5: =(OK5/$O$116)*16757.91 -> 0 | PD5: =52000/60 -> 866.66667 | PE5: 20 | PF5: =3288/100 -> 32.88 | PG5: 5 | PH5: =PH$3 -> 495.20491 | PJ5: =SUM(OZ5:PI5) -> 2122.1957 | PK5: =PK$3 -> 643.25573 | PM5: =(PK5+PL5)*30% -> 192.97672 | PN5: =SUM(PK5:PM5) -> 836.23245 | PO5: =PJ5+PN5 -> 2958.4282 | PP5: =OY5-PO5 -> 2435.7118 | PQ5: 4546.76 | PR5: 6333.92 | PS5: 0 | PT5: 0 | PU5: 0 | PV5: 0 | PW5: 0 | PX5: 14688.9 | PY5: 0 | PZ5: 0 | QA5: 25569.58 | QB5: =QE5-QA5 -> 0 | QC5: 1647 | QD5: MOVE S320 | QE5: =SUM(PQ5:PZ5) -> 25569.58 | QF5: 378.49 | QG5: 4357.14 | QH5: 0 | QI5: 0 | QJ5: 0 | QK5: 0 | QL5: 0 | QM5: 500 | QN5: 0 | QO5: 0 | QP5: =SUM(QF5:QO5) -> 5235.63 | QS5: =(QA5/$QA$116)*27743.06 -> 300.57056 | QT5: =(QB5/$O$116)*10429.01 -> 0 | QU5: =52000/60 -> 866.66667 | QV5: 20 | QW5: =2074.8/110 -> 18.861818 | QX5: 5 | QY5: =QY$3 -> 428.14773 | RA5: =SUM(QQ5:QZ5) -> 1639.2468 | RB5: =68119.05/110 -> 619.26409 | RD5: =(RB5+RC5)*30% -> 185.77923 | RE5: =SUM(RB5:RD5) -> 805.04332 | RF5: =RA5+RE5 -> 2444.2901 | RG5: =QP5-RF5 -> 2791.3399 | RH5: 5909.12 | RI5: 6935.55 | RJ5: 0 | RK5: 0 | RL5: 0 | RM5: 0 | RN5: 0 | RO5: 18831.14 | RP5: 0 | RQ5: 0 | RR5: 31675.81 | RS5: =RV5-RR5 -> 0 | RT5: 1905 | RU5: MOVE S320 | RV5: =SUM(RH5:RQ5) -> 31675.81 | RW5: 491.88 | RX5: 4357.14 | RY5: 0 | RZ5: 0 | SA5: 0 | SB5: 0 | SC5: 0 | SD5: 500 | SE5: 0 | SF5: 0 | SG5: 5349.02 | SJ5: =(RR5/$RR$116)*25115.94 -> 311.27521 | SK5: =(RS5/$O$116)*12319.54 -> 0 | SL5: =52000/60 -> 866.66667 | SM5: 20 | SN5: =56040/113 -> 495.9292 | SO5: 5 | SP5: =SP$3 -> 428.52876 | SR5: =SUM(SH5:SQ5) -> 2127.3998 | SS5: =SS$3 -> 596.28469 | SU5: =(SS5+ST5)*30% -> 178.88541 | SV5: =SUM(SS5:SU5) -> 775.1701 | SW5: =SR5+SV5 -> 2902.5699 | SX5: =SG5-SW5 -> 2446.4501 | SY5: =Q5+BH5+CY5+EP5+GG5+HX5+JO5+LF5+MW5+ON5+QE5+RV5 -> 399749.33 | SZ5: =AB5+BS5+DJ5+FA5+GR5+II5+JZ5+LQ5+NH5+OY5+QP5+SG5 -> 65001.73 | TA5: =AR5+CI5+DZ5+FQ5+HH5+IY5+KP5+MG5+NX5+PO5+RF5+SW5 -> 29321.499 | TB5: =SZ5-TA5 -> 35680.231
A6: 1104 | B6: 1104_POZN_GL | C6: MOVE S320 | D6: 19593.64 | E6: 15001.6 | F6: 29041.47 | G6: 0 | H6: 0 | I6: 0 | J6: 0 | K6: 20 | L6: 0 | M6: 0 | N6: 63656.71 | O6: =Q6-N6 -> 0 | P6: 2890 | Q6: =SUM(D6:M6) -> 63656.71 | R6: 1630.96 | S6: 4357.14 | T6: 1855.24 | U6: 0 | V6: 0 | W6: 0 | X6: 0 | Y6: 1.39 | Z6: 0 | AA6: 0 | AB6: =SUM(R6:AA6) -> 7844.73 | AE6: =(N6/$N$116)*21028.32 -> 692.12655 | AF6: =(O6/$O$116)*15324.97 -> 0 | AH6: 20 | AJ6: 5 | AK6: =39081.75/95 -> 411.38684 | AM6: =SUM(AC6:AL6) -> 1128.5134 | AN6: =61284.58/95 -> 645.10084 | AO6: 0 | AP6: =(AN6+AO6)*30% -> 193.53025 | AQ6: =SUM(AN6:AP6) -> 838.63109 | AR6: =AM6+AQ6 -> 1967.1445 | AS6: =AB6-AR6 -> 5877.5855 | AT6: 23181.8 | AU6: 17692.09 | AV6: 38843.4 | AW6: 0 | AX6: 0 | AY6: 0 | AZ6: 0 | BA6: 150.5 | BB6: 0 | BC6: 0 | BD6: 79867.79 | BE6: =BH6-BD6 -> 0 | BF6: 3553 | BG6: MOVE S320 | BH6: =SUM(AT6:BC6) -> 79867.79 | BI6: 1929.63 | BJ6: 4357.14 | BK6: 2480.81 | BL6: 0 | BM6: 0 | BN6: 0 | BO6: 0 | BP6: 10.45 | BQ6: 0 | BR6: 0 | BS6: =SUM(BI6:BR6) -> 8778.03 | BV6: =(BD6/$BD$116)*21083.85 -> 875.96718 | BW6: =(BE6/$O$116)*12925.76 -> 0 | BY6: 20 | CA6: 5 | CB6: =37537.5/96 -> 391.01562 | CD6: =SUM(BT6:CC6) -> 1291.9828 | CE6: =63860.36/96 -> 665.21208 | CG6: =(CE6+CF6)*30% -> 199.56363 | CH6: =SUM(CE6:CG6) -> 864.77571 | CI6: =CD6+CH6 -> 2156.7585 | CJ6: =BS6-CI6 -> 6621.2715 | CK6: 30296.94 | CL6: 18980.41 | CM6: 39562.45 | CN6: 0 | CO6: 0 | CP6: 0 | CQ6: 0 | CR6: 12.5 | CS6: 9.5 | CT6: 0 | CU6: 88861.8 | CV6: =CY6-CU6 -> 0 | CW6: 3916 | CX6: MOVE S320 | CY6: =SUM(CK6:CT6) -> 88861.8 | CZ6: 2521.88 | DA6: 4357.14 | DB6: 2527.27 | DC6: 0 | DD6: 0 | DE6: 0 | DF6: 0 | DG6: 0.87 | DH6: 0.53 | DI6: 0 | DJ6: =SUM(CZ6:DI6) -> 9407.69 | DM6: =(CU6/$CU$116)*24055.75 -> 966.05196 | DN6: =(CV6/$O$116)*16258.02 -> 0 | DP6: 20 | DR6: 5 | DS6: =DS$3 -> 428.4697 | DU6: =SUM(DK6:DT6) -> 1419.5217 | DV6: =DV$3 -> 596.35071 | DX6: =(DV6+DW6)*30% -> 178.90521 | DY6: =SUM(DV6:DX6) -> 775.25592 | DZ6: =DU6+DY6 -> 2194.7776 | EA6: =DJ6-DZ6 -> 7212.9124 | EB6: 33798.17 | EC6: 21952.12 | ED6: 39975.22 | EE6: 0 | EF6: 0 | EG6: 0 | EH6: 0 | EI6: 20.98 | EJ6: 8.38 | EK6: 0 | EL6: 95754.87 | EM6: =EP6-EL6 -> 0 | EN6: 4074 | EO6: MOVE S320 | EP6: =SUM(EB6:EK6) -> 95754.87 | EQ6: 2813.35 | ER6: 4357.14 | ES6: 2553.83 | ET6: 0 | EU6: 0 | EV6: 0 | EW6: 0 | EX6: 1.46 | EY6: 0.47 | EZ6: 0 | FA6: =SUM(EQ6:EZ6) -> 9726.25 | FD6: =(EL6/$EL$116)*26325.65 -> 1068.8207 | FE6: =(EM6/$O$116)*14846.27 -> 0 | FF6: =52000/60 -> 866.66667 | FG6: 20 | FH6: =14375.2/102 -> 140.93333 | FI6: 5 | FJ6: =FJ$3 -> 424.6802 | FL6: =SUM(FB6:FK6) -> 2526.1009 | FM6: =FM$3 -> 664.41902 | FO6: =(FM6+FN6)*30% -> 199.32571 | FP6: =SUM(FM6:FO6) -> 863.74473 | FQ6: =FL6+FP6 -> 3389.8457 | FR6: =FA6-FQ6 -> 6336.4043 | FS6: 38062.77 | FT6: 26012.15 | FU6: 49080 | FV6: 0 | FW6: 0 | FX6: 0 | FY6: 0 | FZ6: 82.9 | GA6: 0 | GB6: 0 | GC6: 113237.82 | GD6: =GG6-GC6 -> 0 | GE6: 4576 | GF6: MOVE S320 | GG6: =SUM(FS6:GB6) -> 113237.82 | GH6: 3168.34 | GI6: 4357.14 | GJ6: 3135.13 | GK6: 0 | GL6: 0 | GM6: 0 | GN6: 0 | GO6: 5.76 | GP6: 0 | GQ6: 0 | GR6: =SUM(GH6:GQ6) -> 10666.37 | GU6: =(GC6/$GC$116)*30198.86 -> 1254.816 | GV6: =(GD6/$O$116)*16844.27 -> 0 | GW6: =52000/60 -> 866.66667 | GX6: 20 | GY6: =18860.4/102 -> 184.90588 | GZ6: 5 | HA6: =HA$3 -> 358.47794 | HC6: =SUM(GS6:HB6) -> 2689.8665 | HD6: =HD$3 -> 866.9202 | HF6: =(HD6+HE6)*30% -> 260.07606 | HG6: =SUM(HD6:HF6) -> 1126.9963 | HH6: =HC6+HG6 -> 3816.8627 | HI6: =GR6-HH6 -> 6849.5073 | HJ6: 51202.69 | HK6: 27883.61 | HL6: 53104.79 | HM6: 0 | HN6: 16.94 | HO6: 0 | HP6: 0 | HQ6: 82.2 | HR6: 0 | HS6: 0 | HT6: 132290.23 | HU6: =HX6-HT6 -> 0 | HV6: 5105 | HW6: MOVE S320 | HX6: =SUM(HJ6:HS6) -> 132290.23 | HY6: 4262.12 | HZ6: 4357.14 | IA6: 3392.33 | IB6: 0 | IC6: 1.1 | ID6: 0 | IE6: 0 | IF6: 5.71 | IG6: 0 | IH6: 0 | II6: =SUM(HY6:IH6) -> 12018.4 | IL6: =(HT6/$HT$116)*31846.83 -> 1465.4393 | IM6: =(HU6/$O$116)*17321.85 -> 0 | IN6: =52000/60 -> 866.66667 | IO6: 20 | IP6: =24366/105 -> 232.05714 | IQ6: 5 | IR6: =IR$3 -> 445.62857 | IT6: =SUM(IJ6:IS6) -> 3034.7917 | IU6: =IU$3 -> 538.79476 | IW6: =(IU6+IV6)*30% -> 161.63843 | IX6: =SUM(IU6:IW6) -> 700.43319 | IY6: =IT6+IX6 -> 3735.2249 | IZ6: =II6-IY6 -> 8283.1751 | JA6: 48144.6 | JB6: 26704.36 | JC6: 55036.03 | JD6: 0 | JE6: 12 | JF6: 0 | JG6: 0 | JH6: 35.81 | JI6: 0 | JJ6: 0 | JK6: 129932.8 | JL6: =JO6-JK6 -> 0 | JM6: 4853 | JN6: MOVE S320 | JO6: =SUM(JA6:JJ6) -> 129932.8 | JP6: 4007.58 | JQ6: 4357.14 | JR6: 3515.46 | JS6: 0 | JT6: 0.78 | JU6: 0 | JV6: 0 | JW6: 2.49 | JX6: 0 | JY6: 0 | JZ6: =SUM(JP6:JY6) -> 11883.45 | KC6: =(JK6/$N$116)*39010.72 -> 2620.8339 | KD6: =(JL6/$O$116)*19244.4 -> 0 | KE6: =52000/60 -> 866.66667 | KF6: 20 | KH6: 5 | KI6: =KI$3 -> 543.39953 | KK6: =SUM(KA6:KJ6) -> 4055.9001 | KL6: =KL$3 -> 497.32093 | KN6: =(KL6+KM6)*30% -> 149.19628 | KO6: =SUM(KL6:KN6) -> 646.51721 | KP6: =KK6+KO6 -> 4702.4173 | KQ6: =JZ6-KP6 -> 7181.0327 | KR6: 44337.04 | KS6: 28952.16 | KT6: 50580.42 | KU6: 0 | KV6: 17.66 | KW6: 0 | KX6: 0 | KY6: 53.7 | KZ6: 0 | LA6: 0 | LB6: 123940.98 | LC6: =LF6-LB6 -> 0 | LD6: 4609 | LE6: MOVE S320 | LF6: =SUM(KR6:LA6) -> 123940.98 | LG6: 3690.62 | LH6: 4357.14 | LI6: 3230.57 | LJ6: 0 | LK6: 1.14 | LL6: 0 | LM6: 0 | LN6: 3.73 | LO6: 0 | LP6: 0 | LQ6: =SUM(LG6:LP6) -> 11283.2 | LT6: =(LB6/$LB$116)*39133.48 -> 1263.5941 | LU6: =(LC6/$O$116)*17015.75 -> 0 | LV6: =52000/60 -> 866.66667 | LW6: 20 | LY6: 5 | LZ6: =LZ$3 -> 508.03738 | MB6: =SUM(LR6:MA6) -> 2663.2982 | MC6: =MC$3 -> 593.54907 | ME6: =(MC6+MD6)*30% -> 178.06472 | MF6: =SUM(MC6:ME6) -> 771.61379 | MG6: =MB6+MF6 -> 3434.912 | MH6: =LQ6-MG6 -> 7848.288 | MI6: 28175.47 | MJ6: 20655.24 | MK6: 37457.45 | ML6: 0 | MM6: 0 | MN6: 0 | MO6: 0 | MP6: 36.1 | MQ6: 0 | MR6: 87.34 | MS6: 86411.6 | MT6: =MW6-MS6 -> 0 | MU6: 3648 | MV6: MOVE S320 | MW6: =SUM(MI6:MR6) -> 86411.6 | MX6: 2345.35 | MY6: 4357.14 | MZ6: 2392.52 | NA6: 0 | NB6: 0 | NC6: 0 | ND6: 0 | NE6: 2.51 | NF6: 0 | NG6: 4.85 | NH6: =SUM(MX6:NG6) -> 9102.37 | NK6: =(MS6/$N$116)*0 -> 0 | NL6: =(MT6/$O$116)*13804.26 -> 0 | NM6: =52000/60 -> 866.66667 | NN6: 20 | NP6: 5 | NQ6: =NQ$3 -> 469.6789 | NS6: =SUM(NI6:NR6) -> 1361.3456 | NT6: =78812.25/109 -> 723.04817 | NV6: =(NT6+NU6)*30% -> 216.91445 | NW6: =SUM(NT6:NV6) -> 939.96261 | NX6: =NS6+NW6 -> 2301.3082 | NY6: =NH6-NX6 -> 6801.0618 | NZ6: 30080.03 | OA6: 20011.16 | OB6: 43390.64 | OC6: 0 | OD6: 0 | OE6: 0 | OF6: 0 | OG6: 28.16 | OH6: 0 | OI6: 157.86 | OJ6: 93667.85 | OK6: =ON6-OJ6 -> 0 | OL6: 4078 | OM6: MOVE S320 | ON6: =SUM(NZ6:OI6) -> 93667.85 | OO6: 2503.88 | OP6: 4357.14 | OQ6: 2772.11 | OR6: 0 | OS6: 0 | OT6: 0 | OU6: 0 | OV6: 1.96 | OW6: 0 | OX6: 8.77 | OY6: =SUM(OO6:OX6) -> 9643.86 | PB6: =(OJ6/$OJ$116)*56307.47 -> 2025.4044 | PC6: =(OK6/$O$116)*16757.91 -> 0 | PD6: =52000/60 -> 866.66667 | PE6: 20 | PF6: =3288/100 -> 32.88 | PG6: 5 | PH6: =PH$3 -> 495.20491 | PJ6: =SUM(OZ6:PI6) -> 3445.1559 | PK6: =PK$3 -> 643.25573 | PM6: =(PK6+PL6)*30% -> 192.97672 | PN6: =SUM(PK6:PM6) -> 836.23245 | PO6: =PJ6+PN6 -> 4281.3884 | PP6: =OY6-PO6 -> 5362.4716 | PQ6: 25867.89 | PR6: 16386.24 | PS6: 37135.75 | PT6: 0 | PU6: 0 | PV6: 0 | PW6: 0 | PX6: 14.5 | PY6: 0 | PZ6: 504.45 | QA6: 79908.83 | QB6: =QE6-QA6 -> 0 | QC6: 3371 | QD6: MOVE S320 | QE6: =SUM(PQ6:PZ6) -> 79908.83 | QF6: 2153.26 | QG6: 4357.14 | QH6: 2372.46 | QI6: 0 | QJ6: 0 | QK6: 0 | QL6: 0 | QM6: 1.01 | QN6: 0 | QO6: 28.02 | QP6: =SUM(QF6:QO6) -> 8911.89 | QS6: =(QA6/$QA$116)*27743.06 -> 939.32877 | QT6: =(QB6/$O$116)*10429.01 -> 0 | QU6: =52000/60 -> 866.66667 | QV6: 20 | QW6: =2074.8/110 -> 18.861818 | QX6: 5 | QY6: =QY$3 -> 428.14773 | RA6: =SUM(QQ6:QZ6) -> 2278.005 | RB6: =68119.05/110 -> 619.26409 | RD6: =(RB6+RC6)*30% -> 185.77923 | RE6: =SUM(RB6:RD6) -> 805.04332 | RF6: =RA6+RE6 -> 3083.0483 | RG6: =QP6-RF6 -> 5828.8417 | RH6: 27450.72 | RI6: 17975.59 | RJ6: 37929.34 | RK6: 0 | RL6: 0 | RM6: 0 | RN6: 0 | RO6: 48.56 | RP6: 0 | RQ6: 495.07 | RR6: 83899.28 | RS6: =RV6-RR6 -> 0 | RT6: 3408 | RU6: MOVE S320 | RV6: =SUM(RH6:RQ6) -> 83899.28 | RW6: 2285.02 | RX6: 4357.14 | RY6: 2423.03 | RZ6: 0 | SA6: 0 | SB6: 0 | SC6: 0 | SD6: 3.37 | SE6: 0 | SF6: 27.5 | SG6: 9068.56 | SJ6: =(RR6/$RR$116)*25115.94 -> 824.47034 | SK6: =(RS6/$O$116)*12319.54 -> 0 | SL6: =52000/60 -> 866.66667 | SM6: 20 | SN6: =56040/113 -> 495.9292 | SO6: 5 | SP6: =SP$3 -> 428.52876 | SR6: =SUM(SH6:SQ6) -> 2640.595 | SS6: =SS$3 -> 596.28469 | SU6: =(SS6+ST6)*30% -> 178.88541 | SV6: =SUM(SS6:SU6) -> 775.1701 | SW6: =SR6+SV6 -> 3415.7651 | SX6: =SG6-SW6 -> 5652.7949 | SY6: =Q6+BH6+CY6+EP6+GG6+HX6+JO6+LF6+MW6+ON6+QE6+RV6 -> 1171430.6 | SZ6: =AB6+BS6+DJ6+FA6+GR6+II6+JZ6+LQ6+NH6+OY6+QP6+SG6 -> 118334.8 | TA6: =AR6+CI6+DZ6+FQ6+HH6+IY6+KP6+MG6+NX6+PO6+RF6+SW6 -> 38479.453 | TB6: =SZ6-TA6 -> 79855.347
A7: 1105 | B7: 1105_SWINOU | C7: MOVE S320 | D7: 3013.93 | E7: 5953 | F7: 0 | G7: 0 | H7: 0 | I7: 0 | J7: 0 | K7: 0 | L7: 0 | M7: 0 | N7: 8966.93 | O7: =Q7-N7 -> 0 | P7: 424 | Q7: =SUM(D7:M7) -> 8966.93 | R7: 250.87 | S7: 4357.14 | T7: 0 | U7: 0 | V7: 0 | W7: 0 | X7: 0 | Y7: 0 | Z7: 0 | AA7: 0 | AB7: =SUM(R7:AA7) -> 4608.01 | AE7: =(N7/$N$116)*21028.32 -> 97.495618 | AF7: =(O7/$O$116)*15324.97 -> 0 | AH7: 20 | AJ7: 5 | AK7: =39081.75/95 -> 411.38684 | AM7: =SUM(AC7:AL7) -> 533.88246 | AN7: =61284.58/95 -> 645.10084 | AO7: 0 | AP7: =(AN7+AO7)*30% -> 193.53025 | AQ7: =SUM(AN7:AP7) -> 838.63109 | AR7: =AM7+AQ7 -> 1372.5136 | AS7: =AB7-AR7 -> 3235.4964 | AT7: 3170.44 | AU7: 5430.52 | AV7: 0 | AW7: 0 | AX7: 0 | AY7: 0 | AZ7: 0 | BA7: 0 | BB7: 0 | BC7: 0 | BD7: 8600.96 | BE7: =BH7-BD7 -> 0 | BF7: 386 | BG7: MOVE S320 | BH7: =SUM(AT7:BC7) -> 8600.96 | BI7: 263.91 | BJ7: 4357.14 | BK7: 0 | BL7: 0 | BM7: 0 | BN7: 0 | BO7: 0 | BP7: 0 | BQ7: 0 | BR7: 0 | BS7: =SUM(BI7:BR7) -> 4621.05 | BV7: =(BD7/$BD$116)*21083.85 -> 94.33288 | BW7: =(BE7/$O$116)*12925.76 -> 0 | BY7: 20 | CA7: 5 | CB7: =37537.5/96 -> 391.01562 | CD7: =SUM(BT7:CC7) -> 510.3485 | CE7: =63860.36/96 -> 665.21208 | CG7: =(CE7+CF7)*30% -> 199.56363 | CH7: =SUM(CE7:CG7) -> 864.77571 | CI7: =CD7+CH7 -> 1375.1242 | CJ7: =BS7-CI7 -> 3245.9258 | CK7: 4629.64 | CL7: 6931.1 | CM7: 0 | CN7: 0 | CO7: 0 | CP7: 0 | CQ7: 0 | CR7: 0 | CS7: 0 | CT7: 0 | CU7: 11560.74 | CV7: =CY7-CU7 -> 0 | CW7: 482 | CX7: MOVE S320 | CY7: =SUM(CK7:CT7) -> 11560.74 | CZ7: 385.37 | DA7: 4357.14 | DB7: 0 | DC7: 0 | DD7: 0 | DE7: 0 | DF7: 0 | DG7: 0 | DH7: 0 | DI7: 0 | DJ7: =SUM(CZ7:DI7) -> 4742.51 | DM7: =(CU7/$CU$116)*24055.75 -> 125.6814 | DN7: =(CV7/$O$116)*16258.02 -> 0 | DP7: 20 | DR7: 5 | DS7: =DS$3 -> 428.4697 | DU7: =SUM(DK7:DT7) -> 579.1511 | DV7: =DV$3 -> 596.35071 | DX7: =(DV7+DW7)*30% -> 178.90521 | DY7: =SUM(DV7:DX7) -> 775.25592 | DZ7: =DU7+DY7 -> 1354.407 | EA7: =DJ7-DZ7 -> 3388.103 | EB7: 4119.21 | EC7: 7181.88 | ED7: 0 | EE7: 0 | EF7: 0 | EG7: 0 | EH7: 0 | EI7: 0 | EJ7: 0 | EK7: 0 | EL7: 11301.09 | EM7: =EP7-EL7 -> 0 | EN7: 482 | EO7: MOVE S320 | EP7: =SUM(EB7:EK7) -> 11301.09 | EQ7: 342.88 | ER7: 4357.14 | ES7: 0 | ET7: 0 | EU7: 0 | EV7: 0 | EW7: 0 | EX7: 0 | EY7: 0 | EZ7: 0 | FA7: =SUM(EQ7:EZ7) -> 4700.02 | FD7: =(EL7/$EL$116)*26325.65 -> 126.14334 | FE7: =(EM7/$O$116)*14846.27 -> 0 | FF7: =52000/60 -> 866.66667 | FG7: 20 | FH7: =14375.2/102 -> 140.93333 | FI7: 5 | FJ7: =FJ$3 -> 424.6802 | FL7: =SUM(FB7:FK7) -> 1583.4235 | FM7: =FM$3 -> 664.41902 | FO7: =(FM7+FN7)*30% -> 199.32571 | FP7: =SUM(FM7:FO7) -> 863.74473 | FQ7: =FL7+FP7 -> 2447.1683 | FR7: =FA7-FQ7 -> 2252.8517 | FS7: 5933.64 | FT7: 12111.8 | FU7: 0 | FV7: 0 | FW7: 0 | FX7: 0 | FY7: 0 | FZ7: 46.7 | GA7: 0 | GB7: 0 | GC7: 18092.14 | GD7: =GG7-GC7 -> 0 | GE7: 787 | GF7: MOVE S320 | GG7: =SUM(FS7:GB7) -> 18092.14 | GH7: 493.91 | GI7: 4357.14 | GJ7: 0 | GK7: 0 | GL7: 0 | GM7: 0 | GN7: 0 | GO7: 3.24 | GP7: 0 | GQ7: 0 | GR7: =SUM(GH7:GQ7) -> 4854.29 | GU7: =(GC7/$GC$116)*30198.86 -> 200.48343 | GV7: =(GD7/$O$116)*16844.27 -> 0 | GW7: =52000/60 -> 866.66667 | GX7: 20 | GY7: =18860.4/102 -> 184.90588 | GZ7: 5 | HA7: =HA$3 -> 358.47794 | HC7: =SUM(GS7:HB7) -> 1635.5339 | HD7: =HD$3 -> 866.9202 | HF7: =(HD7+HE7)*30% -> 260.07606 | HG7: =SUM(HD7:HF7) -> 1126.9963 | HH7: =HC7+HG7 -> 2762.5302 | HI7: =GR7-HH7 -> 2091.7598 | HJ7: 7500.38 | HK7: 13743.52 | HL7: 20.2 | HM7: 0 | HN7: 0 | HO7: 0 | HP7: 0 | HQ7: 13 | HR7: 0 | HS7: 0 | HT7: 21277.1 | HU7: =HX7-HT7 -> 0 | HV7: 881 | HW7: MOVE S320 | HX7: =SUM(HJ7:HS7) -> 21277.1 | HY7: 624.33 | HZ7: 4357.14 | IA7: 1.29 | IB7: 0 | IC7: 0 | ID7: 0 | IE7: 0 | IF7: 0.9 | IG7: 0 | IH7: 0 | II7: =SUM(HY7:IH7) -> 4983.66 | IL7: =(HT7/$HT$116)*31846.83 -> 235.69616 | IM7: =(HU7/$O$116)*17321.85 -> 0 | IN7: =52000/60 -> 866.66667 | IO7: 20 | IP7: =24366/105 -> 232.05714 | IQ7: 5 | IR7: =IR$3 -> 445.62857 | IT7: =SUM(IJ7:IS7) -> 1805.0485 | IU7: =IU$3 -> 538.79476 | IW7: =(IU7+IV7)*30% -> 161.63843 | IX7: =SUM(IU7:IW7) -> 700.43319 | IY7: =IT7+IX7 -> 2505.4817 | IZ7: =II7-IY7 -> 2478.1783 | JA7: 11780.08 | JB7: 16270.03 | JC7: 105.5 | JD7: 0 | JE7: 0 | JF7: 0 | JG7: 0 | JH7: 0 | JI7: 25.77 | JJ7: 0 | JK7: 28181.38 | JL7: =JO7-JK7 -> 0 | JM7: 1130 | JN7: MOVE S320 | JO7: =SUM(JA7:JJ7) -> 28181.38 | JP7: 980.58 | JQ7: 4357.14 | JR7: 6.74 | JS7: 0 | JT7: 0 | JU7: 0 | JV7: 0 | JW7: 0 | JX7: 1.43 | JY7: 0 | JZ7: =SUM(JP7:JY7) -> 5345.89 | KC7: =(JK7/$N$116)*39010.72 -> 568.43782 | KD7: =(JL7/$O$116)*19244.4 -> 0 | KE7: =52000/60 -> 866.66667 | KF7: 20 | KH7: 5 | KI7: =KI$3 -> 543.39953 | KK7: =SUM(KA7:KJ7) -> 2003.504 | KL7: =KL$3 -> 497.32093 | KN7: =(KL7+KM7)*30% -> 149.19628 | KO7: =SUM(KL7:KN7) -> 646.51721 | KP7: =KK7+KO7 -> 2650.0212 | KQ7: =JZ7-KP7 -> 2695.8688 | KR7: 10665.31 | KS7: 21097.43 | KT7: 11.6 | KU7: 0 | KV7: 0 | KW7: 0 | KX7: 0 | KY7: 0 | KZ7: 0 | LA7: 0 | LB7: 31774.34 | LC7: =LF7-LB7 -> 0 | LD7: 1287 | LE7: MOVE S320 | LF7: =SUM(KR7:LA7) -> 31774.34 | LG7: 887.79 | LH7: 4357.14 | LI7: 0.74 | LJ7: 0 | LK7: 0 | LL7: 0 | LM7: 0 | LN7: 0 | LO7: 0 | LP7: 0 | LQ7: =SUM(LG7:LP7) -> 5245.67 | LT7: =(LB7/$LB$116)*39133.48 -> 323.94346 | LU7: =(LC7/$O$116)*17015.75 -> 0 | LV7: =52000/60 -> 866.66667 | LW7: 20 | LY7: 5 | LZ7: =LZ$3 -> 508.03738 | MB7: =SUM(LR7:MA7) -> 1723.6475 | MC7: =MC$3 -> 593.54907 | ME7: =(MC7+MD7)*30% -> 178.06472 | MF7: =SUM(MC7:ME7) -> 771.61379 | MG7: =MB7+MF7 -> 2495.2613 | MH7: =LQ7-MG7 -> 2750.4087 | MI7: 4251.16 | MJ7: 13685.49 | MK7: 12.8 | ML7: 0 | MM7: 0 | MN7: 0 | MO7: 0 | MP7: 0 | MQ7: 0 | MR7: 0 | MS7: 17949.45 | MT7: =MW7-MS7 -> 0 | MU7: 764 | MV7: MOVE S320 | MW7: =SUM(MI7:MR7) -> 17949.45 | MX7: 353.87 | MY7: 4357.14 | MZ7: 0.82 | NA7: 0 | NB7: 0 | NC7: 0 | ND7: 0 | NE7: 0 | NF7: 0 | NG7: 0 | NH7: =SUM(MX7:NG7) -> 4711.83 | NK7: =(MS7/$N$116)*0 -> 0 | NL7: =(MT7/$O$116)*13804.26 -> 0 | NM7: =52000/60 -> 866.66667 | NN7: 20 | NP7: 5 | NQ7: =NQ$3 -> 469.6789 | NS7: =SUM(NI7:NR7) -> 1361.3456 | NT7: =78812.25/109 -> 723.04817 | NV7: =(NT7+NU7)*30% -> 216.91445 | NW7: =SUM(NT7:NV7) -> 939.96261 | NX7: =NS7+NW7 -> 2301.3082 | NY7: =NH7-NX7 -> 2410.5218 | NZ7: 3107.08 | OA7: 11487.18 | OB7: 0 | OC7: 0 | OD7: 0 | OE7: 0 | OF7: 0 | OG7: 0 | OH7: 0 | OI7: 0 | OJ7: 14594.26 | OK7: =ON7-OJ7 -> 0 | OL7: 620 | OM7: MOVE S320 | ON7: =SUM(NZ7:OI7) -> 14594.26 | OO7: 258.63 | OP7: 4357.14 | OQ7: 0 | OR7: 0 | OS7: 0 | OT7: 0 | OU7: 0 | OV7: 0 | OW7: 0 | OX7: 0 | OY7: =SUM(OO7:OX7) -> 4615.77 | PB7: =(OJ7/$OJ$116)*56307.47 -> 315.57549 | PC7: =(OK7/$O$116)*16757.91 -> 0 | PD7: =52000/60 -> 866.66667 | PE7: 20 | PF7: =3288/100 -> 32.88 | PG7: 5 | PH7: =PH$3 -> 495.20491 | PJ7: =SUM(OZ7:PI7) -> 1735.3271 | PK7: =PK$3 -> 643.25573 | PM7: =(PK7+PL7)*30% -> 192.97672 | PN7: =SUM(PK7:PM7) -> 836.23245 | PO7: =PJ7+PN7 -> 2571.5595 | PP7: =OY7-PO7 -> 2044.2105 | PQ7: 2007.91 | PR7: 8830.72 | PS7: 0 | PT7: 0 | PU7: 0 | PV7: 0 | PW7: 0 | PX7: 3 | PY7: 0 | PZ7: 21.8 | QA7: 10863.43 | QB7: =QE7-QA7 -> 0 | QC7: 464 | QD7: MOVE S320 | QE7: =SUM(PQ7:PZ7) -> 10863.43 | QF7: 167.13 | QG7: 4357.14 | QH7: 0 | QI7: 0 | QJ7: 0 | QK7: 0 | QL7: 0 | QM7: 0.21 | QN7: 0 | QO7: 1.21 | QP7: =SUM(QF7:QO7) -> 4525.69 | QS7: =(QA7/$QA$116)*27743.06 -> 127.69968 | QT7: =(QB7/$O$116)*10429.01 -> 0 | QU7: =52000/60 -> 866.66667 | QV7: 20 | QW7: =2074.8/110 -> 18.861818 | QX7: 5 | QY7: =QY$3 -> 428.14773 | RA7: =SUM(QQ7:QZ7) -> 1466.3759 | RB7: =68119.05/110 -> 619.26409 | RD7: =(RB7+RC7)*30% -> 185.77923 | RE7: =SUM(RB7:RD7) -> 805.04332 | RF7: =RA7+RE7 -> 2271.4192 | RG7: =QP7-RF7 -> 2254.2708 | RH7: 3311.71 | RI7: 8429.56 | RJ7: 12.95 | RK7: 0 | RL7: 0 | RM7: 0 | RN7: 0 | RO7: 0 | RP7: 0 | RQ7: 0 | RR7: 11754.22 | RS7: =RV7-RR7 -> 0 | RT7: 458 | RU7: MOVE S320 | RV7: =SUM(RH7:RQ7) -> 11754.22 | RW7: 275.67 | RX7: 4357.14 | RY7: 0.83 | RZ7: 0 | SA7: 0 | SB7: 0 | SC7: 0 | SD7: 0 | SE7: 0 | SF7: 0 | SG7: 4633.64 | SJ7: =(RR7/$RR$116)*25115.94 -> 115.50762 | SK7: =(RS7/$O$116)*12319.54 -> 0 | SL7: =52000/60 -> 866.66667 | SM7: 20 | SN7: =56040/113 -> 495.9292 | SO7: 5 | SP7: =SP$3 -> 428.52876 | SR7: =SUM(SH7:SQ7) -> 1931.6322 | SS7: =SS$3 -> 596.28469 | SU7: =(SS7+ST7)*30% -> 178.88541 | SV7: =SUM(SS7:SU7) -> 775.1701 | SW7: =SR7+SV7 -> 2706.8023 | SX7: =SG7-SW7 -> 1926.8377 | SY7: =Q7+BH7+CY7+EP7+GG7+HX7+JO7+LF7+MW7+ON7+QE7+RV7 -> 194916.04 | SZ7: =AB7+BS7+DJ7+FA7+GR7+II7+JZ7+LQ7+NH7+OY7+QP7+SG7 -> 57588.03 | TA7: =AR7+CI7+DZ7+FQ7+HH7+IY7+KP7+MG7+NX7+PO7+RF7+SW7 -> 26813.597 | TB7: =SZ7-TA7 -> 30774.433
A8: 1106 | B8: 1106_SZCZ_GL | C8: MOVE S320 | D8: 9547.35 | E8: 16539.53 | F8: 0 | G8: 0 | H8: 0 | I8: 0 | J8: 0 | K8: 0 | L8: 0 | M8: 0 | N8: 26086.88 | O8: =Q8-N8 -> 0 | P8: 1332 | Q8: =SUM(D8:M8) -> 26086.88 | R8: 794.72 | S8: 4357.14 | T8: 0 | U8: 0 | V8: 0 | W8: 0 | X8: 0 | Y8: 0 | Z8: 0 | AA8: 0 | AB8: =SUM(R8:AA8) -> 5151.86 | AE8: =(N8/$N$116)*21028.32 -> 283.63737 | AF8: =(O8/$O$116)*15324.97 -> 0 | AH8: 20 | AJ8: 5 | AK8: =39081.75/95 -> 411.38684 | AM8: =SUM(AC8:AL8) -> 720.02422 | AN8: =61284.58/95 -> 645.10084 | AO8: 0 | AP8: =(AN8+AO8)*30% -> 193.53025 | AQ8: =SUM(AN8:AP8) -> 838.63109 | AR8: =AM8+AQ8 -> 1558.6553 | AS8: =AB8-AR8 -> 3593.2047 | AT8: 8349.57 | AU8: 13665.22 | AV8: 0 | AW8: 0 | AX8: 0 | AY8: 0 | AZ8: 0 | BA8: 38.2 | BB8: 0 | BC8: 0 | BD8: 22052.99 | BE8: =BH8-BD8 -> 0 | BF8: 1031 | BG8: MOVE S320 | BH8: =SUM(AT8:BC8) -> 22052.99 | BI8: 695.01 | BJ8: 4357.14 | BK8: 0 | BL8: 0 | BM8: 0 | BN8: 0 | BO8: 0 | BP8: 2.65 | BQ8: 0 | BR8: 0 | BS8: =SUM(BI8:BR8) -> 5054.8 | BV8: =(BD8/$BD$116)*21083.85 -> 241.87091 | BW8: =(BE8/$O$116)*12925.76 -> 0 | BY8: 20 | CA8: 5 | CB8: =37537.5/96 -> 391.01562 | CD8: =SUM(BT8:CC8) -> 657.88654 | CE8: =63860.36/96 -> 665.21208 | CG8: =(CE8+CF8)*30% -> 199.56363 | CH8: =SUM(CE8:CG8) -> 864.77571 | CI8: =CD8+CH8 -> 1522.6622 | CJ8: =BS8-CI8 -> 3532.1378 | CK8: 13386.26 | CL8: 19964.51 | CM8: 25.6 | CN8: 0 | CO8: 0 | CP8: 0 | CQ8: 0 | CR8: 6 | CS8: 0 | CT8: 0 | CU8: 33382.37 | CV8: =CY8-CU8 -> 0 | CW8: 1491 | CX8: MOVE S320 | CY8: =SUM(CK8:CT8) -> 33382.37 | CZ8: 1114.26 | DA8: 4357.14 | DB8: 1.64 | DC8: 0 | DD8: 0 | DE8: 0 | DF8: 0 | DG8: 0.42 | DH8: 0 | DI8: 0 | DJ8: =SUM(CZ8:DI8) -> 5473.46 | DM8: =(CU8/$CU$116)*24055.75 -> 362.91302 | DN8: =(CV8/$O$116)*16258.02 -> 0 | DP8: 20 | DR8: 5 | DS8: =DS$3 -> 428.4697 | DU8: =SUM(DK8:DT8) -> 816.38271 | DV8: =DV$3 -> 596.35071 | DX8: =(DV8+DW8)*30% -> 178.90521 | DY8: =SUM(DV8:DX8) -> 775.25592 | DZ8: =DU8+DY8 -> 1591.6386 | EA8: =DJ8-DZ8 -> 3881.8214 | EB8: 16305.95 | EC8: 24884.52 | ED8: 0 | EE8: 0 | EF8: 0 | EG8: 0 | EH8: 0 | EI8: 0 | EJ8: 0 | EK8: 0 | EL8: 41190.47 | EM8: =EP8-EL8 -> 0 | EN8: 1816 | EO8: MOVE S320 | EP8: =SUM(EB8:EK8) -> 41190.47 | EQ8: 1357.3 | ER8: 4357.14 | ES8: 0 | ET8: 0 | EU8: 0 | EV8: 0 | EW8: 0 | EX8: 0 | EY8: 0 | EZ8: 0 | FA8: =SUM(EQ8:EZ8) -> 5714.44 | FD8: =(EL8/$EL$116)*26325.65 -> 459.77012 | FE8: =(EM8/$O$116)*14846.27 -> 0 | FF8: =52000/60 -> 866.66667 | FG8: 20 | FH8: =14375.2/102 -> 140.93333 | FI8: 5 | FJ8: =FJ$3 -> 424.6802 | FL8: =SUM(FB8:FK8) -> 1917.0503 | FM8: =FM$3 -> 664.41902 | FO8: =(FM8+FN8)*30% -> 199.32571 | FP8: =SUM(FM8:FO8) -> 863.74473 | FQ8: =FL8+FP8 -> 2780.795 | FR8: =FA8-FQ8 -> 2933.645 | FS8: 16726.97 | FT8: 23947.96 | FU8: 0 | FV8: 0 | FW8: 0 | FX8: 0 | FY8: 0 | FZ8: 0 | GA8: 19.95 | GB8: 0 | GC8: 40694.88 | GD8: =GG8-GC8 -> 0 | GE8: 1689 | GF8: MOVE S320 | GG8: =SUM(FS8:GB8) -> 40694.88 | GH8: 1392.37 | GI8: 4357.14 | GJ8: 0 | GK8: 0 | GL8: 0 | GM8: 0 | GN8: 0 | GO8: 0 | GP8: 1.11 | GQ8: 0 | GR8: =SUM(GH8:GQ8) -> 5750.62 | GU8: =(GC8/$GC$116)*30198.86 -> 450.94992 | GV8: =(GD8/$O$116)*16844.27 -> 0 | GW8: =52000/60 -> 866.66667 | GX8: 20 | GY8: =18860.4/102 -> 184.90588 | GZ8: 5 | HA8: =HA$3 -> 358.47794 | HC8: =SUM(GS8:HB8) -> 1886.0004 | HD8: =HD$3 -> 866.9202 | HF8: =(HD8+HE8)*30% -> 260.07606 | HG8: =SUM(HD8:HF8) -> 1126.9963 | HH8: =HC8+HG8 -> 3012.9967 | HI8: =GR8-HH8 -> 2737.6233 | HJ8: 20662.34 | HK8: 31848.62 | HL8: 0 | HM8: 0 | HN8: 0 | HO8: 0 | HP8: 0 | HQ8: 0 | HR8: 0 | HS8: 0 | HT8: 52510.96 | HU8: =HX8-HT8 -> 0 | HV8: 2134 | HW8: MOVE S320 | HX8: =SUM(HJ8:HS8) -> 52510.96 | HY8: 1719.93 | HZ8: 4357.14 | IA8: 0 | IB8: 0 | IC8: 0 | ID8: 0 | IE8: 0 | IF8: 0 | IG8: 0 | IH8: 0 | II8: =SUM(HY8:IH8) -> 6077.07 | IL8: =(HT8/$HT$116)*31846.83 -> 581.68789 | IM8: =(HU8/$O$116)*17321.85 -> 0 | IN8: =52000/60 -> 866.66667 | IO8: 20 | IP8: =24366/105 -> 232.05714 | IQ8: 5 | IR8: =IR$3 -> 445.62857 | IT8: =SUM(IJ8:IS8) -> 2151.0403 | IU8: =IU$3 -> 538.79476 | IW8: =(IU8+IV8)*30% -> 161.63843 | IX8: =SUM(IU8:IW8) -> 700.43319 | IY8: =IT8+IX8 -> 2851.4735 | IZ8: =II8-IY8 -> 3225.5965 | JA8: 32324.22 | JB8: 42076.99 | JC8: 67.3 | JD8: 0 | JE8: 0 | JF8: 0 | JG8: 0 | JH8: 68.97 | JI8: 0 | JJ8: 0 | JK8: 74537.48 | JL8: =JO8-JK8 -> 0 | JM8: 2622 | JN8: MOVE S320 | JO8: =SUM(JA8:JJ8) -> 74537.48 | JP8: 2690.7 | JQ8: 4357.14 | JR8: 4.3 | JS8: 0 | JT8: 0 | JU8: 0 | JV8: 0 | JW8: 4.79 | JX8: 0 | JY8: 0 | JZ8: =SUM(JP8:JY8) -> 7056.93 | KC8: =(JK8/$N$116)*39010.72 -> 1503.4722 | KD8: =(JL8/$O$116)*19244.4 -> 0 | KE8: =52000/60 -> 866.66667 | KF8: 20 | KH8: 5 | KI8: =KI$3 -> 543.39953 | KK8: =SUM(KA8:KJ8) -> 2938.5384 | KL8: =KL$3 -> 497.32093 | KN8: =(KL8+KM8)*30% -> 149.19628 | KO8: =SUM(KL8:KN8) -> 646.51721 | KP8: =KK8+KO8 -> 3585.0556 | KQ8: =JZ8-KP8 -> 3471.8744 | KR8: 29682.71 | KS8: 51274.58 | KT8: 0 | KU8: 0 | KV8: 0 | KW8: 0 | KX8: 0 | KY8: 38.2 | KZ8: 0 | LA8: 0 | LB8: 80995.49 | LC8: =LF8-LB8 -> 0 | LD8: 2921 | LE8: MOVE S320 | LF8: =SUM(KR8:LA8) -> 80995.49 | LG8: 2470.81 | LH8: 4357.14 | LI8: 0 | LJ8: 0 | LK8: 0 | LL8: 0 | LM8: 0 | LN8: 2.65 | LO8: 0 | LP8: 0 | LQ8: =SUM(LG8:LP8) -> 6830.6 | LT8: =(LB8/$LB$116)*39133.48 -> 825.75938 | LU8: =(LC8/$O$116)*17015.75 -> 0 | LV8: =52000/60 -> 866.66667 | LW8: 20 | LY8: 5 | LZ8: =LZ$3 -> 508.03738 | MB8: =SUM(LR8:MA8) -> 2225.4634 | MC8: =MC$3 -> 593.54907 | ME8: =(MC8+MD8)*30% -> 178.06472 | MF8: =SUM(MC8:ME8) -> 771.61379 | MG8: =MB8+MF8 -> 2997.0772 | MH8: =LQ8-MG8 -> 3833.5228 | MI8: 19779 | MJ8: 33990.15 | MK8: 31.26 | ML8: 0 | MM8: 0 | MN8: 0 | MO8: 0 | MP8: 29.3 | MQ8: 0 | MR8: 18.8 | MS8: 53848.51 | MT8: =MW8-MS8 -> 0 | MU8: 2159 | MV8: MOVE S320 | MW8: =SUM(MI8:MR8) -> 53848.51 | MX8: 1646.42 | MY8: 4357.14 | MZ8: 2 | NA8: 0 | NB8: 0 | NC8: 0 | ND8: 0 | NE8: 2.03 | NF8: 0 | NG8: 1.04 | NH8: =SUM(MX8:NG8) -> 6008.63 | NK8: =(MS8/$N$116)*0 -> 0 | NL8: =(MT8/$O$116)*13804.26 -> 0 | NM8: =52000/60 -> 866.66667 | NN8: 20 | NP8: 5 | NQ8: =NQ$3 -> 469.6789 | NS8: =SUM(NI8:NR8) -> 1361.3456 | NT8: =78812.25/109 -> 723.04817 | NV8: =(NT8+NU8)*30% -> 216.91445 | NW8: =SUM(NT8:NV8) -> 939.96261 | NX8: =NS8+NW8 -> 2301.3082 | NY8: =NH8-NX8 -> 3707.3218 | NZ8: 18796.02 | OA8: 28666.98 | OB8: 0 | OC8: 0 | OD8: 0 | OE8: 0 | OF8: 0 | OG8: 148.2 | OH8: 0 | OI8: 0 | OJ8: 47611.2 | OK8: =ON8-OJ8 -> 0 | OL8: 2073 | OM8: MOVE S320 | ON8: =SUM(NZ8:OI8) -> 47611.2 | OO8: 1564.59 | OP8: 4357.14 | OQ8: 0 | OR8: 0 | OS8: 0 | OT8: 0 | OU8: 0 | OV8: 10.29 | OW8: 0 | OX8: 0 | OY8: =SUM(OO8:OX8) -> 5932.02 | PB8: =(OJ8/$OJ$116)*56307.47 -> 1029.5094 | PC8: =(OK8/$O$116)*16757.91 -> 0 | PD8: =52000/60 -> 866.66667 | PE8: 20 | PF8: =3288/100 -> 32.88 | PG8: 5 | PH8: =PH$3 -> 495.20491 | PJ8: =SUM(OZ8:PI8) -> 2449.261 | PK8: =PK$3 -> 643.25573 | PM8: =(PK8+PL8)*30% -> 192.97672 | PN8: =SUM(PK8:PM8) -> 836.23245 | PO8: =PJ8+PN8 -> 3285.4934 | PP8: =OY8-PO8 -> 2646.5266 | PQ8: 16503.32 | PR8: 29280.82 | PS8: 51.85 | PT8: 0 | PU8: 0 | PV8: 0 | PW8: 0 | PX8: 40.2 | PY8: 0 | PZ8: 0 | QA8: 45876.19 | QB8: =QE8-QA8 -> 0 | QC8: 1971 | QD8: MOVE S320 | QE8: =SUM(PQ8:PZ8) -> 45876.19 | QF8: 1373.75 | QG8: 4357.14 | QH8: 3.31 | QI8: 0 | QJ8: 0 | QK8: 0 | QL8: 0 | QM8: 2.79 | QN8: 0 | QO8: 0 | QP8: =SUM(QF8:QO8) -> 5736.99 | QS8: =(QA8/$QA$116)*27743.06 -> 539.27489 | QT8: =(QB8/$O$116)*10429.01 -> 0 | QU8: =52000/60 -> 866.66667 | QV8: 20 | QW8: =2074.8/110 -> 18.861818 | QX8: 5 | QY8: =QY$3 -> 428.14773 | RA8: =SUM(QQ8:QZ8) -> 1877.9511 | RB8: =68119.05/110 -> 619.26409 | RD8: =(RB8+RC8)*30% -> 185.77923 | RE8: =SUM(RB8:RD8) -> 805.04332 | RF8: =RA8+RE8 -> 2682.9944 | RG8: =QP8-RF8 -> 3053.9956 | RH8: 14777.72 | RI8: 27517.12 | RJ8: 0 | RK8: 0 | RL8: 0 | RM8: 0 | RN8: 0 | RO8: 0 | RP8: 0 | RQ8: 0 | RR8: 42294.84 | RS8: =RV8-RR8 -> 0 | RT8: 1810 | RU8: MOVE S320 | RV8: =SUM(RH8:RQ8) -> 42294.84 | RW8: 1230.11 | RX8: 4357.14 | RY8: 0 | RZ8: 0 | SA8: 0 | SB8: 0 | SC8: 0 | SD8: 0 | SE8: 0 | SF8: 0 | SG8: 5587.25 | SJ8: =(RR8/$RR$116)*25115.94 -> 415.62742 | SK8: =(RS8/$O$116)*12319.54 -> 0 | SL8: =52000/60 -> 866.66667 | SM8: 20 | SN8: =56040/113 -> 495.9292 | SO8: 5 | SP8: =SP$3 -> 428.52876 | SR8: =SUM(SH8:SQ8) -> 2231.7521 | SS8: =SS$3 -> 596.28469 | SU8: =(SS8+ST8)*30% -> 178.88541 | SV8: =SUM(SS8:SU8) -> 775.1701 | SW8: =SR8+SV8 -> 3006.9221 | SX8: =SG8-SW8 -> 2580.3279 | SY8: =Q8+BH8+CY8+EP8+GG8+HX8+JO8+LF8+MW8+ON8+QE8+RV8 -> 561082.26 | SZ8: =AB8+BS8+DJ8+FA8+GR8+II8+JZ8+LQ8+NH8+OY8+QP8+SG8 -> 70374.67 | TA8: =AR8+CI8+DZ8+FQ8+HH8+IY8+KP8+MG8+NX8+PO8+RF8+SW8 -> 31177.072 | TB8: =SZ8-TA8 -> 39197.598
A9: 1107 | B9: 1107_OPOLE | C9: MOVE S320 | D9: 6500.65 | E9: 15847.82 | F9: 13.2 | G9: 0 | H9: 0 | I9: 0 | J9: 0 | K9: 23.6 | L9: 35.44 | M9: 0 | N9: 22420.71 | O9: 0 | P9: 1472 | Q9: =SUM(D9:M9) -> 22420.71 | R9: 541.13 | S9: 4357.14 | T9: 0.84 | U9: 0 | V9: 0 | W9: 0 | X9: 0 | Y9: 1.64 | Z9: 1.97 | AA9: 0 | AB9: =SUM(R9:AA9) -> 4902.72 | AE9: =(N9/$N$116)*21028.32 -> 243.77585 | AF9: =(O9/$O$116)*15324.97 -> 0 | AH9: 20 | AJ9: 5 | AK9: =39081.75/95 -> 411.38684 | AM9: =SUM(AC9:AL9) -> 680.16269 | AN9: =61284.58/95 -> 645.10084 | AO9: 0 | AP9: =(AN9+AO9)*30% -> 193.53025 | AQ9: =SUM(AN9:AP9) -> 838.63109 | AR9: =AM9+AQ9 -> 1518.7938 | AS9: =AB9-AR9 -> 3383.9262 | AT9: 8250.49 | AU9: 14326.99 | AV9: 0 | AW9: 0 | AX9: 0 | AY9: 0 | AZ9: 0 | BA9: 96.7 | BB9: 32.87 | BC9: 0 | BD9: 22707.05 | BE9: 0 | BF9: 1506 | BG9: MOVE S320 | BH9: =SUM(AT9:BC9) -> 22707.05 | BI9: 686.78 | BJ9: 4357.14 | BK9: 0 | BL9: 0 | BM9: 0 | BN9: 0 | BO9: 0 | BP9: 6.72 | BQ9: 1.83 | BR9: 0 | BS9: =SUM(BI9:BR9) -> 5052.47 | BV9: =(BD9/$BD$116)*21083.85 -> 249.04446 | BW9: =(BE9/$O$116)*12925.76 -> 0 | BY9: 20 | CA9: 5 | CB9: =37537.5/96 -> 391.01562 | CD9: =SUM(BT9:CC9) -> 665.06008 | CE9: =63860.36/96 -> 665.21208 | CG9: =(CE9+CF9)*30% -> 199.56363 | CH9: =SUM(CE9:CG9) -> 864.77571 | CI9: =CD9+CH9 -> 1529.8358 | CJ9: =BS9-CI9 -> 3522.6342 | CK9: 9679.71 | CL9: 16598.63 | CM9: 6.6 | CN9: 0 | CO9: 0 | CP9: 0 | CQ9: 0 | CR9: 18.45 | CS9: 80.75 | CT9: 0 | CU9: 26384.14 | CV9: 0 | CW9: 1689 | CX9: MOVE S320 | CY9: =SUM(CK9:CT9) -> 26384.14 | CZ9: 805.76 | DA9: 4357.14 | DB9: 0.42 | DC9: 0 | DD9: 0 | DE9: 0 | DF9: 0 | DG9: 1.28 | DH9: 4.49 | DI9: 0 | DJ9: =SUM(CZ9:DI9) -> 5169.09 | DM9: =(CU9/$CU$116)*24055.75 -> 286.83248 | DN9: =(CV9/$O$116)*16258.02 -> 0 | DP9: 20 | DR9: 5 | DS9: =DS$3 -> 428.4697 | DU9: =SUM(DK9:DT9) -> 740.30217 | DV9: =DV$3 -> 596.35071 | DX9: =(DV9+DW9)*30% -> 178.90521 | DY9: =SUM(DV9:DX9) -> 775.25592 | DZ9: =DU9+DY9 -> 1515.5581 | EA9: =DJ9-DZ9 -> 3653.5319 | EB9: 10327.79 | EC9: 17818.5 | ED9: 0 | EE9: 0 | EF9: 0 | EG9: 0 | EH9: 0 | EI9: 39 | EJ9: 90.26 | EK9: 0 | EL9: 28275.55 | EM9: 0 | EN9: 1772 | EO9: MOVE S320 | EP9: =SUM(EB9:EK9) -> 28275.55 | EQ9: 859.7 | ER9: 4357.14 | ES9: 0 | ET9: 0 | EU9: 0 | EV9: 0 | EW9: 0 | EX9: 2.71 | EY9: 5.01 | EZ9: 0 | FA9: =SUM(EQ9:EZ9) -> 5224.56 | FD9: =(EL9/$EL$116)*26325.65 -> 315.61313 | FE9: =(EM9/$O$116)*14846.27 -> 0 | FF9: =52000/60 -> 866.66667 | FG9: 20 | FH9: =14375.2/102 -> 140.93333 | FI9: 5 | FJ9: =FJ$3 -> 424.6802 | FL9: =SUM(FB9:FK9) -> 1772.8933 | FM9: =FM$3 -> 664.41902 | FO9: =(FM9+FN9)*30% -> 199.32571 | FP9: =SUM(FM9:FO9) -> 863.74473 | FQ9: =FL9+FP9 -> 2636.638 | FR9: =FA9-FQ9 -> 2587.922 | FS9: 9177.36 | FT9: 19934.97 | FU9: 13.2 | FV9: 0 | FW9: 0 | FX9: 0 | FY9: 0 | FZ9: 50.26 | GA9: 65.59 | GB9: 0 | GC9: 29241.38 | GD9: 0 | GE9: 1894 | GF9: MOVE S320 | GG9: =SUM(FS9:GB9) -> 29241.38 | GH9: 763.94 | GI9: 4357.14 | GJ9: 0.84 | GK9: 0 | GL9: 0 | GM9: 0 | GN9: 0 | GO9: 3.42 | GP9: 3.64 | GQ9: 0 | GR9: =SUM(GH9:GQ9) -> 5128.98 | GU9: =(GC9/$GC$116)*30198.86 -> 324.03088 | GV9: =(GD9/$O$116)*16844.27 -> 0 | GW9: =52000/60 -> 866.66667 | GX9: 20 | GY9: =18860.4/102 -> 184.90588 | GZ9: 5 | HA9: =HA$3 -> 358.47794 | HC9: =SUM(GS9:HB9) -> 1759.0814 | HD9: =HD$3 -> 866.9202 | HF9: =(HD9+HE9)*30% -> 260.07606 | HG9: =SUM(HD9:HF9) -> 1126.9963 | HH9: =HC9+HG9 -> 2886.0776 | HI9: =GR9-HH9 -> 2242.9024 | HJ9: 8986.88 | HK9: 20372.11 | HL9: 6.6 | HM9: 0 | HN9: 0 | HO9: 0 | HP9: 0 | HQ9: 88.41 | HR9: 23.37 | HS9: 0 | HT9: 29477.37 | HU9: 0 | HV9: 1931 | HW9: MOVE S320 | HX9: =SUM(HJ9:HS9) -> 29477.37 | HY9: 748.08 | HZ9: 4357.14 | IA9: 0.42 | IB9: 0 | IC9: 0 | ID9: 0 | IE9: 0 | IF9: 6.14 | IG9: 1.3 | IH9: 0 | II9: =SUM(HY9:IH9) -> 5113.08 | IL9: =(HT9/$HT$116)*31846.83 -> 326.53429 | IM9: =(HU9/$O$116)*17321.85 -> 0 | IN9: =52000/60 -> 866.66667 | IO9: 20 | IP9: =24366/105 -> 232.05714 | IQ9: 5 | IR9: =IR$3 -> 445.62857 | IT9: =SUM(IJ9:IS9) -> 1895.8867 | IU9: =IU$3 -> 538.79476 | IW9: =(IU9+IV9)*30% -> 161.63843 | IX9: =SUM(IU9:IW9) -> 700.43319 | IY9: =IT9+IX9 -> 2596.3199 | IZ9: =II9-IY9 -> 2516.7601 | JA9: 11587.76 | JB9: 20195.99 | JC9: 19.8 | JD9: 0 | JE9: 0 | JF9: 0 | JG9: 0 | JH9: 95.75 | JI9: 64.6 | JJ9: 0 | JK9: 31963.9 | JL9: 0 | JM9: 1937 | JN9: MOVE S320 | JO9: =SUM(JA9:JJ9) -> 31963.9 | JP9: 964.61 | JQ9: 4357.14 | JR9: 1.26 | JS9: 0 | JT9: 0 | JU9: 0 | JV9: 0 | JW9: 6.58 | JX9: 3.59 | JY9: 0 | JZ9: =SUM(JP9:JY9) -> 5333.18 | KC9: =(JK9/$N$116)*39010.72 -> 644.73385 | KD9: =(JL9/$O$116)*19244.4 -> 0 | KE9: =52000/60 -> 866.66667 | KF9: 20 | KH9: 5 | KI9: =KI$3 -> 543.39953 | KK9: =SUM(KA9:KJ9) -> 2079.8 | KL9: =KL$3 -> 497.32093 | KN9: =(KL9+KM9)*30% -> 149.19628 | KO9: =SUM(KL9:KN9) -> 646.51721 | KP9: =KK9+KO9 -> 2726.3173 | KQ9: =JZ9-KP9 -> 2606.8627 | KR9: 13275.15 | KS9: 21085.36 | KT9: 6.6 | KU9: 0 | KV9: 0 | KW9: 0 | KX9: 0 | KY9: 62.74 | KZ9: 39.9 | LA9: 0 | LB9: 34469.75 | LC9: 0 | LD9: 1934 | LE9: MOVE S320 | LF9: =SUM(KR9:LA9) -> 34469.75 | LG9: 1105.07 | LH9: 4357.14 | LI9: 0.42 | LJ9: 0 | LK9: 0 | LL9: 0 | LM9: 0 | LN9: 4.36 | LO9: 2.22 | LP9: 0 | LQ9: =SUM(LG9:LP9) -> 5469.21 | LT9: =(LB9/$LB$116)*39133.48 -> 351.42351 | LU9: =(LC9/$O$116)*17015.75 -> 0 | LV9: =52000/60 -> 866.66667 | LW9: 20 | LY9: 5 | LZ9: =LZ$3 -> 508.03738 | MB9: =SUM(LR9:MA9) -> 1751.1276 | MC9: =MC$3 -> 593.54907 | ME9: =(MC9+MD9)*30% -> 178.06472 | MF9: =SUM(MC9:ME9) -> 771.61379 | MG9: =MB9+MF9 -> 2522.7413 | MH9: =LQ9-MG9 -> 2946.4687 | MI9: 9750.15 | MJ9: 14092.64 | MK9: 0 | ML9: 0 | MM9: 0 | MN9: 0 | MO9: 0 | MP9: 43.26 | MQ9: 9.5 | MR9: 0 | MS9: 23895.55 | MT9: 0 | MU9: 1359 | MV9: MOVE S320 | MW9: =SUM(MI9:MR9) -> 23895.55 | MX9: 811.63 | MY9: 4357.14 | MZ9: 0 | NA9: 0 | NB9: 0 | NC9: 0 | ND9: 0 | NE9: 3 | NF9: 0.53 | NG9: 0 | NH9: =SUM(MX9:NG9) -> 5172.3 | NK9: =(MS9/$N$116)*0 -> 0 | NL9: =(MT9/$O$116)*13804.26 -> 0 | NM9: =52000/60 -> 866.66667 | NN9: 20 | NP9: 5 | NQ9: =NQ$3 -> 469.6789 | NS9: =SUM(NI9:NR9) -> 1361.3456 | NT9: =78812.25/109 -> 723.04817 | NV9: =(NT9+NU9)*30% -> 216.91445 | NW9: =SUM(NT9:NV9) -> 939.96261 | NX9: =NS9+NW9 -> 2301.3082 | NY9: =NH9-NX9 -> 2870.9918 | NZ9: 10337.34 | OA9: 18920.48 | OB9: 18.7 | OC9: 0 | OD9: 0 | OE9: 0 | OF9: 0 | OG9: 37.1 | OH9: 11.4 | OI9: 0 | OJ9: 29325.02 | OK9: =ON9-OJ9 -> 0 | OL9: 1820 | OM9: MOVE S320 | ON9: =SUM(NZ9:OI9) -> 29325.02 | OO9: 860.53 | OP9: 4357.14 | OQ9: 1.19 | OR9: 0 | OS9: 0 | OT9: 0 | OU9: 0 | OV9: 2.58 | OW9: 0.63 | OX9: 0 | OY9: =SUM(OO9:OX9) -> 5222.07 | PB9: =(OJ9/$OJ$116)*56307.47 -> 634.10256 | PC9: =(OK9/$O$116)*16757.91 -> 0 | PD9: =52000/60 -> 866.66667 | PE9: 20 | PF9: =3288/100 -> 32.88 | PG9: 5 | PH9: =PH$3 -> 495.20491 | PJ9: =SUM(OZ9:PI9) -> 2053.8541 | PK9: =PK$3 -> 643.25573 | PM9: =(PK9+PL9)*30% -> 192.97672 | PN9: =SUM(PK9:PM9) -> 836.23245 | PO9: =PJ9+PN9 -> 2890.0866 | PP9: =OY9-PO9 -> 2331.9834 | PQ9: 11770.71 | PR9: 19663.21 | PS9: 6.6 | PT9: 0 | PU9: 0 | PV9: 0 | PW9: 0 | PX9: 124.5 | PY9: 29.13 | PZ9: 0 | QA9: 31594.15 | QB9: 0 | QC9: 1939 | QD9: MOVE S320 | QE9: =SUM(PQ9:PZ9) -> 31594.15 | QF9: 979.84 | QG9: 4357.14 | QH9: 0.42 | QI9: 0 | QJ9: 0 | QK9: 0 | QL9: 0 | QM9: 8.65 | QN9: 1.62 | QO9: 0 | QP9: =SUM(QF9:QO9) -> 5347.67 | QS9: =(QA9/$QA$116)*27743.06 -> 371.38942 | QT9: =(QB9/$O$116)*10429.01 -> 0 | QU9: =52000/60 -> 866.66667 | QV9: 20 | QW9: =2074.8/110 -> 18.861818 | QX9: 5 | QY9: =QY$3 -> 428.14773 | RA9: =SUM(QQ9:QZ9) -> 1710.0656 | RB9: =68119.05/110 -> 619.26409 | RD9: =(RB9+RC9)*30% -> 185.77923 | RE9: =SUM(RB9:RD9) -> 805.04332 | RF9: =RA9+RE9 -> 2515.109 | RG9: =QP9-RF9 -> 2832.561 | RH9: 11986.91 | RI9: 20896.9 | RJ9: 0 | RK9: 0 | RL9: 0 | RM9: 0 | RN9: 0 | RO9: 87.8 | RP9: 58.56 | RQ9: 0 | RR9: 33030.17 | RS9: 0 | RT9: 1967 | RU9: MOVE S320 | RV9: =SUM(RH9:RQ9) -> 33030.17 | RW9: 997.83 | RX9: 4357.14 | RY9: 0 | RZ9: 0 | SA9: 0 | SB9: 0 | SC9: 0 | SD9: 6.1 | SE9: 3.25 | SF9: 0 | SG9: 5364.32 | SJ9: =(RR9/$RR$116)*25115.94 -> 324.58438 | SK9: =(RS9/$O$116)*12319.54 -> 0 | SL9: =52000/60 -> 866.66667 | SM9: 20 | SN9: =56040/113 -> 495.9292 | SO9: 5 | SP9: =SP$3 -> 428.52876 | SR9: =SUM(SH9:SQ9) -> 2140.709 | SS9: =SS$3 -> 596.28469 | SU9: =(SS9+ST9)*30% -> 178.88541 | SV9: =SUM(SS9:SU9) -> 775.1701 | SW9: =SR9+SV9 -> 2915.8791 | SX9: =SG9-SW9 -> 2448.4409 | SY9: =Q9+BH9+CY9+EP9+GG9+HX9+JO9+LF9+MW9+ON9+QE9+RV9 -> 342784.74 | SZ9: =AB9+BS9+DJ9+FA9+GR9+II9+JZ9+LQ9+NH9+OY9+QP9+SG9 -> 62499.65 | TA9: =AR9+CI9+DZ9+FQ9+HH9+IY9+KP9+MG9+NX9+PO9+RF9+SW9 -> 28554.665 | TB9: =SZ9-TA9 -> 33944.985
A10: 1108 | B10: 1108_TCZEW | C10: MOVE S320 | D10: 5892.81 | E10: 15598.14 | F10: 0 | G10: 0 | H10: 0 | I10: 21.3 | J10: 0 | K10: 0 | L10: 0 | M10: 0 | N10: 21512.25 | O10: 0 | P10: 1467 | Q10: =SUM(D10:M10) -> 21512.25 | R10: 490.55 | S10: 4357.14 | T10: 0 | U10: 0 | V10: 0 | W10: 1.38 | X10: 0 | Y10: 0 | Z10: 0 | AA10: 0 | AB10: =SUM(R10:AA10) -> 4849.07 | AE10: =(N10/$N$116)*21028.32 -> 233.89835 | AF10: =(O10/$O$116)*15324.97 -> 0 | AH10: 20 | AJ10: 5 | AK10: =39081.75/95 -> 411.38684 | AM10: =SUM(AC10:AL10) -> 670.28519 | AN10: =61284.58/95 -> 645.10084 | AO10: 0 | AP10: =(AN10+AO10)*30% -> 193.53025 | AQ10: =SUM(AN10:AP10) -> 838.63109 | AR10: =AM10+AQ10 -> 1508.9163 | AS10: =AB10-AR10 -> 3340.1537 | AT10: 8649.74 | AU10: 17975.26 | AV10: 0 | AW10: 0 | AX10: 0 | AY10: 123.9 | AZ10: 0 | BA10: 0 | BB10: 0 | BC10: 0 | BD10: 26748.9 | BE10: 0 | BF10: 1853 | BG10: MOVE S320 | BH10: =SUM(AT10:BC10) -> 26748.9 | BI10: 720.04 | BJ10: 4357.14 | BK10: 0 | BL10: 0 | BM10: 0 | BN10: 8.05 | BO10: 0 | BP10: 0 | BQ10: 0 | BR10: 0 | BS10: =SUM(BI10:BR10) -> 5085.23 | BV10: =(BD10/$BD$116)*21083.85 -> 293.37432 | BW10: =(BE10/$O$116)*12925.76 -> 0 | BY10: 20 | CA10: 5 | CB10: =37537.5/96 -> 391.01562 | CD10: =SUM(BT10:CC10) -> 709.38994 | CE10: =63860.36/96 -> 665.21208 | CG10: =(CE10+CF10)*30% -> 199.56363 | CH10: =SUM(CE10:CG10) -> 864.77571 | CI10: =CD10+CH10 -> 1574.1657 | CJ10: =BS10-CI10 -> 3511.0643 | CK10: 10014.36 | CL10: 21230.76 | CM10: 14.87 | CN10: 0 | CO10: 4.72 | CP10: 93.65 | CQ10: 0 | CR10: 0 | CS10: 0 | CT10: 0 | CU10: 31358.36 | CV10: 0 | CW10: 2078 | CX10: MOVE S320 | CY10: =SUM(CK10:CT10) -> 31358.36 | CZ10: 833.63 | DA10: 4357.14 | DB10: 0.95 | DC10: 0 | DD10: 0.31 | DE10: 6.08 | DF10: 0 | DG10: 0 | DH10: 0 | DI10: 0 | DJ10: =SUM(CZ10:DI10) -> 5198.11 | DM10: =(CU10/$CU$116)*24055.75 -> 340.9092 | DN10: =(CV10/$O$116)*16258.02 -> 0 | DP10: 20 | DR10: 5 | DS10: =DS$3 -> 428.4697 | DU10: =SUM(DK10:DT10) -> 794.3789 | DV10: =DV$3 -> 596.35071 | DX10: =(DV10+DW10)*30% -> 178.90521 | DY10: =SUM(DV10:DX10) -> 775.25592 | DZ10: =DU10+DY10 -> 1569.6348 | EA10: =DJ10-DZ10 -> 3628.4752 | EB10: 13647.06 | EC10: 28009.72 | ED10: 0 | EE10: 0 | EF10: 0 | EG10: 261.25 | EH10: 0 | EI10: 0 | EJ10: 0 | EK10: 0 | EL10: 41918.03 | EM10: 0 | EN10: 2786 | EO10: MOVE S320 | EP10: =SUM(EB10:EK10) -> 41918.03 | EQ10: 1136.04 | ER10: 4357.14 | ES10: 0 | ET10: 0 | EU10: 0 | EV10: 16.97 | EW10: 0 | EX10: 0 | EY10: 0 | EZ10: 0 | FA10: =SUM(EQ10:EZ10) -> 5510.15 | FD10: =(EL10/$EL$116)*26325.65 -> 467.89118 | FE10: =(EM10/$O$116)*14846.27 -> 0 | FF10: =52000/60 -> 866.66667 | FG10: 20 | FH10: =14375.2/102 -> 140.93333 | FI10: 5 | FJ10: =FJ$3 -> 424.6802 | FL10: =SUM(FB10:FK10) -> 1925.1714 | FM10: =FM$3 -> 664.41902 | FO10: =(FM10+FN10)*30% -> 199.32571 | FP10: =SUM(FM10:FO10) -> 863.74473 | FQ10: =FL10+FP10 -> 2788.9161 | FR10: =FA10-FQ10 -> 2721.2339 | FS10: 13980.59 | FT10: 28457.32 | FU10: 0 | FV10: 0 | FW10: 0 | FX10: 398.3 | FY10: 0 | FZ10: 532.58 | GA10: 0 | GB10: 0 | GC10: 43368.79 | GD10: 0 | GE10: 2684 | GF10: MOVE S320 | GG10: =SUM(FS10:GB10) -> 43368.79 | GH10: 1163.8 | GI10: 4357.14 | GJ10: 0 | GK10: 0 | GL10: 0 | GM10: 25.87 | GN10: 0 | GO10: 36.98 | GP10: 0 | GQ10: 0 | GR10: =SUM(GH10:GQ10) -> 5583.79 | GU10: =(GC10/$GC$116)*30198.86 -> 480.58017 | GV10: =(GD10/$O$116)*16844.27 -> 0 | GW10: =52000/60 -> 866.66667 | GX10: 20 | GY10: =18860.4/102 -> 184.90588 | GZ10: 5 | HA10: =HA$3 -> 358.47794 | HC10: =SUM(GS10:HB10) -> 1915.6307 | HD10: =HD$3 -> 866.9202 | HF10: =(HD10+HE10)*30% -> 260.07606 | HG10: =SUM(HD10:HF10) -> 1126.9963 | HH10: =HC10+HG10 -> 3042.6269 | HI10: =GR10-HH10 -> 2541.1631 | HJ10: 9368.06 | HK10: 22305.76 | HL10: 0 | HM10: 0 | HN10: 7.5 | HO10: 165.6 | HP10: 0 | HQ10: 0 | HR10: 0 | HS10: 0 | HT10: 31846.92 | HU10: 0 | HV10: 2211 | HW10: MOVE S320 | HX10: =SUM(HJ10:HS10) -> 31846.92 | HY10: 779.84 | HZ10: 4357.14 | IA10: 0 | IB10: 0 | IC10: 0.49 | ID10: 10.76 | IE10: 0 | IF10: 0 | IG10: 0 | IH10: 0 | II10: =SUM(HY10:IH10) -> 5148.23 | IL10: =(HT10/$HT$116)*31846.83 -> 352.78288 | IM10: =(HU10/$O$116)*17321.85 -> 0 | IN10: =52000/60 -> 866.66667 | IO10: 20 | IP10: =24366/105 -> 232.05714 | IQ10: 5 | IR10: =IR$3 -> 445.62857 | IT10: =SUM(IJ10:IS10) -> 1922.1353 | IU10: =IU$3 -> 538.79476 | IW10: =(IU10+IV10)*30% -> 161.63843 | IX10: =SUM(IU10:IW10) -> 700.43319 | IY10: =IT10+IX10 -> 2622.5685 | IZ10: =II10-IY10 -> 2525.6615 | JA10: 10524.67 | JB10: 29859.27 | JC10: 0 | JD10: 0 | JE10: 6.5 | JF10: 280.55 | JG10: 0 | JH10: 0 | JI10: 0 | JJ10: 0 | JK10: 40670.99 | JL10: 0 | JM10: 2650 | JN10: MOVE S320 | JO10: =SUM(JA10:JJ10) -> 40670.99 | JP10: 876.11 | JQ10: 4357.14 | JR10: 0 | JS10: 0 | JT10: 0.42 | JU10: 18.22 | JV10: 0 | JW10: 0 | JX10: 0 | JY10: 0 | JZ10: =SUM(JP10:JY10) -> 5251.89 | KC10: =(JK10/$N$116)*39010.72 -> 820.36184 | KD10: =(JL10/$O$116)*19244.4 -> 0 | KE10: =52000/60 -> 866.66667 | KF10: 20 | KH10: 5 | KI10: =KI$3 -> 543.39953 | KK10: =SUM(KA10:KJ10) -> 2255.428 | KL10: =KL$3 -> 497.32093 | KN10: =(KL10+KM10)*30% -> 149.19628 | KO10: =SUM(KL10:KN10) -> 646.51721 | KP10: =KK10+KO10 -> 2901.9453 | KQ10: =JZ10-KP10 -> 2349.9447 | KR10: 13198.71 | KS10: 32103.74 | KT10: 0 | KU10: 0 | KV10: 0 | KW10: 357.5 | KX10: 0 | KY10: 0 | KZ10: 0 | LA10: 0 | LB10: 45659.95 | LC10: 0 | LD10: 2838 | LE10: MOVE S320 | LF10: =SUM(KR10:LA10) -> 45659.95 | LG10: 1098.7 | LH10: 4357.14 | LI10: 0 | LJ10: 0 | LK10: 0 | LL10: 23.22 | LM10: 0 | LN10: 0 | LO10: 0 | LP10: 0 | LQ10: =SUM(LG10:LP10) -> 5479.06 | LT10: =(LB10/$LB$116)*39133.48 -> 465.50903 | LU10: =(LC10/$O$116)*17015.75 -> 0 | LV10: =52000/60 -> 866.66667 | LW10: 20 | LY10: 5 | LZ10: =LZ$3 -> 508.03738 | MB10: =SUM(LR10:MA10) -> 1865.2131 | MC10: =MC$3 -> 593.54907 | ME10: =(MC10+MD10)*30% -> 178.06472 | MF10: =SUM(MC10:ME10) -> 771.61379 | MG10: =MB10+MF10 -> 2636.8269 | MH10: =LQ10-MG10 -> 2842.2331 | MI10: 8359.61 | MJ10: 21912.62 | MK10: 13.2 | ML10: 0 | MM10: 0 | MN10: 152.1 | MO10: 0 | MP10: 0 | MQ10: 0 | MR10: 0 | MS10: 30437.53 | MT10: 0 | MU10: 2110 | MV10: MOVE S320 | MW10: =SUM(MI10:MR10) -> 30437.53 | MX10: 695.89 | MY10: 4357.14 | MZ10: 0.84 | NA10: 0 | NB10: 0 | NC10: 9.88 | ND10: 0 | NE10: 0 | NF10: 0 | NG10: 0 | NH10: =SUM(MX10:NG10) -> 5063.75 | NK10: =(MS10/$N$116)*0 -> 0 | NL10: =(MT10/$O$116)*13804.26 -> 0 | NM10: =52000/60 -> 866.66667 | NN10: 20 | NP10: 5 | NQ10: =NQ$3 -> 469.6789 | NS10: =SUM(NI10:NR10) -> 1361.3456 | NT10: =78812.25/109 -> 723.04817 | NV10: =(NT10+NU10)*30% -> 216.91445 | NW10: =SUM(NT10:NV10) -> 939.96261 | NX10: =NS10+NW10 -> 2301.3082 | NY10: =NH10-NX10 -> 2762.4418 | NZ10: 9385.12 | OA10: 22465.36 | OB10: 0 | OC10: 0 | OD10: 0 | OE10: 218.8 | OF10: 0 | OG10: 22.43 | OH10: 0 | OI10: 0 | OJ10: 32091.71 | OK10: =ON10-OJ10 -> 0 | OL10: 2123 | OM10: MOVE S320 | ON10: =SUM(NZ10:OI10) -> 32091.71 | OO10: 781.26 | OP10: 4357.14 | OQ10: 0 | OR10: 0 | OS10: 0 | OT10: 14.21 | OU10: 0 | OV10: 1.56 | OW10: 0 | OX10: 0 | OY10: =SUM(OO10:OX10) -> 5154.17 | PB10: =(OJ10/$OJ$116)*56307.47 -> 693.92742 | PC10: =(OK10/$O$116)*16757.91 -> 0 | PD10: =52000/60 -> 866.66667 | PE10: 20 | PF10: =3288/100 -> 32.88 | PG10: 5 | PH10: =PH$3 -> 495.20491 | PJ10: =SUM(OZ10:PI10) -> 2113.679 | PK10: =PK$3 -> 643.25573 | PM10: =(PK10+PL10)*30% -> 192.97672 | PN10: =SUM(PK10:PM10) -> 836.23245 | PO10: =PJ10+PN10 -> 2949.9114 | PP10: =OY10-PO10 -> 2204.2586 | PQ10: 9521.86 | PR10: 18944.6 | PS10: 0 | PT10: 0 | PU10: 0 | PV10: 219.85 | PW10: 0 | PX10: 0 | PY10: 0 | PZ10: 0 | QA10: 28686.31 | QB10: 0 | QC10: 1828 | QD10: MOVE S320 | QE10: =SUM(PQ10:PZ10) -> 28686.31 | QF10: 792.64 | QG10: 4357.14 | QH10: 0 | QI10: 0 | QJ10: 0 | QK10: 14.28 | QL10: 0 | QM10: 0 | QN10: 0 | QO10: 0 | QP10: =SUM(QF10:QO10) -> 5164.06 | QS10: =(QA10/$QA$116)*27743.06 -> 337.20774 | QT10: =(QB10/$O$116)*10429.01 -> 0 | QU10: =52000/60 -> 866.66667 | QV10: 20 | QW10: =2074.8/110 -> 18.861818 | QX10: 5 | QY10: =QY$3 -> 428.14773 | RA10: =SUM(QQ10:QZ10) -> 1675.884 | RB10: =68119.05/110 -> 619.26409 | RD10: =(RB10+RC10)*30% -> 185.77923 | RE10: =SUM(RB10:RD10) -> 805.04332 | RF10: =RA10+RE10 -> 2480.9273 | RG10: =QP10-RF10 -> 2683.1327 | RH10: 9958.07 | RI10: 18143.65 | RJ10: 0 | RK10: 0 | RL10: 0 | RM10: 270.8 | RN10: 0 | RO10: 0 | RP10: 14.59 | RQ10: 0 | RR10: 28387.11 | RS10: 0 | RT10: 1899 | RU10: MOVE S320 | RV10: =SUM(RH10:RQ10) -> 28387.11 | RW10: 828.95 | RX10: 4357.14 | RY10: 0 | RZ10: 0 | SA10: 0 | SB10: 17.59 | SC10: 0 | SD10: 0 | SE10: 0.81 | SF10: 0 | SG10: 5204.49 | SJ10: =(RR10/$RR$116)*25115.94 -> 278.95746 | SK10: =(RS10/$O$116)*12319.54 -> 0 | SL10: =52000/60 -> 866.66667 | SM10: 20 | SN10: =56040/113 -> 495.9292 | SO10: 5 | SP10: =SP$3 -> 428.52876 | SR10: =SUM(SH10:SQ10) -> 2095.0821 | SS10: =SS$3 -> 596.28469 | SU10: =(SS10+ST10)*30% -> 178.88541 | SV10: =SUM(SS10:SU10) -> 775.1701 | SW10: =SR10+SV10 -> 2870.2522 | SX10: =SG10-SW10 -> 2334.2378 | SY10: =Q10+BH10+CY10+EP10+GG10+HX10+JO10+LF10+MW10+ON10+QE10+RV10 -> 402686.85 | SZ10: =AB10+BS10+DJ10+FA10+GR10+II10+JZ10+LQ10+NH10+OY10+QP10+SG10 -> 62692 | TA10: =AR10+CI10+DZ10+FQ10+HH10+IY10+KP10+MG10+NX10+PO10+RF10+SW10 -> 29247.999 | TB10: =SZ10-TA10 -> 33444.001
A11: 1109 | B11: 1109_JAROSW | C11: MOVE S320 | D11: 2745.84 | E11: 6252.53 | F11: 0 | G11: 0 | H11: 0 | I11: 0 | J11: 0 | K11: 0 | L11: 5 | M11: 0 | N11: 9003.37 | O11: 0 | P11: 818 | Q11: =SUM(D11:M11) -> 9003.37 | R11: 228.57 | S11: 4357.14 | T11: 0 | U11: 0 | V11: 0 | W11: 0 | X11: 0 | Y11: 0 | Z11: 0.28 | AA11: 0 | AB11: =SUM(R11:AA11) -> 4585.99 | AE11: =(N11/$N$116)*21028.32 -> 97.891823 | AF11: =(O11/$O$116)*15324.97 -> 0 | AH11: 20 | AJ11: 5 | AK11: =39081.75/95 -> 411.38684 | AM11: =SUM(AC11:AL11) -> 534.27866 | AN11: =61284.58/95 -> 645.10084 | AO11: 0 | AP11: =(AN11+AO11)*30% -> 193.53025 | AQ11: =SUM(AN11:AP11) -> 838.63109 | AR11: =AM11+AQ11 -> 1372.9098 | AS11: =AB11-AR11 -> 3213.0802 | AT11: 2965.26 | AU11: 5211.28 | AV11: 0 | AW11: 0 | AX11: 0 | AY11: 0 | AZ11: 0 | BA11: 0 | BB11: 0 | BC11: 0 | BD11: 8176.54 | BE11: 0 | BF11: 655 | BG11: MOVE S320 | BH11: =SUM(AT11:BC11) -> 8176.54 | BI11: 246.84 | BJ11: 4357.14 | BK11: 0 | BL11: 0 | BM11: 0 | BN11: 0 | BO11: 0 | BP11: 0 | BQ11: 0 | BR11: 0 | BS11: =SUM(BI11:BR11) -> 4603.98 | BV11: =(BD11/$BD$116)*21083.85 -> 89.677962 | BW11: =(BE11/$O$116)*12925.76 -> 0 | BY11: 20 | CA11: 5 | CB11: =37537.5/96 -> 391.01562 | CD11: =SUM(BT11:CC11) -> 505.69359 | CE11: =63860.36/96 -> 665.21208 | CG11: =(CE11+CF11)*30% -> 199.56363 | CH11: =SUM(CE11:CG11) -> 864.77571 | CI11: =CD11+CH11 -> 1370.4693 | CJ11: =BS11-CI11 -> 3233.5107 | CK11: 2508.44 | CL11: 6925.74 | CM11: 0 | CN11: 0 | CO11: 0 | CP11: 0 | CQ11: 0 | CR11: 0 | CS11: 0 | CT11: 0 | CU11: 9434.18 | CV11: 0 | CW11: 886 | CX11: MOVE S320 | CY11: =SUM(CK11:CT11) -> 9434.18 | CZ11: 208.81 | DA11: 4357.14 | DB11: 0 | DC11: 0 | DD11: 0 | DE11: 0 | DF11: 0 | DG11: 0 | DH11: 0 | DI11: 0 | DJ11: =SUM(CZ11:DI11) -> 4565.95 | DM11: =(CU11/$CU$116)*24055.75 -> 102.56272 | DN11: =(CV11/$O$116)*16258.02 -> 0 | DP11: 20 | DR11: 5 | DS11: =DS$3 -> 428.4697 | DU11: =SUM(DK11:DT11) -> 556.03242 | DV11: =DV$3 -> 596.35071 | DX11: =(DV11+DW11)*30% -> 178.90521 | DY11: =SUM(DV11:DX11) -> 775.25592 | DZ11: =DU11+DY11 -> 1331.2883 | EA11: =DJ11-DZ11 -> 3234.6617 | EB11: 2822.25 | EC11: 7198.07 | ED11: 0 | EE11: 0 | EF11: 0 | EG11: 0 | EH11: 0 | EI11: 0 | EJ11: 0 | EK11: 0 | EL11: 10020.32 | EM11: 0 | EN11: 881 | EO11: MOVE S320 | EP11: =SUM(EB11:EK11) -> 10020.32 | EQ11: 234.93 | ER11: 4357.14 | ES11: 0 | ET11: 0 | EU11: 0 | EV11: 0 | EW11: 0 | EX11: 0 | EY11: 0 | EZ11: 0 | FA11: =SUM(EQ11:EZ11) -> 4592.07 | FD11: =(EL11/$EL$116)*26325.65 -> 111.84732 | FE11: =(EM11/$O$116)*14846.27 -> 0 | FF11: =52000/60 -> 866.66667 | FG11: 20 | FH11: =14375.2/102 -> 140.93333 | FI11: 5 | FJ11: =FJ$3 -> 424.6802 | FL11: =SUM(FB11:FK11) -> 1569.1275 | FM11: =FM$3 -> 664.41902 | FO11: =(FM11+FN11)*30% -> 199.32571 | FP11: =SUM(FM11:FO11) -> 863.74473 | FQ11: =FL11+FP11 -> 2432.8722 | FR11: =FA11-FQ11 -> 2159.1978 | FS11: 3119.05 | FT11: 8342.35 | FU11: 0 | FV11: 0 | FW11: 0 | FX11: 0 | FY11: 0 | FZ11: 0 | GA11: 0 | GB11: 0 | GC11: 11461.4 | GD11: 0 | GE11: 898 | GF11: MOVE S320 | GG11: =SUM(FS11:GB11) -> 11461.4 | GH11: 259.63 | GI11: 4357.14 | GJ11: 0 | GK11: 0 | GL11: 0 | GM11: 0 | GN11: 0 | GO11: 0 | GP11: 0 | GQ11: 0 | GR11: =SUM(GH11:GQ11) -> 4616.77 | GU11: =(GC11/$GC$116)*30198.86 -> 127.00658 | GV11: =(GD11/$O$116)*16844.27 -> 0 | GX11: 20 | GY11: =18860.4/102 -> 184.90588 | GZ11: 5 | HA11: =HA$3 -> 358.47794 | HC11: =SUM(GS11:HB11) -> 695.3904 | HD11: =HD$3 -> 866.9202 | HF11: =(HD11+HE11)*30% -> 260.07606 | HG11: =SUM(HD11:HF11) -> 1126.9963 | HH11: =HC11+HG11 -> 1822.3867 | HI11: =GR11-HH11 -> 2794.3833 | HJ11: 3407.88 | HK11: 6957.48 | HL11: 0 | HM11: 0 | HN11: 0 | HO11: 0 | HP11: 0 | HQ11: 0 | HR11: 0 | HS11: 0 | HT11: 10365.36 | HU11: 0 | HV11: 857 | HW11: MOVE S320 | HX11: =SUM(HJ11:HS11) -> 10365.36 | HY11: 283.68 | HZ11: 4357.14 | IA11: 0 | IB11: 0 | IC11: 0 | ID11: 0 | IE11: 0 | IF11: 0 | IG11: 0 | IH11: 0 | II11: =SUM(HY11:IH11) -> 4640.82 | IL11: =(HT11/$HT$116)*31846.83 -> 114.82183 | IM11: =(HU11/$O$116)*17321.85 -> 0 | IN11: =52000/60 -> 866.66667 | IO11: 20 | IP11: =24366/105 -> 232.05714 | IQ11: 5 | IR11: =IR$3 -> 445.62857 | IT11: =SUM(IJ11:IS11) -> 1684.1742 | IU11: =IU$3 -> 538.79476 | IW11: =(IU11+IV11)*30% -> 161.63843 | IX11: =SUM(IU11:IW11) -> 700.43319 | IY11: =IT11+IX11 -> 2384.6074 | IZ11: =II11-IY11 -> 2256.2126 | JA11: 3251.93 | JB11: 6904.36 | JC11: 0 | JD11: 0 | JE11: 0 | JF11: 0 | JG11: 0 | JH11: 0 | JI11: 0 | JJ11: 0 | JK11: 10156.29 | JL11: 0 | JM11: 714 | JN11: MOVE S320 | JO11: =SUM(JA11:JJ11) -> 10156.29 | JP11: 270.7 | JQ11: 4357.14 | JR11: 0 | JS11: 0 | JT11: 0 | JU11: 0 | JV11: 0 | JW11: 0 | JX11: 0 | JY11: 0 | JZ11: =SUM(JP11:JY11) -> 4627.84 | KC11: =(JK11/$N$116)*39010.72 -> 204.85935 | KD11: =(JL11/$O$116)*19244.4 -> 0 | KE11: =52000/60 -> 866.66667 | KF11: 20 | KH11: 5 | KI11: =KI$3 -> 543.39953 | KK11: =SUM(KA11:KJ11) -> 1639.9256 | KL11: =KL$3 -> 497.32093 | KN11: =(KL11+KM11)*30% -> 149.19628 | KO11: =SUM(KL11:KN11) -> 646.51721 | KP11: =KK11+KO11 -> 2286.4428 | KQ11: =JZ11-KP11 -> 2341.3972 | KR11: 2544.34 | KS11: 6895.83 | KT11: 0 | KU11: 0 | KV11: 0 | KW11: 0 | KX11: 0 | KY11: 0 | KZ11: 0 | LA11: 0 | LB11: 9440.17 | LC11: 0 | LD11: 676 | LE11: MOVE S320 | LF11: =SUM(KR11:LA11) -> 9440.17 | LG11: 211.8 | LH11: 4357.14 | LI11: 0 | LJ11: 0 | LK11: 0 | LL11: 0 | LM11: 0 | LN11: 0 | LO11: 0 | LP11: 0 | LQ11: =SUM(LG11:LP11) -> 4568.94 | LT11: =(LB11/$LB$116)*39133.48 -> 96.24374 | LU11: =(LC11/$O$116)*17015.75 -> 0 | LV11: =52000/60 -> 866.66667 | LW11: 20 | LY11: 5 | LZ11: =LZ$3 -> 508.03738 | MB11: =SUM(LR11:MA11) -> 1495.9478 | MC11: =MC$3 -> 593.54907 | ME11: =(MC11+MD11)*30% -> 178.06472 | MF11: =SUM(MC11:ME11) -> 771.61379 | MG11: =MB11+MF11 -> 2267.5616 | MH11: =LQ11-MG11 -> 2301.3784 | MI11: 2115.54 | MJ11: 6334.32 | MK11: 0 | ML11: 0 | MM11: 0 | MN11: 0 | MO11: 0 | MP11: 0 | MQ11: 0 | MR11: 0 | MS11: 8449.86 | MT11: 0 | MU11: 698 | MV11: MOVE S320 | MW11: =SUM(MI11:MR11) -> 8449.86 | MX11: 176.1 | MY11: 4357.14 | MZ11: 0 | NA11: 0 | NB11: 0 | NC11: 0 | ND11: 0 | NE11: 0 | NF11: 0 | NG11: 0 | NH11: =SUM(MX11:NG11) -> 4533.24 | NK11: =(MS11/$N$116)*0 -> 0 | NL11: =(MT11/$O$116)*13804.26 -> 0 | NM11: =52000/60 -> 866.66667 | NN11: 20 | NP11: 5 | NQ11: =NQ$3 -> 469.6789 | NS11: =SUM(NI11:NR11) -> 1361.3456 | NT11: =78812.25/109 -> 723.04817 | NV11: =(NT11+NU11)*30% -> 216.91445 | NW11: =SUM(NT11:NV11) -> 939.96261 | NX11: =NS11+NW11 -> 2301.3082 | NY11: =NH11-NX11 -> 2231.9318 | NZ11: 2144.83 | OA11: 6730.28 | OB11: 0 | OC11: 0 | OD11: 0 | OE11: 0 | OF11: 0 | OG11: 0 | OH11: 0 | OI11: 0 | OJ11: 8875.11 | OK11: =ON11-OJ11 -> 0 | OL11: 801 | OM11: MOVE S320 | ON11: =SUM(NZ11:OI11) -> 8875.11 | OO11: 178.54 | OP11: 4357.14 | OQ11: 0 | OR11: 0 | OS11: 0 | OT11: 0 | OU11: 0 | OV11: 0 | OW11: 0 | OX11: 0 | OY11: =SUM(OO11:OX11) -> 4535.68 | PB11: =(OJ11/$OJ$116)*56307.47 -> 191.90882 | PC11: =(OK11/$O$116)*16757.91 -> 0 | PD11: =52000/60 -> 866.66667 | PE11: 20 | PF11: =3288/100 -> 32.88 | PG11: 5 | PH11: =PH$3 -> 495.20491 | PJ11: =SUM(OZ11:PI11) -> 1611.6604 | PK11: =PK$3 -> 643.25573 | PM11: =(PK11+PL11)*30% -> 192.97672 | PN11: =SUM(PK11:PM11) -> 836.23245 | PO11: =PJ11+PN11 -> 2447.8928 | PP11: =OY11-PO11 -> 2087.7872 | PQ11: 2376.46 | PR11: 6379.06 | PS11: 0 | PT11: 0 | PU11: 0 | PV11: 0 | PW11: 0 | PX11: 0 | PY11: 0 | PZ11: 0 | QA11: 8755.52 | QB11: 0 | QC11: 724 | QD11: MOVE S320 | QE11: =SUM(PQ11:PZ11) -> 8755.52 | QF11: 197.82 | QG11: 4357.14 | QH11: 0 | QI11: 0 | QJ11: 0 | QK11: 0 | QL11: 0 | QM11: 0 | QN11: 0 | QO11: 0 | QP11: =SUM(QF11:QO11) -> 4554.96 | QS11: =(QA11/$QA$116)*27743.06 -> 102.92119 | QT11: =(QB11/$O$116)*10429.01 -> 0 | QU11: =52000/60 -> 866.66667 | QV11: 20 | QW11: =2074.8/110 -> 18.861818 | QX11: 5 | QY11: =QY$3 -> 428.14773 | RA11: =SUM(QQ11:QZ11) -> 1441.5974 | RB11: =68119.05/110 -> 619.26409 | RD11: =(RB11+RC11)*30% -> 185.77923 | RE11: =SUM(RB11:RD11) -> 805.04332 | RF11: =RA11+RE11 -> 2246.6407 | RG11: =QP11-RF11 -> 2308.3193 | RH11: 2179.93 | RI11: 5911.01 | RJ11: 0 | RK11: 0 | RL11: 0 | RM11: 0 | RN11: 0 | RO11: 0 | RP11: 0 | RQ11: 0 | RR11: 8090.94 | RS11: 0 | RT11: 680 | RU11: MOVE S320 | RV11: =SUM(RH11:RQ11) -> 8090.94 | RW11: 181.46 | RX11: 4357.14 | RY11: 0 | RZ11: 0 | SA11: 0 | SB11: 0 | SC11: 0 | SD11: 0 | SE11: 0 | SF11: 0 | SG11: 4538.6 | SJ11: =(RR11/$RR$116)*25115.94 -> 79.508907 | SK11: =(RS11/$O$116)*12319.54 -> 0 | SL11: =52000/60 -> 866.66667 | SM11: 20 | SN11: =56040/113 -> 495.9292 | SO11: 5 | SP11: =SP$3 -> 428.52876 | SR11: =SUM(SH11:SQ11) -> 1895.6335 | SS11: =SS$3 -> 596.28469 | SU11: =(SS11+ST11)*30% -> 178.88541 | SV11: =SUM(SS11:SU11) -> 775.1701 | SW11: =SR11+SV11 -> 2670.8036 | SX11: =SG11-SW11 -> 1867.7964 | SY11: =Q11+BH11+CY11+EP11+GG11+HX11+JO11+LF11+MW11+ON11+QE11+RV11 -> 112229.06 | SZ11: =AB11+BS11+DJ11+FA11+GR11+II11+JZ11+LQ11+NH11+OY11+QP11+SG11 -> 54964.84 | TA11: =AR11+CI11+DZ11+FQ11+HH11+IY11+KP11+MG11+NX11+PO11+RF11+SW11 -> 24935.183 | TB11: =SZ11-TA11 -> 30029.657
A12: 1110 | B12: 1110_BIALYS | C12: MOVE S320 | D12: 2595.01 | E12: 4117.97 | F12: 0 | G12: 0 | H12: 0 | I12: 0 | J12: 0 | K12: 0 | L12: 0 | M12: 0 | N12: 6712.98 | O12: =Q12-N12 -> 0 | P12: 581 | Q12: =SUM(D12:M12) -> 6712.98 | R12: 216.01 | S12: 4357.14 | T12: 0 | U12: 0 | V12: 0 | W12: 0 | X12: 0 | Y12: 0 | Z12: 0 | AA12: 0 | AB12: =SUM(R12:AA12) -> 4573.15 | AE12: =(N12/$N$116)*21028.32 -> 72.988875 | AF12: =(O12/$O$116)*15324.97 -> 0 | AH12: 20 | AJ12: 0 | AK12: =39081.75/95 -> 411.38684 | AM12: =SUM(AC12:AL12) -> 504.37572 | AN12: =61284.58/95 -> 645.10084 | AO12: 0 | AP12: =(AN12+AO12)*30% -> 193.53025 | AQ12: =SUM(AN12:AP12) -> 838.63109 | AR12: =AM12+AQ12 -> 1343.0068 | AS12: =AB12-AR12 -> 3230.1432 | AT12: 3158.43 | AU12: 3509.99 | AV12: 0 | AW12: 0 | AX12: 0 | AY12: 0 | AZ12: 0 | BA12: 0 | BB12: 0 | BC12: 0 | BD12: 6668.42 | BE12: =BH12-BD12 -> 0 | BF12: 529 | BG12: MOVE S320 | BH12: =SUM(AT12:BC12) -> 6668.42 | BI12: 262.9 | BJ12: 4357.14 | BK12: 0 | BL12: 0 | BM12: 0 | BN12: 0 | BO12: 0 | BP12: 0 | BQ12: 0 | BR12: 0 | BS12: =SUM(BI12:BR12) -> 4620.04 | BV12: =(BD12/$BD$116)*21083.85 -> 73.137332 | BW12: =(BE12/$O$116)*12925.76 -> 0 | BY12: 20 | CA12: 5 | CB12: =37537.5/96 -> 391.01562 | CD12: =SUM(BT12:CC12) -> 489.15296 | CE12: =63860.36/96 -> 665.21208 | CG12: =(CE12+CF12)*30% -> 199.56363 | CH12: =SUM(CE12:CG12) -> 864.77571 | CI12: =CD12+CH12 -> 1353.9287 | CJ12: =BS12-CI12 -> 3266.1113 | CK12: 3176.9 | CL12: 3987.35 | CM12: 0 | CN12: 0 | CO12: 0 | CP12: 0 | CQ12: 0 | CR12: 0 | CS12: 0 | CT12: 0 | CU12: 7164.25 | CV12: =CY12-CU12 -> 0 | CW12: 576 | CX12: MOVE S320 | CY12: =SUM(CK12:CT12) -> 7164.25 | CZ12: 264.44 | DA12: 4357.14 | DB12: 0 | DC12: 0 | DD12: 0 | DE12: 0 | DF12: 0 | DG12: 0 | DH12: 0 | DI12: 0 | DJ12: =SUM(CZ12:DI12) -> 4621.58 | DM12: =(CU12/$CU$116)*24055.75 -> 77.88541 | DN12: =(CV12/$O$116)*16258.02 -> 0 | DP12: 20 | DR12: 5 | DS12: =DS$3 -> 428.4697 | DU12: =SUM(DK12:DT12) -> 531.35511 | DV12: =DV$3 -> 596.35071 | DX12: =(DV12+DW12)*30% -> 178.90521 | DY12: =SUM(DV12:DX12) -> 775.25592 | DZ12: =DU12+DY12 -> 1306.611 | EA12: =DJ12-DZ12 -> 3314.969 | EB12: 2741.24 | EC12: 4072.44 | ED12: 0 | EE12: 0 | EF12: 0 | EG12: 0 | EH12: 0 | EI12: 29.3 | EJ12: 0 | EK12: 0 | EL12: 6842.98 | EM12: =EP12-EL12 -> 0 | EN12: 570 | EO12: MOVE S320 | EP12: =SUM(EB12:EK12) -> 6842.98 | EQ12: 228.18 | ER12: 4357.14 | ES12: 0 | ET12: 0 | EU12: 0 | EV12: 0 | EW12: 0 | EX12: 2.03 | EY12: 0 | EZ12: 0 | FA12: =SUM(EQ12:EZ12) -> 4587.35 | FD12: =(EL12/$EL$116)*26325.65 -> 76.381691 | FE12: =(EM12/$O$116)*14846.27 -> 0 | FF12: =52000/60 -> 866.66667 | FG12: 20 | FH12: =14375.2/102 -> 140.93333 | FI12: 5 | FJ12: =FJ$3 -> 424.6802 | FL12: =SUM(FB12:FK12) -> 1533.6619 | FM12: =FM$3 -> 664.41902 | FO12: =(FM12+FN12)*30% -> 199.32571 | FP12: =SUM(FM12:FO12) -> 863.74473 | FQ12: =FL12+FP12 -> 2397.4066 | FR12: =FA12-FQ12 -> 2189.9434 | FS12: 3800.73 | FT12: 4693.02 | FU12: 0 | FV12: 0 | FW12: 0 | FX12: 0 | FY12: 0 | FZ12: 0 | GA12: 0 | GB12: 0 | GC12: 8493.75 | GD12: =GG12-GC12 -> 0 | GE12: 658 | GF12: MOVE S320 | GG12: =SUM(FS12:GB12) -> 8493.75 | GH12: 316.37 | GI12: 4357.14 | GJ12: 0 | GK12: 0 | GL12: 0 | GM12: 0 | GN12: 0 | GO12: 0 | GP12: 0 | GQ12: 0 | GR12: =SUM(GH12:GQ12) -> 4673.51 | GU12: =(GC12/$GC$116)*30198.86 -> 94.121321 | GV12: =(GD12/$O$116)*16844.27 -> 0 | GX12: 20 | GY12: =18860.4/102 -> 184.90588 | GZ12: 5 | HA12: =HA$3 -> 358.47794 | HC12: =SUM(GS12:HB12) -> 662.50514 | HD12: =HD$3 -> 866.9202 | HF12: =(HD12+HE12)*30% -> 260.07606 | HG12: =SUM(HD12:HF12) -> 1126.9963 | HH12: =HC12+HG12 -> 1789.5014 | HI12: =GR12-HH12 -> 2884.0086 | HJ12: 4346.3 | HK12: 5685.81 | HL12: 0 | HM12: 0 | HN12: 0 | HO12: 0 | HP12: 0 | HQ12: 0 | HR12: 0 | HS12: 0 | HT12: 10032.11 | HU12: =HX12-HT12 -> 0 | HV12: 775 | HW12: MOVE S320 | HX12: =SUM(HJ12:HS12) -> 10032.11 | HY12: 361.78 | HZ12: 4357.14 | IA12: 0 | IB12: 0 | IC12: 0 | ID12: 0 | IE12: 0 | IF12: 0 | IG12: 0 | IH12: 0 | II12: =SUM(HY12:IH12) -> 4718.92 | IL12: =(HT12/$HT$116)*31846.83 -> 111.13027 | IM12: =(HU12/$O$116)*17321.85 -> 0 | IN12: =52000/60 -> 866.66667 | IO12: 20 | IP12: =24366/105 -> 232.05714 | IQ12: 5 | IR12: =IR$3 -> 445.62857 | IT12: =SUM(IJ12:IS12) -> 1680.4826 | IU12: =IU$3 -> 538.79476 | IW12: =(IU12+IV12)*30% -> 161.63843 | IX12: =SUM(IU12:IW12) -> 700.43319 | IY12: =IT12+IX12 -> 2380.9158 | IZ12: =II12-IY12 -> 2338.0042 | JA12: 4088.63 | JB12: 5661.39 | JC12: 0 | JD12: 0 | JE12: 0 | JF12: 0 | JG12: 0 | JH12: 0 | JI12: 0 | JJ12: 0 | JK12: 9750.02 | JL12: =JO12-JK12 -> 0 | JM12: 763 | JN12: MOVE S320 | JO12: =SUM(JA12:JJ12) -> 9750.02 | JP12: 340.33 | JQ12: 4357.14 | JR12: 0 | JS12: 0 | JT12: 0 | JU12: 0 | JV12: 0 | JW12: 0 | JX12: 0 | JY12: 0 | JZ12: =SUM(JP12:JY12) -> 4697.47 | KC12: =(JK12/$N$116)*39010.72 -> 196.66461 | KD12: =(JL12/$O$116)*19244.4 -> 0 | KE12: =52000/60 -> 866.66667 | KF12: 20 | KH12: 5 | KI12: =KI$3 -> 543.39953 | KK12: =SUM(KA12:KJ12) -> 1631.7308 | KL12: =KL$3 -> 497.32093 | KN12: =(KL12+KM12)*30% -> 149.19628 | KO12: =SUM(KL12:KN12) -> 646.51721 | KP12: =KK12+KO12 -> 2278.248 | KQ12: =JZ12-KP12 -> 2419.222 | KR12: 5037.03 | KS12: 6365.12 | KT12: 0 | KU12: 0 | KV12: 0 | KW12: 0 | KX12: 0 | KY12: 15.21 | KZ12: 0 | LA12: 0 | LB12: 11417.36 | LC12: =LF12-LB12 -> 0 | LD12: 750 | LE12: MOVE S320 | LF12: =SUM(KR12:LA12) -> 11417.36 | LG12: 419.29 | LH12: 4357.14 | LI12: 0 | LJ12: 0 | LK12: 0 | LL12: 0 | LM12: 0 | LN12: 1.06 | LO12: 0 | LP12: 0 | LQ12: =SUM(LG12:LP12) -> 4777.49 | LT12: =(LB12/$LB$116)*39133.48 -> 116.40145 | LU12: =(LC12/$O$116)*17015.75 -> 0 | LV12: =52000/60 -> 866.66667 | LW12: 20 | LY12: 5 | LZ12: =LZ$3 -> 508.03738 | MB12: =SUM(LR12:MA12) -> 1516.1055 | MC12: =MC$3 -> 593.54907 | ME12: =(MC12+MD12)*30% -> 178.06472 | MF12: =SUM(MC12:ME12) -> 771.61379 | MG12: =MB12+MF12 -> 2287.7193 | MH12: =LQ12-MG12 -> 2489.7707 | MI12: 4068.26 | MJ12: 4699.96 | MK12: 0 | ML12: 0 | MM12: 0 | MN12: 0 | MO12: 0 | MP12: 0 | MQ12: 0 | MR12: 0 | MS12: 8768.22 | MT12: =MW12-MS12 -> 0 | MU12: 713 | MV12: MOVE S320 | MW12: =SUM(MI12:MR12) -> 8768.22 | MX12: 338.65 | MY12: 4357.14 | MZ12: 0 | NA12: 0 | NB12: 0 | NC12: 0 | ND12: 0 | NE12: 0 | NF12: 0 | NG12: 0 | NH12: =SUM(MX12:NG12) -> 4695.79 | NK12: =(MS12/$N$116)*0 -> 0 | NL12: =(MT12/$O$116)*13804.26 -> 0 | NN12: 20 | NP12: 0 | NQ12: =NQ$3 -> 469.6789 | NS12: =SUM(NI12:NR12) -> 489.6789 | NT12: =78812.25/109 -> 723.04817 | NV12: =(NT12+NU12)*30% -> 216.91445 | NW12: =SUM(NT12:NV12) -> 939.96261 | NX12: =NS12+NW12 -> 1429.6415 | NY12: =NH12-NX12 -> 3266.1485 | NZ12: 2302.66 | OA12: 4350.07 | OB12: 0 | OC12: 0 | OD12: 0 | OE12: 0 | OF12: 0 | OG12: 0 | OH12: 0 | OI12: 0 | OJ12: 6652.73 | OK12: =ON12-OJ12 -> 0 | OL12: 645 | OM12: MOVE S320 | ON12: =SUM(NZ12:OI12) -> 6652.73 | OO12: 191.67 | OP12: 4357.14 | OQ12: 0 | OR12: 0 | OS12: 0 | OT12: 0 | OU12: 0 | OV12: 0 | OW12: 0 | OX12: 0 | OY12: =SUM(OO12:OX12) -> 4548.81 | PB12: =(OJ12/$OJ$116)*56307.47 -> 143.85372 | PC12: =(OK12/$O$116)*16757.91 -> 0 | PD12: =52000/60 -> 866.66667 | PE12: 20 | PF12: =3288/100 -> 32.88 | PG12: 5 | PH12: =PH$3 -> 495.20491 | PJ12: =SUM(OZ12:PI12) -> 1563.6053 | PK12: =PK$3 -> 643.25573 | PM12: =(PK12+PL12)*30% -> 192.97672 | PN12: =SUM(PK12:PM12) -> 836.23245 | PO12: =PJ12+PN12 -> 2399.8377 | PP12: =OY12-PO12 -> 2148.9723 | PQ12: 2888.27 | PR12: 4547.89 | PS12: 0 | PT12: 0 | PU12: 0 | PV12: 0 | PW12: 0 | PX12: 0 | PY12: 0 | PZ12: 0 | QA12: 7436.16 | QB12: =QE12-QA12 -> 0 | QC12: 664 | QD12: MOVE S320 | QE12: =SUM(PQ12:PZ12) -> 7436.16 | QF12: 240.42 | QG12: 4357.14 | QH12: 0 | QI12: 0 | QJ12: 0 | QK12: 0 | QL12: 0 | QM12: 0 | QN12: 0 | QO12: 0 | QP12: =SUM(QF12:QO12) -> 4597.56 | QS12: =(QA12/$QA$116)*27743.06 -> 87.412105 | QT12: =(QB12/$O$116)*10429.01 -> 0 | QU12: =52000/60 -> 866.66667 | QV12: 20 | QW12: =2074.8/110 -> 18.861818 | QX12: 5 | QY12: =QY$3 -> 428.14773 | RA12: =SUM(QQ12:QZ12) -> 1426.0883 | RB12: =68119.05/110 -> 619.26409 | RD12: =(RB12+RC12)*30% -> 185.77923 | RE12: =SUM(RB12:RD12) -> 805.04332 | RF12: =RA12+RE12 -> 2231.1316 | RG12: =QP12-RF12 -> 2366.4284 | RH12: 1620.56 | RI12: 4913.15 | RJ12: 13.06 | RK12: 0 | RL12: 0 | RM12: 0 | RN12: 0 | RO12: 0 | RP12: 0 | RQ12: 0 | RR12: 6546.77 | RS12: =RV12-RR12 -> 0 | RT12: 659 | RU12: MOVE S320 | RV12: =SUM(RH12:RQ12) -> 6546.77 | RW12: 134.89 | RX12: 4357.14 | RY12: 0.83 | RZ12: 0 | SA12: 0 | SB12: 0 | SC12: 0 | SD12: 0 | SE12: 0 | SF12: 0 | SG12: 4492.86 | SJ12: =(RR12/$RR$116)*25115.94 -> 64.334494 | SK12: =(RS12/$O$116)*12319.54 -> 0 | SL12: =52000/60 -> 866.66667 | SM12: 20 | SN12: =56040/113 -> 495.9292 | SO12: 5 | SP12: =SP$3 -> 428.52876 | SR12: =SUM(SH12:SQ12) -> 1880.4591 | SS12: =SS$3 -> 596.28469 | SU12: =(SS12+ST12)*30% -> 178.88541 | SV12: =SUM(SS12:SU12) -> 775.1701 | SW12: =SR12+SV12 -> 2655.6292 | SX12: =SG12-SW12 -> 1837.2308 | SY12: =Q12+BH12+CY12+EP12+GG12+HX12+JO12+LF12+MW12+ON12+QE12+RV12 -> 96485.75 | SZ12: =AB12+BS12+DJ12+FA12+GR12+II12+JZ12+LQ12+NH12+OY12+QP12+SG12 -> 55604.53 | TA12: =AR12+CI12+DZ12+FQ12+HH12+IY12+KP12+MG12+NX12+PO12+RF12+SW12 -> 23853.578 | TB12: =SZ12-TA12 -> 31750.952
A13: 1111 | B13: 1111_PUCK | C13: MOVE S320 | D13: 0 | E13: 0 | F13: 0 | G13: 0 | H13: 0 | I13: 0 | J13: 0 | K13: 0 | L13: 0 | M13: 0 | N13: 0 | O13: =Q13-N13 -> 0 | P13: 0 | Q13: =SUM(D13:M13) -> 0 | R13: 0 | S13: 0 | T13: 0 | U13: 0 | V13: 0 | W13: 0 | X13: 0 | Y13: 0 | Z13: 0 | AA13: 0 | AB13: =SUM(R13:AA13) -> 0 | AE13: =(N13/$N$116)*21028.32 -> 0 | AF13: =(O13/$O$116)*15324.97 -> 0 | AH13: 0 | AJ13: 0 | AM13: =SUM(AC13:AL13) -> 0 | AO13: 0 | AP13: =(AN13+AO13)*30% -> 0 | AQ13: =SUM(AN13:AP13) -> 0 | AR13: =AM13+AQ13 -> 0 | AS13: =AB13-AR13 -> 0 | BE13: =BH13-BD13 -> 0 | BG13: MOVE S320 | BH13: =SUM(AT13:BC13) -> 0 | BS13: =SUM(BI13:BR13) -> 0 | BV13: =(BD13/$BD$116)*21083.85 -> 0 | BW13: =(BE13/$O$116)*12925.76 -> 0 | CD13: =SUM(BT13:CC13) -> 0 | CG13: =(CE13+CF13)*30% -> 0 | CH13: =SUM(CE13:CG13) -> 0 | CI13: =CD13+CH13 -> 0 | CJ13: =BS13-CI13 -> 0 | CK13: 0 | CL13: 620.62 | CM13: 0 | CN13: 0 | CO13: 0 | CP13: 0 | CQ13: 0 | CR13: 0 | CS13: 0 | CT13: 0 | CU13: 620.62 | CV13: =CY13-CU13 -> 0 | CW13: 46 | CX13: MOVE S320 | CY13: =SUM(CK13:CT13) -> 620.62 | CZ13: 0 | DA13: 338.71 | DB13: 0 | DC13: 0 | DD13: 0 | DE13: 0 | DF13: 0 | DG13: 0 | DH13: 0 | DI13: 0 | DJ13: =SUM(CZ13:DI13) -> 338.71 | DM13: =(CU13/$CU$116)*24055.75 -> 6.7470068 | DN13: =(CV13/$O$116)*16258.02 -> 0 | DP13: 20 | DR13: 5 | DS13: =DS$3 -> 428.4697 | DU13: =SUM(DK13:DT13) -> 460.2167 | DV13: =DV$3 -> 596.35071 | DX13: =(DV13+DW13)*30% -> 178.90521 | DY13: =SUM(DV13:DX13) -> 775.25592 | DZ13: =DU13+DY13 -> 1235.4726 | EA13: =DJ13-DZ13 -> -896.76262 | EB13: 443.52 | EC13: 4937.55 | ED13: 0 | EE13: 0 | EF13: 0 | EG13: 0 | EH13: 0 | EI13: 0 | EJ13: 0 | EK13: 0 | EL13: 5381.07 | EM13: =EP13-EL13 -> 0 | EN13: 377 | EO13: MOVE S320 | EP13: =SUM(EB13:EK13) -> 5381.07 | EQ13: 36.92 | ER13: 3500 | ES13: 0 | ET13: 0 | EU13: 0 | EV13: 0 | EW13: 0 | EX13: 0 | EY13: 0 | EZ13: 0 | FA13: =SUM(EQ13:EZ13) -> 3536.92 | FD13: =(EL13/$EL$116)*26325.65 -> 60.063777 | FE13: =(EM13/$O$116)*14846.27 -> 0 | FG13: 20 | FH13: =14375.2/102 -> 140.93333 | FI13: 5 | FJ13: =FJ$3 -> 424.6802 | FL13: =SUM(FB13:FK13) -> 650.67731 | FM13: =FM$3 -> 664.41902 | FO13: =(FM13+FN13)*30% -> 199.32571 | FP13: =SUM(FM13:FO13) -> 863.74473 | FQ13: =FL13+FP13 -> 1514.422 | FR13: =FA13-FQ13 -> 2022.498 | FS13: 102.4 | FT13: 7149.2 | FU13: 0 | FV13: 0 | FW13: 0 | FX13: 0 | FY13: 0 | FZ13: 33.3 | GA13: 0 | GB13: 0 | GC13: 7284.9 | GD13: =GG13-GC13 -> 0 | GE13: 456 | GF13: MOVE S320 | GG13: =SUM(FS13:GB13) -> 7284.9 | GH13: 8.52 | GI13: 3500 | GJ13: 0 | GK13: 0 | GL13: 0 | GM13: 0 | GN13: 0 | GO13: 2.31 | GP13: 0 | GQ13: 0 | GR13: =SUM(GH13:GQ13) -> 3510.83 | GU13: =(GC13/$GC$116)*30198.86 -> 80.725759 | GV13: =(GD13/$O$116)*16844.27 -> 0 | GX13: 20 | GY13: =18860.4/102 -> 184.90588 | GZ13: 5 | HA13: =HA$3 -> 358.47794 | HC13: =SUM(GS13:HB13) -> 649.10958 | HD13: =HD$3 -> 866.9202 | HF13: =(HD13+HE13)*30% -> 260.07606 | HG13: =SUM(HD13:HF13) -> 1126.9963 | HH13: =HC13+HG13 -> 1776.1058 | HI13: =GR13-HH13 -> 1734.7242 | HJ13: 219.33 | HK13: 4603.4 | HL13: 0 | HM13: 0 | HN13: 0 | HO13: 0 | HP13: 0 | HQ13: 0 | HR13: 0 | HS13: 0 | HT13: 4822.73 | HU13: =HX13-HT13 -> 0 | HV13: 325 | HW13: MOVE S320 | HX13: =SUM(HJ13:HS13) -> 4822.73 | HY13: 18.26 | HZ13: 3500 | IA13: 0 | IB13: 0 | IC13: 0 | ID13: 0 | IE13: 0 | IF13: 0 | IG13: 0 | IH13: 0 | II13: =SUM(HY13:IH13) -> 3518.26 | IL13: =(HT13/$HT$116)*31846.83 -> 53.423583 | IM13: =(HU13/$O$116)*17321.85 -> 0 | IO13: 20 | IP13: =24366/105 -> 232.05714 | IQ13: 5 | IR13: =IR$3 -> 445.62857 | IT13: =SUM(IJ13:IS13) -> 756.1093 | IU13: =IU$3 -> 538.79476 | IW13: =(IU13+IV13)*30% -> 161.63843 | IX13: =SUM(IU13:IW13) -> 700.43319 | IY13: =IT13+IX13 -> 1456.5425 | IZ13: =II13-IY13 -> 2061.7175 | JA13: 1547.12 | JB13: 10294.14 | JC13: 0 | JD13: 0 | JE13: 0 | JF13: 0 | JG13: 0 | JH13: 0 | JI13: 0 | JJ13: 0 | JK13: 11841.26 | JL13: =JO13-JK13 -> 0 | JM13: 610 | JN13: MOVE S320 | JO13: =SUM(JA13:JJ13) -> 11841.26 | JP13: 128.78 | JQ13: 3500 | JR13: 0 | JS13: 0 | JT13: 0 | JU13: 0 | JV13: 0 | JW13: 0 | JX13: 0 | JY13: 0 | JZ13: =SUM(JP13:JY13) -> 3628.78 | KC13: =(JK13/$N$116)*39010.72 -> 238.84636 | KD13: =(JL13/$O$116)*19244.4 -> 0 | KF13: 20 | KH13: 5 | KI13: =KI$3 -> 543.39953 | KK13: =SUM(KA13:KJ13) -> 807.24589 | KL13: =KL$3 -> 497.32093 | KN13: =(KL13+KM13)*30% -> 149.19628 | KO13: =SUM(KL13:KN13) -> 646.51721 | KP13: =KK13+KO13 -> 1453.7631 | KQ13: =JZ13-KP13 -> 2175.0169 | KR13: 1207.26 | KS13: 13285.01 | KT13: 0 | KU13: 0 | KV13: 0 | KW13: 0 | KX13: 0 | KY13: 0 | KZ13: 0 | LA13: 0 | LB13: 14492.27 | LC13: =LF13-LB13 -> 0 | LD13: 678 | LE13: MOVE S320 | LF13: =SUM(KR13:LA13) -> 14492.27 | LG13: 100.49 | LH13: 3500 | LI13: 0 | LJ13: 0 | LK13: 0 | LL13: 0 | LM13: 0 | LN13: 0 | LO13: 0 | LP13: 0 | LQ13: =SUM(LG13:LP13) -> 3600.49 | LT13: =(LB13/$LB$116)*39133.48 -> 147.75055 | LU13: =(LC13/$O$116)*17015.75 -> 0 | LV13: =52000/60 -> 866.66667 | LW13: 20 | LY13: 5 | LZ13: =LZ$3 -> 508.03738 | MB13: =SUM(LR13:MA13) -> 1547.4546 | MC13: =MC$3 -> 593.54907 | ME13: =(MC13+MD13)*30% -> 178.06472 | MF13: =SUM(MC13:ME13) -> 771.61379 | MG13: =MB13+MF13 -> 2319.0684 | MH13: =LQ13-MG13 -> 1281.4216 | MI13: 146 | MJ13: 4074 | MK13: 0 | ML13: 0 | MM13: 0 | MN13: 0 | MO13: 0 | MP13: 0 | MQ13: 0 | MR13: 0 | MS13: 4220 | MT13: =MW13-MS13 -> 0 | MU13: 296 | MV13: MOVE S320 | MW13: =SUM(MI13:MR13) -> 4220 | MX13: 12.15 | MY13: 3500 | MZ13: 0 | NA13: 0 | NB13: 0 | NC13: 0 | ND13: 0 | NE13: 0 | NF13: 0 | NG13: 0 | NH13: =SUM(MX13:NG13) -> 3512.15 | NK13: =(MS13/$N$116)*0 -> 0 | NL13: =(MT13/$O$116)*13804.26 -> 0 | NN13: 0 | NP13: 0 | NQ13: =NQ$3 -> 469.6789 | NS13: =SUM(NI13:NR13) -> 469.6789 | NT13: =78812.25/109 -> 723.04817 | NV13: =(NT13+NU13)*30% -> 216.91445 | NW13: =SUM(NT13:NV13) -> 939.96261 | NX13: =NS13+NW13 -> 1409.6415 | NY13: =NH13-NX13 -> 2102.5085 | NZ13: 205.36 | OA13: 4173.1 | OB13: 0 | OC13: 0 | OD13: 0 | OE13: 0 | OF13: 0 | OG13: 0 | OH13: 0 | OI13: 0 | OJ13: 4378.46 | OK13: =ON13-OJ13 -> 0 | OL13: 277 | OM13: MOVE S320 | ON13: =SUM(NZ13:OI13) -> 4378.46 | OO13: 17.09 | OP13: 3500 | OQ13: 0 | OR13: 0 | OS13: 0 | OT13: 0 | OU13: 0 | OV13: 0 | OW13: 0 | OX13: 0 | OY13: =SUM(OO13:OX13) -> 3517.09 | PB13: =(OJ13/$OJ$116)*56307.47 -> 94.676583 | PC13: =(OK13/$O$116)*16757.91 -> 0 | PD13: =52000/60 -> 866.66667 | PE13: 20 | PF13: =3288/100 -> 32.88 | PG13: 5 | PH13: =PH$3 -> 495.20491 | PJ13: =SUM(OZ13:PI13) -> 1514.4282 | PK13: =PK$3 -> 643.25573 | PM13: =(PK13+PL13)*30% -> 192.97672 | PN13: =SUM(PK13:PM13) -> 836.23245 | PO13: =PJ13+PN13 -> 2350.6606 | PP13: =OY13-PO13 -> 1166.4294 | PQ13: 72 | PR13: 3040.91 | PS13: 0 | PT13: 0 | PU13: 0 | PV13: 0 | PW13: 0 | PX13: 0 | PY13: 0 | PZ13: 0 | QA13: 3112.91 | QB13: =QE13-QA13 -> 0 | QC13: 243 | QD13: MOVE S320 | QE13: =SUM(PQ13:PZ13) -> 3112.91 | QF13: 5.99 | QG13: 3500 | QH13: 0 | QI13: 0 | QJ13: 0 | QK13: 0 | QL13: 0 | QM13: 0 | QN13: 0 | QO13: 0 | QP13: =SUM(QF13:QO13) -> 3505.99 | QS13: =(QA13/$QA$116)*27743.06 -> 36.592275 | QT13: =(QB13/$O$116)*10429.01 -> 0 | QU13: =52000/60 -> 866.66667 | QV13: 20 | QW13: =2074.8/110 -> 18.861818 | QX13: 5 | QY13: =QY$3 -> 428.14773 | RA13: =SUM(QQ13:QZ13) -> 1375.2685 | RB13: =68119.05/110 -> 619.26409 | RD13: =(RB13+RC13)*30% -> 185.77923 | RE13: =SUM(RB13:RD13) -> 805.04332 | RF13: =RA13+RE13 -> 2180.3118 | RG13: =QP13-RF13 -> 1325.6782 | RH13: 240 | RI13: 2554.51 | RJ13: 0 | RK13: 0 | RL13: 0 | RM13: 0 | RN13: 0 | RO13: 0 | RP13: 0 | RQ13: 0 | RR13: 2794.51 | RS13: =RV13-RR13 -> 0 | RT13: 230 | RU13: MOVE S320 | RV13: =SUM(RH13:RQ13) -> 2794.51 | RW13: 19.98 | RX13: 3500 | RY13: 0 | RZ13: 0 | SA13: 0 | SB13: 0 | SC13: 0 | SD13: 0 | SE13: 0 | SF13: 0 | SG13: 3519.98 | SJ13: =(RR13/$RR$116)*25115.94 -> 27.461387 | SK13: =(RS13/$O$116)*12319.54 -> 0 | SL13: =52000/60 -> 866.66667 | SM13: 20 | SN13: =56040/113 -> 495.9292 | SO13: 5 | SP13: =SP$3 -> 428.52876 | SR13: =SUM(SH13:SQ13) -> 1843.586 | SS13: =SS$3 -> 596.28469 | SU13: =(SS13+ST13)*30% -> 178.88541 | SV13: =SUM(SS13:SU13) -> 775.1701 | SW13: =SR13+SV13 -> 2618.7561 | SX13: =SG13-SW13 -> 901.22388 | SY13: =Q13+BH13+CY13+EP13+GG13+HX13+JO13+LF13+MW13+ON13+QE13+RV13 -> 58948.73 | SZ13: =AB13+BS13+DJ13+FA13+GR13+II13+JZ13+LQ13+NH13+OY13+QP13+SG13 -> 32189.2 | TA13: =AR13+CI13+DZ13+FQ13+HH13+IY13+KP13+MG13+NX13+PO13+RF13+SW13 -> 18314.745 | TB13: =SZ13-TA13 -> 13874.455
A14: 1112 | B14: 1112_CHOJN | C14: MOVE S320 | D14: 0 | E14: 0 | F14: 0 | G14: 0 | H14: 0 | I14: 0 | J14: 0 | K14: 0 | L14: 0 | M14: 0 | N14: 0 | O14: =Q14-N14 -> 0 | P14: 0 | Q14: =SUM(D14:M14) -> 0 | R14: 0 | S14: 0 | T14: 0 | U14: 0 | V14: 0 | W14: 0 | X14: 0 | Y14: 0 | Z14: 0 | AA14: 0 | AB14: =SUM(R14:AA14) -> 0 | AE14: =(N14/$N$116)*21028.32 -> 0 | AF14: =(O14/$O$116)*15324.97 -> 0 | AH14: 0 | AJ14: 0 | AM14: =SUM(AC14:AL14) -> 0 | AO14: 0 | AP14: =(AN14+AO14)*30% -> 0 | AQ14: =SUM(AN14:AP14) -> 0 | AR14: =AM14+AQ14 -> 0 | AS14: =AB14-AR14 -> 0 | AT14: 571.63 | AU14: 3145.9 | AV14: 37 | AW14: 0 | AX14: 1235.62 | AY14: 0 | AZ14: 0 | BA14: 0 | BB14: 0 | BC14: 0 | BD14: 4990.15 | BE14: =BH14-BD14 -> 0 | BF14: 213 | BG14: MOVE S320 | BH14: =SUM(AT14:BC14) -> 4990.15 | BI14: 47.58 | BJ14: 3500 | BK14: 2.36 | BL14: 0 | BM14: 80.08 | BN14: 0 | BO14: 0 | BP14: 0 | BQ14: 0 | BR14: 0 | BS14: =SUM(BI14:BR14) -> 3630.02 | BV14: =(BD14/$BD$116)*21083.85 -> 54.730544 | BW14: =(BE14/$O$116)*12925.76 -> 0 | BY14: 20 | CA14: 5 | CB14: =37537.5/96 -> 391.01562 | CD14: =SUM(BT14:CC14) -> 470.74617 | CE14: =63860.36/96 -> 665.21208 | CG14: =(CE14+CF14)*30% -> 199.56363 | CH14: =SUM(CE14:CG14) -> 864.77571 | CI14: =CD14+CH14 -> 1335.5219 | CJ14: =BS14-CI14 -> 2294.4981 | CK14: 1685.64 | CL14: 7847.44 | CM14: 0 | CN14: 0 | CO14: 2787.6 | CP14: 0 | CQ14: 0 | CR14: 0 | CS14: 0 | CT14: 0 | CU14: 12320.68 | CV14: =CY14-CU14 -> 0 | CW14: 490 | CX14: MOVE S320 | CY14: =SUM(CK14:CT14) -> 12320.68 | CZ14: 140.32 | DA14: 3500 | DB14: 0 | DC14: 0 | DD14: 180.58 | DE14: 0 | DF14: 0 | DG14: 0 | DH14: 0 | DI14: 0 | DJ14: =SUM(CZ14:DI14) -> 3820.9 | DM14: =(CU14/$CU$116)*24055.75 -> 133.94301 | DN14: =(CV14/$O$116)*16258.02 -> 0 | DP14: 20 | DR14: 5 | DS14: =DS$3 -> 428.4697 | DU14: =SUM(DK14:DT14) -> 587.41271 | DV14: =DV$3 -> 596.35071 | DX14: =(DV14+DW14)*30% -> 178.90521 | DY14: =SUM(DV14:DX14) -> 775.25592 | DZ14: =DU14+DY14 -> 1362.6686 | EA14: =DJ14-DZ14 -> 2458.2314 | EB14: 1627.3 | EC14: 9184.31 | ED14: 69.7 | EE14: 0 | EF14: 3677.34 | EG14: 0 | EH14: 0 | EI14: 0 | EJ14: 0 | EK14: 0 | EL14: 14558.65 | EM14: =EP14-EL14 -> 0 | EN14: 601 | EO14: MOVE S320 | EP14: =SUM(EB14:EK14) -> 14558.65 | EQ14: 135.46 | ER14: 3500 | ES14: 4.45 | ET14: 0 | EU14: 238.2 | EV14: 0 | EW14: 0 | EX14: 0 | EY14: 0 | EZ14: 0 | FA14: =SUM(EQ14:EZ14) -> 3878.11 | FD14: =(EL14/$EL$116)*26325.65 -> 162.50439 | FE14: =(EM14/$O$116)*14846.27 -> 0 | FG14: 20 | FH14: =14375.2/102 -> 140.93333 | FI14: 5 | FJ14: =FJ$3 -> 424.6802 | FL14: =SUM(FB14:FK14) -> 753.11792 | FM14: =FM$3 -> 664.41902 | FO14: =(FM14+FN14)*30% -> 199.32571 | FP14: =SUM(FM14:FO14) -> 863.74473 | FQ14: =FL14+FP14 -> 1616.8626 | FR14: =FA14-FQ14 -> 2261.2474 | FS14: 1113.53 | FT14: 7958.09 | FU14: 65.75 | FV14: 0 | FW14: 2469.94 | FX14: 0 | FY14: 0 | FZ14: 0 | GA14: 0 | GB14: 0 | GC14: 11607.31 | GD14: =GG14-GC14 -> 0 | GE14: 499 | GF14: MOVE S320 | GG14: =SUM(FS14:GB14) -> 11607.31 | GH14: 92.69 | GI14: 3500 | GJ14: 4.2 | GK14: 0 | GL14: 159.69 | GM14: 0 | GN14: 0 | GO14: 0 | GP14: 0 | GQ14: 0 | GR14: =SUM(GH14:GQ14) -> 3756.58 | GU14: =(GC14/$GC$116)*30198.86 -> 128.62344 | GV14: =(GD14/$O$116)*16844.27 -> 0 | GX14: 20 | GY14: =18860.4/102 -> 184.90588 | GZ14: 5 | HA14: =HA$3 -> 358.47794 | HC14: =SUM(GS14:HB14) -> 697.00726 | HD14: =HD$3 -> 866.9202 | HF14: =(HD14+HE14)*30% -> 260.07606 | HG14: =SUM(HD14:HF14) -> 1126.9963 | HH14: =HC14+HG14 -> 1824.0035 | HI14: =GR14-HH14 -> 1932.5765 | HJ14: 1882.98 | HK14: 7976.89 | HL14: 66.22 | HM14: 0 | HN14: 2207.14 | HO14: 0 | HP14: 0 | HQ14: 0 | HR14: 0 | HS14: 0 | HT14: 12133.23 | HU14: =HX14-HT14 -> 0 | HV14: 494 | HW14: MOVE S320 | HX14: =SUM(HJ14:HS14) -> 12133.23 | HY14: 156.74 | HZ14: 3500 | IA14: 4.23 | IB14: 0 | IC14: 142.83 | ID14: 0 | IE14: 0 | IF14: 0 | IG14: 0 | IH14: 0 | II14: =SUM(HY14:IH14) -> 3803.8 | IL14: =(HT14/$HT$116)*31846.83 -> 134.40533 | IM14: =(HU14/$O$116)*17321.85 -> 0 | IO14: 20 | IP14: =24366/105 -> 232.05714 | IQ14: 5 | IR14: =IR$3 -> 445.62857 | IT14: =SUM(IJ14:IS14) -> 837.09105 | IU14: =IU$3 -> 538.79476 | IW14: =(IU14+IV14)*30% -> 161.63843 | IX14: =SUM(IU14:IW14) -> 700.43319 | IY14: =IT14+IX14 -> 1537.5242 | IZ14: =II14-IY14 -> 2266.2758 | JA14: 1749.41 | JB14: 10151.11 | JC14: 0 | JD14: 0 | JE14: 1577.56 | JF14: 0 | JG14: 0 | JH14: 0 | JI14: 0 | JJ14: 0 | JK14: 13478.08 | JL14: =JO14-JK14 -> 0 | JM14: 501 | JN14: MOVE S320 | JO14: =SUM(JA14:JJ14) -> 13478.08 | JP14: 145.62 | JQ14: 3500 | JR14: 0 | JS14: 0 | JT14: 102.25 | JU14: 0 | JV14: 0 | JW14: 0 | JX14: 0 | JY14: 0 | JZ14: =SUM(JP14:JY14) -> 3747.87 | KC14: =(JK14/$N$116)*39010.72 -> 271.86214 | KD14: =(JL14/$O$116)*19244.4 -> 0 | KF14: 20 | KH14: 5 | KI14: =KI$3 -> 543.39953 | KK14: =SUM(KA14:KJ14) -> 840.26168 | KL14: =KL$3 -> 497.32093 | KN14: =(KL14+KM14)*30% -> 149.19628 | KO14: =SUM(KL14:KN14) -> 646.51721 | KP14: =KK14+KO14 -> 1486.7789 | KQ14: =JZ14-KP14 -> 2261.0911 | KR14: 1944.11 | KS14: 12858.36 | KT14: 58.6 | KU14: 0 | KV14: 3474.24 | KW14: 0 | KX14: 0 | KY14: 16.32 | KZ14: 0 | LA14: 0 | LB14: 18351.63 | LC14: =LF14-LB14 -> 0 | LD14: 705 | LE14: MOVE S320 | LF14: =SUM(KR14:LA14) -> 18351.63 | LG14: 161.83 | LH14: 3500 | LI14: 3.74 | LJ14: 0 | LK14: 224.69 | LL14: 0 | LM14: 0 | LN14: 1.13 | LO14: 0 | LP14: 0 | LQ14: =SUM(LG14:LP14) -> 3891.39 | LT14: =(LB14/$LB$116)*39133.48 -> 187.09721 | LU14: =(LC14/$O$116)*17015.75 -> 0 | LV14: =52000/60 -> 866.66667 | LW14: 20 | LY14: 5 | LZ14: =LZ$3 -> 508.03738 | MB14: =SUM(LR14:MA14) -> 1586.8013 | MC14: =MC$3 -> 593.54907 | ME14: =(MC14+MD14)*30% -> 178.06472 | MF14: =SUM(MC14:ME14) -> 771.61379 | MG14: =MB14+MF14 -> 2358.415 | MH14: =LQ14-MG14 -> 1532.975 | MI14: 1767.49 | MJ14: 9098.57 | MK14: 0 | ML14: 0 | MM14: 1866.47 | MN14: 0 | MO14: 0 | MP14: 0 | MQ14: 0 | MR14: 0 | MS14: 12732.53 | MT14: =MW14-MS14 -> 0 | MU14: 482 | MV14: MOVE S320 | MW14: =SUM(MI14:MR14) -> 12732.53 | MX14: 147.13 | MY14: 3500 | MZ14: 0 | NA14: 0 | NB14: 120.75 | NC14: 0 | ND14: 0 | NE14: 0 | NF14: 0 | NG14: 0 | NH14: =SUM(MX14:NG14) -> 3767.88 | NK14: =(MS14/$N$116)*0 -> 0 | NL14: =(MT14/$O$116)*13804.26 -> 0 | NN14: 0 | NP14: 0 | NQ14: =NQ$3 -> 469.6789 | NS14: =SUM(NI14:NR14) -> 469.6789 | NT14: =78812.25/109 -> 723.04817 | NV14: =(NT14+NU14)*30% -> 216.91445 | NW14: =SUM(NT14:NV14) -> 939.96261 | NX14: =NS14+NW14 -> 1409.6415 | NY14: =NH14-NX14 -> 2358.2385 | NZ14: 967.81 | OA14: 7368.89 | OB14: 0 | OC14: 0 | OD14: 2239.55 | OE14: 0 | OF14: 0 | OG14: 0 | OH14: 0 | OI14: 0 | OJ14: 10576.25 | OK14: =ON14-OJ14 -> 0 | OL14: 431 | OM14: MOVE S320 | ON14: =SUM(NZ14:OI14) -> 10576.25 | OO14: 80.56 | OP14: 3500 | OQ14: 0 | OR14: 0 | OS14: 145.02 | OT14: 0 | OU14: 0 | OV14: 0 | OW14: 0 | OX14: 0 | OY14: =SUM(OO14:OX14) -> 3725.58 | PB14: =(OJ14/$OJ$116)*56307.47 -> 228.69301 | PC14: =(OK14/$O$116)*16757.91 -> 0 | PD14: =52000/60 -> 866.66667 | PE14: 20 | PF14: =3288/100 -> 32.88 | PG14: 5 | PH14: =PH$3 -> 495.20491 | PJ14: =SUM(OZ14:PI14) -> 1648.4446 | PK14: =PK$3 -> 643.25573 | PM14: =(PK14+PL14)*30% -> 192.97672 | PN14: =SUM(PK14:PM14) -> 836.23245 | PO14: =PJ14+PN14 -> 2484.677 | PP14: =OY14-PO14 -> 1240.903 | PQ14: 552.15 | PR14: 7427.11 | PS14: 0 | PT14: 0 | PU14: 1779.98 | PV14: 0 | PW14: 0 | PX14: 0 | PY14: 0 | PZ14: 0 | QA14: 9759.24 | QB14: =QE14-QA14 -> 0 | QC14: 381 | QD14: MOVE S320 | QE14: =SUM(PQ14:PZ14) -> 9759.24 | QF14: 45.96 | QG14: 3500 | QH14: 0 | QI14: 0 | QJ14: 115.27 | QK14: 0 | QL14: 0 | QM14: 0 | QN14: 0 | QO14: 0 | QP14: =SUM(QF14:QO14) -> 3661.23 | QS14: =(QA14/$QA$116)*27743.06 -> 114.71992 | QT14: =(QB14/$O$116)*10429.01 -> 0 | QU14: =52000/60 -> 866.66667 | QV14: 20 | QW14: =2074.8/110 -> 18.861818 | QX14: 5 | QY14: =QY$3 -> 428.14773 | RA14: =SUM(QQ14:QZ14) -> 1453.3961 | RB14: =68119.05/110 -> 619.26409 | RD14: =(RB14+RC14)*30% -> 185.77923 | RE14: =SUM(RB14:RD14) -> 805.04332 | RF14: =RA14+RE14 -> 2258.4395 | RG14: =QP14-RF14 -> 1402.7905 | RH14: 736.91 | RI14: 7171.74 | RJ14: 0 | RK14: 0 | RL14: 1846.37 | RM14: 0 | RN14: 0 | RO14: 0 | RP14: 0 | RQ14: 0 | RR14: 9755.02 | RS14: =RV14-RR14 -> 0 | RT14: 387 | RU14: MOVE S320 | RV14: =SUM(RH14:RQ14) -> 9755.02 | RW14: 61.34 | RX14: 3500 | RY14: 0 | RZ14: 0 | SA14: 119.63 | SB14: 0 | SC14: 0 | SD14: 0 | SE14: 0 | SF14: 0 | SG14: 3680.97 | SJ14: =(RR14/$RR$116)*25115.94 -> 95.861665 | SK14: =(RS14/$O$116)*12319.54 -> 0 | SL14: =52000/60 -> 866.66667 | SM14: 20 | SN14: =56040/113 -> 495.9292 | SO14: 5 | SP14: =SP$3 -> 428.52876 | SR14: =SUM(SH14:SQ14) -> 1911.9863 | SS14: =SS$3 -> 596.28469 | SU14: =(SS14+ST14)*30% -> 178.88541 | SV14: =SUM(SS14:SU14) -> 775.1701 | SW14: =SR14+SV14 -> 2687.1564 | SX14: =SG14-SW14 -> 993.81361 | SY14: =Q14+BH14+CY14+EP14+GG14+HX14+JO14+LF14+MW14+ON14+QE14+RV14 -> 130262.77 | SZ14: =AB14+BS14+DJ14+FA14+GR14+II14+JZ14+LQ14+NH14+OY14+QP14+SG14 -> 41364.33 | TA14: =AR14+CI14+DZ14+FQ14+HH14+IY14+KP14+MG14+NX14+PO14+RF14+SW14 -> 20361.689 | TB14: =SZ14-TA14 -> 21002.641
A15: 1113 | B15: 1113_OLAWA | C15: MOVE S320 | D15: 0 | E15: 0 | F15: 0 | G15: 0 | H15: 0 | I15: 0 | J15: 0 | K15: 0 | L15: 0 | M15: 0 | N15: 0 | O15: =Q15-N15 -> 0 | P15: 0 | Q15: =SUM(D15:M15) -> 0 | R15: 0 | S15: 0 | T15: 0 | U15: 0 | V15: 0 | W15: 0 | X15: 0 | Y15: 0 | Z15: 0 | AA15: 0 | AB15: =SUM(R15:AA15) -> 0 | AE15: =(N15/$N$116)*21028.32 -> 0 | AF15: =(O15/$O$116)*15324.97 -> 0 | AH15: 0 | AJ15: 0 | AM15: =SUM(AC15:AL15) -> 0 | AO15: 0 | AP15: =(AN15+AO15)*30% -> 0 | AQ15: =SUM(AN15:AP15) -> 0 | AR15: =AM15+AQ15 -> 0 | AS15: =AB15-AR15 -> 0 | BE15: =BH15-BD15 -> 0 | BG15: MOVE S320 | BH15: =SUM(AT15:BC15) -> 0 | BS15: =SUM(BI15:BR15) -> 0 | BV15: =(BD15/$BD$116)*21083.85 -> 0 | BW15: =(BE15/$O$116)*12925.76 -> 0 | CG15: =(CE15+CF15)*30% -> 0 | CH15: =SUM(CE15:CG15) -> 0 | CI15: =CD15+CH15 -> 0 | CJ15: =BS15-CI15 -> 0 | CK15: 0 | CL15: 7138.9 | CM15: 0 | CN15: 0 | CO15: 0 | CP15: 0 | CQ15: 0 | CR15: 100.39 | CS15: 0 | CT15: 0 | CU15: 7239.29 | CV15: =CY15-CU15 -> 0 | CW15: 615 | CX15: MOVE S320 | CY15: =SUM(CK15:CT15) -> 7239.29 | CZ15: 0 | DA15: 3900 | DB15: 0 | DC15: 0 | DD15: 0 | DE15: 0 | DF15: 0 | DG15: 6.97 | DH15: 0 | DI15: 0 | DJ15: =SUM(CZ15:DI15) -> 3906.97 | DM15: =(CU15/$CU$116)*24055.75 -> 78.7012 | DN15: =(CV15/$O$116)*16258.02 -> 0 | DP15: 20 | DR15: 5 | DS15: =DS$3 -> 428.4697 | DU15: =SUM(DK15:DT15) -> 532.1709 | DV15: =DV$3 -> 596.35071 | DX15: =(DV15+DW15)*30% -> 178.90521 | DY15: =SUM(DV15:DX15) -> 775.25592 | DZ15: =DU15+DY15 -> 1307.4268 | EA15: =DJ15-DZ15 -> 2599.5432 | EB15: 10181.21 | EC15: 19789.86 | ED15: 0 | EE15: 0 | EF15: 0 | EG15: 0 | EH15: 0 | EI15: 353.48 | EJ15: 0 | EK15: 0 | EL15: 30324.55 | EM15: =EP15-EL15 -> 0 | EN15: 2264 | EO15: MOVE S320 | EP15: =SUM(EB15:EK15) -> 30324.55 | EQ15: 847.42 | ER15: 3900 | ES15: 0 | ET15: 0 | EU15: 0 | EV15: 0 | EW15: 0 | EX15: 24.48 | EY15: 0 | EZ15: 0 | FA15: =SUM(EQ15:EZ15) -> 4771.9 | FD15: =(EL15/$EL$116)*26325.65 -> 338.48417 | FE15: =(EM15/$O$116)*14846.27 -> 0 | FG15: 20 | FH15: =14375.2/102 -> 140.93333 | FI15: 5 | FJ15: =FJ$3 -> 424.6802 | FL15: =SUM(FB15:FK15) -> 929.0977 | FM15: =FM$3 -> 664.41902 | FO15: =(FM15+FN15)*30% -> 199.32571 | FP15: =SUM(FM15:FO15) -> 863.74473 | FQ15: =FL15+FP15 -> 1792.8424 | FR15: =FA15-FQ15 -> 2979.0576 | FS15: 15063.05 | FT15: 23962.58 | FU15: 0 | FV15: 0 | FW15: 0 | FX15: 0 | FY15: 0 | FZ15: 530 | GA15: 0 | GB15: 0 | GC15: 39555.63 | GD15: =GG15-GC15 -> 0 | GE15: 2637 | GF15: MOVE S320 | GG15: =SUM(FS15:GB15) -> 39555.63 | GH15: 1253.76 | GI15: 3900 | GJ15: 0 | GK15: 0 | GL15: 0 | GM15: 0 | GN15: 0 | GO15: 36.81 | GP15: 0 | GQ15: 0 | GR15: =SUM(GH15:GQ15) -> 5190.57 | GU15: =(GC15/$GC$116)*30198.86 -> 438.32561 | GV15: =(GD15/$O$116)*16844.27 -> 0 | GX15: 20 | GY15: =18860.4/102 -> 184.90588 | GZ15: 5 | HA15: =HA$3 -> 358.47794 | HC15: =SUM(GS15:HB15) -> 1006.7094 | HD15: =HD$3 -> 866.9202 | HF15: =(HD15+HE15)*30% -> 260.07606 | HG15: =SUM(HD15:HF15) -> 1126.9963 | HH15: =HC15+HG15 -> 2133.7057 | HI15: =GR15-HH15 -> 3056.8643 | HJ15: 16169.57 | HK15: 24284.76 | HL15: 0 | HM15: 0 | HN15: 0 | HO15: 0 | HP15: 0 | HQ15: 443.8 | HR15: 0 | HS15: 0 | HT15: 40898.13 | HU15: =HX15-HT15 -> 0 | HV15: 2957 | HW15: MOVE S320 | HX15: =SUM(HJ15:HS15) -> 40898.13 | HY15: 1345.86 | HZ15: 3900 | IA15: 0 | IB15: 0 | IC15: 0 | ID15: 0 | IE15: 0 | IF15: 30.82 | IG15: 0 | IH15: 0 | II15: =SUM(HY15:IH15) -> 5276.68 | IL15: =(HT15/$HT$116)*31846.83 -> 453.04727 | IM15: =(HU15/$O$116)*17321.85 -> 0 | IO15: 20 | IP15: =24366/105 -> 232.05714 | IQ15: 5 | IR15: =IR$3 -> 445.62857 | IT15: =SUM(IJ15:IS15) -> 1155.733 | IU15: =IU$3 -> 538.79476 | IW15: =(IU15+IV15)*30% -> 161.63843 | IX15: =SUM(IU15:IW15) -> 700.43319 | IY15: =IT15+IX15 -> 1856.1662 | IZ15: =II15-IY15 -> 3420.5138 | JA15: 19169.8 | JB15: 27256.59 | JC15: 22.68 | JD15: 0 | JE15: 0 | JF15: 0 | JG15: 0 | JH15: 287.25 | JI15: 0 | JJ15: 0 | JK15: 46736.32 | JL15: =JO15-JK15 -> 0 | JM15: 3139 | JN15: MOVE S320 | JO15: =SUM(JA15:JJ15) -> 46736.32 | JP15: 1595.79 | JQ15: 3900 | JR15: 1.45 | JS15: 0 | JT15: 0 | JU15: 0 | JV15: 0 | JW15: 19.95 | JX15: 0 | JY15: 0 | JZ15: =SUM(JP15:JY15) -> 5517.19 | KC15: =(JK15/$N$116)*39010.72 -> 942.70372 | KD15: =(JL15/$O$116)*19244.4 -> 0 | KF15: 20 | KH15: 5 | KI15: =KI$3 -> 543.39953 | KK15: =SUM(KA15:KJ15) -> 1511.1032 | KL15: =KL$3 -> 497.32093 | KN15: =(KL15+KM15)*30% -> 149.19628 | KO15: =SUM(KL15:KN15) -> 646.51721 | KP15: =KK15+KO15 -> 2157.6205 | KQ15: =JZ15-KP15 -> 3359.5695 | KR15: 22654.43 | KS15: 31220.42 | KT15: 0 | KU15: 0 | KV15: 0 | KW15: 0 | KX15: 0 | KY15: 631.93 | KZ15: 0 | LA15: 0 | LB15: 54506.78 | LC15: =LF15-LB15 -> 0 | LD15: 3604 | LE15: MOVE S320 | LF15: =SUM(KR15:LA15) -> 54506.78 | LG15: 1885.84 | LH15: 3900 | LI15: 0 | LJ15: 0 | LK15: 0 | LL15: 0 | LM15: 0 | LN15: 43.81 | LO15: 0 | LP15: 0 | LQ15: =SUM(LG15:LP15) -> 5829.65 | LT15: =(LB15/$LB$116)*39133.48 -> 555.70359 | LU15: =(LC15/$O$116)*17015.75 -> 0 | LV15: =52000/60 -> 866.66667 | LW15: 20 | LY15: 5 | LZ15: =LZ$3 -> 508.03738 | MB15: =SUM(LR15:MA15) -> 1955.4076 | MC15: =MC$3 -> 593.54907 | ME15: =(MC15+MD15)*30% -> 178.06472 | MF15: =SUM(MC15:ME15) -> 771.61379 | MG15: =MB15+MF15 -> 2727.0214 | MH15: =LQ15-MG15 -> 3102.6286 | MI15: 18053.34 | MJ15: 23864.3 | MK15: 0 | ML15: 0 | MM15: 0 | MN15: 0 | MO15: 0 | MP15: 389.45 | MQ15: 0 | MR15: 0 | MS15: 42307.09 | MT15: =MW15-MS15 -> 0 | MU15: 2836 | MV15: MOVE S320 | MW15: =SUM(MI15:MR15) -> 42307.09 | MX15: 1502.84 | MY15: 3900 | MZ15: 0 | NA15: 0 | NB15: 0 | NC15: 0 | ND15: 0 | NE15: 27.05 | NF15: 0 | NG15: 0 | NH15: =SUM(MX15:NG15) -> 5429.89 | NK15: =(MS15/$N$116)*0 -> 0 | NL15: =(MT15/$O$116)*13804.26 -> 0 | NN15: 0 | NP15: 0 | NQ15: =NQ$3 -> 469.6789 | NS15: =SUM(NI15:NR15) -> 469.6789 | NT15: =78812.25/109 -> 723.04817 | NV15: =(NT15+NU15)*30% -> 216.91445 | NW15: =SUM(NT15:NV15) -> 939.96261 | NX15: =NS15+NW15 -> 1409.6415 | NY15: =NH15-NX15 -> 4020.2485 | NZ15: 18499.08 | OA15: 30424.91 | OB15: 0 | OC15: 0 | OD15: 0 | OE15: 0 | OF15: 0 | OG15: 155.02 | OH15: 0 | OI15: 0 | OJ15: 49079.01 | OK15: =ON15-OJ15 -> 0 | OL15: 3471 | OM15: MOVE S320 | ON15: =SUM(NZ15:OI15) -> 49079.01 | OO15: 1539.97 | OP15: 3900 | OQ15: 0 | OR15: 0 | OS15: 0 | OT15: 0 | OU15: 0 | OV15: 10.77 | OW15: 0 | OX15: 0 | OY15: =SUM(OO15:OX15) -> 5450.74 | PB15: =(OJ15/$OJ$116)*56307.47 -> 1061.2482 | PC15: =(OK15/$O$116)*16757.91 -> 0 | PD15: =52000/60 -> 866.66667 | PE15: 20 | PF15: =3288/100 -> 32.88 | PG15: 5 | PH15: =PH$3 -> 495.20491 | PJ15: =SUM(OZ15:PI15) -> 2480.9998 | PK15: =PK$3 -> 643.25573 | PM15: =(PK15+PL15)*30% -> 192.97672 | PN15: =SUM(PK15:PM15) -> 836.23245 | PO15: =PJ15+PN15 -> 3317.2323 | PP15: =OY15-PO15 -> 2133.5077 | PQ15: 17842.88 | PR15: 26106.38 | PS15: 43.5 | PT15: 0 | PU15: 0 | PV15: 0 | PW15: 0 | PX15: 326.02 | PY15: 0 | PZ15: 0 | QA15: 44318.78 | QB15: =QE15-QA15 -> 0 | QC15: 2960 | QD15: MOVE S320 | QE15: =SUM(PQ15:PZ15) -> 44318.78 | QF15: 1485.32 | QG15: 3900 | QH15: 2.78 | QI15: 0 | QJ15: 0 | QK15: 0 | QL15: 0 | QM15: 22.64 | QN15: 0 | QO15: 0 | QP15: =SUM(QF15:QO15) -> 5410.74 | QS15: =(QA15/$QA$116)*27743.06 -> 520.96752 | QT15: =(QB15/$O$116)*10429.01 -> 0 | QU15: =52000/60 -> 866.66667 | QV15: 20 | QW15: =2074.8/110 -> 18.861818 | QX15: 5 | QY15: =QY$3 -> 428.14773 | RA15: =SUM(QQ15:QZ15) -> 1859.6437 | RB15: =68119.05/110 -> 619.26409 | RD15: =(RB15+RC15)*30% -> 185.77923 | RE15: =SUM(RB15:RD15) -> 805.04332 | RF15: =RA15+RE15 -> 2664.6871 | RG15: =QP15-RF15 -> 2746.0529 | RH15: 14891.16 | RI15: 27449.65 | RJ15: 0 | RK15: 0 | RL15: 0 | RM15: 0 | RN15: 0 | RO15: 148.54 | RP15: 20.54 | RQ15: 0 | RR15: 42509.89 | RS15: =RV15-RR15 -> 0 | RT15: 2933 | RU15: MOVE S320 | RV15: =SUM(RH15:RQ15) -> 42509.89 | RW15: 1239.62 | RX15: 3900 | RY15: 0 | RZ15: 0 | SA15: 0 | SB15: 0 | SC15: 0 | SD15: 10.32 | SE15: 1.14 | SF15: 0 | SG15: 5151.08 | SJ15: =(RR15/$RR$116)*25115.94 -> 417.7407 | SK15: =(RS15/$O$116)*12319.54 -> 0 | SL15: =52000/60 -> 866.66667 | SM15: 20 | SN15: =56040/113 -> 495.9292 | SO15: 5 | SP15: =SP$3 -> 428.52876 | SR15: =SUM(SH15:SQ15) -> 2233.8653 | SS15: =SS$3 -> 596.28469 | SU15: =(SS15+ST15)*30% -> 178.88541 | SV15: =SUM(SS15:SU15) -> 775.1701 | SW15: =SR15+SV15 -> 3009.0354 | SX15: =SG15-SW15 -> 2142.0446 | SY15: =Q15+BH15+CY15+EP15+GG15+HX15+JO15+LF15+MW15+ON15+QE15+RV15 -> 397475.47 | SZ15: =AB15+BS15+DJ15+FA15+GR15+II15+JZ15+LQ15+NH15+OY15+QP15+SG15 -> 51935.41 | TA15: =AR15+CI15+DZ15+FQ15+HH15+IY15+KP15+MG15+NX15+PO15+RF15+SW15 -> 22375.379 | TB15: =SZ15-TA15 -> 29560.031
A16: 1114 | B16: 1114_CZLUCH | C16: MOVE S320 | D16: 0 | E16: 0 | F16: 0 | G16: 0 | H16: 0 | I16: 0 | J16: 0 | K16: 0 | L16: 0 | M16: 0 | N16: 0 | O16: =Q16-N16 -> 0 | P16: 0 | Q16: =SUM(D16:M16) -> 0 | R16: 0 | S16: 0 | T16: 0 | U16: 0 | V16: 0 | W16: 0 | X16: 0 | Y16: 0 | Z16: 0 | AA16: 0 | AB16: =SUM(R16:AA16) -> 0 | AE16: =(N16/$N$116)*21028.32 -> 0 | AF16: =(O16/$O$116)*15324.97 -> 0 | AH16: 0 | AJ16: 0 | AM16: =SUM(AC16:AL16) -> 0 | AO16: 0 | AP16: =(AN16+AO16)*30% -> 0 | AQ16: =SUM(AN16:AP16) -> 0 | AR16: =AM16+AQ16 -> 0 | AS16: =AB16-AR16 -> 0 | BE16: =BH16-BD16 -> 0 | BG16: MOVE S320 | BH16: =SUM(AT16:BC16) -> 0 | BS16: =SUM(BI16:BR16) -> 0 | BV16: =(BD16/$BD$116)*21083.85 -> 0 | BW16: =(BE16/$O$116)*12925.76 -> 0 | CG16: =(CE16+CF16)*30% -> 0 | CH16: =SUM(CE16:CG16) -> 0 | CI16: =CD16+CH16 -> 0 | CJ16: =BS16-CI16 -> 0 | CK16: 0 | CL16: 251.57 | CM16: 0 | CN16: 0 | CO16: 0 | CP16: 0 | CQ16: 0 | CR16: 0 | CS16: 0 | CT16: 0 | CU16: 251.57 | CV16: =CY16-CU16 -> 0 | CW16: 12 | CX16: MOVE S320 | CY16: =SUM(CK16:CT16) -> 251.57 | CZ16: 0 | DA16: 338.71 | DB16: 0 | DC16: 0 | DD16: 0 | DE16: 0 | DF16: 0 | DG16: 0 | DH16: 0 | DI16: 0 | DJ16: =SUM(CZ16:DI16) -> 338.71 | DM16: =(CU16/$CU$116)*24055.75 -> 2.7349175 | DN16: =(CV16/$O$116)*16258.02 -> 0 | DP16: 20 | DR16: 5 | DS16: =DS$3 -> 428.4697 | DU16: =SUM(DK16:DT16) -> 456.20461 | DV16: =DV$3 -> 596.35071 | DX16: =(DV16+DW16)*30% -> 178.90521 | DY16: =SUM(DV16:DX16) -> 775.25592 | DZ16: =DU16+DY16 -> 1231.4605 | EA16: =DJ16-DZ16 -> -892.75053 | EB16: 52.64 | EC16: 2027.24 | ED16: 0 | EE16: 0 | EF16: 63.12 | EG16: 0 | EH16: 0 | EI16: 0 | EJ16: 0 | EK16: 0 | EL16: 2143 | EM16: =EP16-EL16 -> 0 | EN16: 106 | EO16: MOVE S320 | EP16: =SUM(EB16:EK16) -> 2143 | EQ16: 4.38 | ER16: 3500 | ES16: 0 | ET16: 0 | EU16: 4.09 | EV16: 0 | EW16: 0 | EX16: 0 | EY16: 0 | EZ16: 0 | FA16: =SUM(EQ16:EZ16) -> 3508.47 | FD16: =(EL16/$EL$116)*26325.65 -> 23.920275 | FE16: =(EM16/$O$116)*14846.27 -> 0 | FG16: 20 | FH16: =14375.2/102 -> 140.93333 | FI16: 5 | FJ16: =FJ$3 -> 424.6802 | FL16: =SUM(FB16:FK16) -> 614.5338 | FM16: =FM$3 -> 664.41902 | FO16: =(FM16+FN16)*30% -> 199.32571 | FP16: =SUM(FM16:FO16) -> 863.74473 | FQ16: =FL16+FP16 -> 1478.2785 | FR16: =FA16-FQ16 -> 2030.1915 | FS16: 167 | FT16: 2333.46 | FU16: 0 | FV16: 0 | FW16: 24 | FX16: 0 | FY16: 0 | FZ16: 0 | GA16: 0 | GB16: 0 | GC16: 2524.46 | GD16: =GG16-GC16 -> 0 | GE16: 105 | GF16: MOVE S320 | GG16: =SUM(FS16:GB16) -> 2524.46 | GH16: 13.9 | GI16: 3500 | GJ16: 0 | GK16: 0 | GL16: 1.56 | GM16: 0 | GN16: 0 | GO16: 0 | GP16: 0 | GQ16: 0 | GR16: =SUM(GH16:GQ16) -> 3515.46 | GU16: =(GC16/$GC$116)*30198.86 -> 27.974159 | GV16: =(GD16/$O$116)*16844.27 -> 0 | GX16: 20 | GY16: =18860.4/102 -> 184.90588 | GZ16: 5 | HA16: =HA$3 -> 358.47794 | HC16: =SUM(GS16:HB16) -> 596.35798 | HD16: =HD$3 -> 866.9202 | HF16: =(HD16+HE16)*30% -> 260.07606 | HG16: =SUM(HD16:HF16) -> 1126.9963 | HH16: =HC16+HG16 -> 1723.3542 | HI16: =GR16-HH16 -> 1792.1058 | HJ16: 177 | HK16: 2682.74 | HL16: 0 | HM16: 0 | HN16: 0 | HO16: 0 | HP16: 0 | HQ16: 0 | HR16: 0 | HS16: 0 | HT16: 2859.74 | HU16: =HX16-HT16 -> 0 | HV16: 120 | HW16: MOVE S320 | HX16: =SUM(HJ16:HS16) -> 2859.74 | HY16: 14.73 | HZ16: 3500 | IA16: 0 | IB16: 0 | IC16: 0 | ID16: 0 | IE16: 0 | IF16: 0 | IG16: 0 | IH16: 0 | II16: =SUM(HY16:IH16) -> 3514.73 | IL16: =(HT16/$HT$116)*31846.83 -> 31.678646 | IM16: =(HU16/$O$116)*17321.85 -> 0 | IO16: 20 | IP16: =24366/105 -> 232.05714 | IQ16: 5 | IR16: =IR$3 -> 445.62857 | IT16: =SUM(IJ16:IS16) -> 734.36436 | IU16: =IU$3 -> 538.79476 | IW16: =(IU16+IV16)*30% -> 161.63843 | IX16: =SUM(IU16:IW16) -> 700.43319 | IY16: =IT16+IX16 -> 1434.7976 | IZ16: =II16-IY16 -> 2079.9324 | JA16: 134.15 | JB16: 3683.69 | JC16: 0 | JD16: 0 | JE16: 39.4 | JF16: 0 | JG16: 0 | JH16: 0 | JI16: 0 | JJ16: 0 | JK16: 3857.24 | JL16: =JO16-JK16 -> 0 | JM16: 165 | JN16: MOVE S320 | JO16: =SUM(JA16:JJ16) -> 3857.24 | JP16: 11.17 | JQ16: 3500 | JR16: 0 | JS16: 0 | JT16: 2.55 | JU16: 0 | JV16: 0 | JW16: 0 | JX16: 0 | JY16: 0 | JZ16: =SUM(JP16:JY16) -> 3513.72 | KC16: =(JK16/$N$116)*39010.72 -> 77.803183 | KD16: =(JL16/$O$116)*19244.4 -> 0 | KF16: 20 | KH16: 5 | KI16: =KI$3 -> 543.39953 | KK16: =SUM(KA16:KJ16) -> 646.20272 | KL16: =KL$3 -> 497.32093 | KN16: =(KL16+KM16)*30% -> 149.19628 | KO16: =SUM(KL16:KN16) -> 646.51721 | KP16: =KK16+KO16 -> 1292.7199 | KQ16: =JZ16-KP16 -> 2221.0001 | KR16: 118.4 | KS16: 2653.34 | KT16: 0 | KU16: 0 | KV16: 89.2 | KW16: 0 | KX16: 0 | KY16: 0 | KZ16: 0 | LA16: 0 | LB16: 2860.94 | LC16: =LF16-LB16 -> 0 | LD16: 132 | LE16: MOVE S320 | LF16: =SUM(KR16:LA16) -> 2860.94 | LG16: 9.86 | LH16: 3500 | LI16: 0 | LJ16: 0 | LK16: 5.78 | LL16: 0 | LM16: 0 | LN16: 0 | LO16: 0 | LP16: 0 | LQ16: =SUM(LG16:LP16) -> 3515.64 | LT16: =(LB16/$LB$116)*39133.48 -> 29.167649 | LU16: =(LC16/$O$116)*17015.75 -> 0 | LW16: 20 | LY16: 5 | LZ16: =LZ$3 -> 508.03738 | MB16: =SUM(LR16:MA16) -> 562.20503 | MC16: =MC$3 -> 593.54907 | ME16: =(MC16+MD16)*30% -> 178.06472 | MF16: =SUM(MC16:ME16) -> 771.61379 | MG16: =MB16+MF16 -> 1333.8188 | MH16: =LQ16-MG16 -> 2181.8212 | MI16: 150 | MJ16: 2440.1 | MK16: 0 | ML16: 0 | MM16: 0 | MN16: 0 | MO16: 0 | MP16: 0 | MQ16: 0 | MR16: 0 | MS16: 2590.1 | MT16: =MW16-MS16 -> 0 | MU16: 125 | MV16: MOVE S320 | MW16: =SUM(MI16:MR16) -> 2590.1 | MX16: 12.49 | MY16: 3500 | MZ16: 0 | NA16: 0 | NB16: 0 | NC16: 0 | ND16: 0 | NE16: 0 | NF16: 0 | NG16: 0 | NH16: =SUM(MX16:NG16) -> 3512.49 | NK16: =(MS16/$N$116)*0 -> 0 | NL16: =(MT16/$O$116)*13804.26 -> 0 | NN16: 0 | NP16: 5 | NQ16: =NQ$3 -> 469.6789 | NS16: =SUM(NI16:NR16) -> 474.6789 | NT16: =78812.25/109 -> 723.04817 | NV16: =(NT16+NU16)*30% -> 216.91445 | NW16: =SUM(NT16:NV16) -> 939.96261 | NX16: =NS16+NW16 -> 1414.6415 | NY16: =NH16-NX16 -> 2097.8485 | NZ16: 71 | OA16: 2581.55 | OB16: 0 | OC16: 0 | OD16: 24 | OE16: 0 | OF16: 0 | OG16: 0 | OH16: 0 | OI16: 0 | OJ16: 2676.55 | OK16: =ON16-OJ16 -> 0 | OL16: 122 | OM16: MOVE S320 | ON16: =SUM(NZ16:OI16) -> 2676.55 | OO16: 5.91 | OP16: 3500 | OQ16: 0 | OR16: 0 | OS16: 1.56 | OT16: 0 | OU16: 0 | OV16: 0 | OW16: 0 | OX16: 0 | OY16: =SUM(OO16:OX16) -> 3507.47 | PB16: =(OJ16/$OJ$116)*56307.47 -> 57.875739 | PC16: =(OK16/$O$116)*16757.91 -> 0 | PE16: 20 | PF16: =3288/100 -> 32.88 | PG16: 5 | PH16: =PH$3 -> 495.20491 | PJ16: =SUM(OZ16:PI16) -> 610.96065 | PK16: =PK$3 -> 643.25573 | PM16: =(PK16+PL16)*30% -> 192.97672 | PN16: =SUM(PK16:PM16) -> 836.23245 | PO16: =PJ16+PN16 -> 1447.1931 | PP16: =OY16-PO16 -> 2060.2769 | PQ16: 58 | PR16: 2527.49 | PS16: 0 | PT16: 0 | PU16: 87.12 | PV16: 0 | PW16: 0 | PX16: 0 | PY16: 0 | PZ16: 0 | QA16: 2672.61 | QB16: =QE16-QA16 -> 0 | QC16: 128 | QD16: MOVE S320 | QE16: =SUM(PQ16:PZ16) -> 2672.61 | QF16: 4.83 | QG16: 3500 | QH16: 0 | QI16: 0 | QJ16: 5.65 | QK16: 0 | QL16: 0 | QM16: 0 | QN16: 0 | QO16: 0 | QP16: =SUM(QF16:QO16) -> 3510.48 | QS16: =(QA16/$QA$116)*27743.06 -> 31.416546 | QT16: =(QB16/$O$116)*10429.01 -> 0 | QU16: =52000/60 -> 866.66667 | QV16: 20 | QW16: =2074.8/110 -> 18.861818 | QX16: 5 | QY16: =QY$3 -> 428.14773 | RA16: =SUM(QQ16:QZ16) -> 1370.0928 | RB16: =68119.05/110 -> 619.26409 | RD16: =(RB16+RC16)*30% -> 185.77923 | RE16: =SUM(RB16:RD16) -> 805.04332 | RF16: =RA16+RE16 -> 2175.1361 | RG16: =QP16-RF16 -> 1335.3439 | RH16: 266.6 | RI16: 2916.27 | RJ16: 0 | RK16: 0 | RL16: 36.36 | RM16: 0 | RN16: 0 | RO16: 0 | RP16: 0 | RQ16: 0 | RR16: 3219.23 | RS16: =RV16-RR16 -> 0 | RT16: 153 | RU16: MOVE S320 | RV16: =SUM(RH16:RQ16) -> 3219.23 | RW16: 22.19 | RX16: 3500 | RY16: 0 | RZ16: 0 | SA16: 2.36 | SB16: 0 | SC16: 0 | SD16: 0 | SE16: 0 | SF16: 0 | SG16: 3524.55 | SJ16: =(RR16/$RR$116)*25115.94 -> 31.635071 | SK16: =(RS16/$O$116)*12319.54 -> 0 | SL16: =52000/60 -> 866.66667 | SM16: 20 | SN16: =56040/113 -> 495.9292 | SO16: 5 | SP16: =SP$3 -> 428.52876 | SR16: =SUM(SH16:SQ16) -> 1847.7597 | SS16: =SS$3 -> 596.28469 | SU16: =(SS16+ST16)*30% -> 178.88541 | SV16: =SUM(SS16:SU16) -> 775.1701 | SW16: =SR16+SV16 -> 2622.9298 | SX16: =SG16-SW16 -> 901.6202 | SY16: =Q16+BH16+CY16+EP16+GG16+HX16+JO16+LF16+MW16+ON16+QE16+RV16 -> 25655.44 | SZ16: =AB16+BS16+DJ16+FA16+GR16+II16+JZ16+LQ16+NH16+OY16+QP16+SG16 -> 31961.72 | TA16: =AR16+CI16+DZ16+FQ16+HH16+IY16+KP16+MG16+NX16+PO16+RF16+SW16 -> 16154.33 | TB16: =SZ16-TA16 -> 15807.39
A17: 1115 | B17: 1115_KRAKÓW | Q17: =SUM(D17:M17) -> 0 | AB17: =SUM(R17:AA17) -> 0 | AE17: =(N17/$N$116)*21028.32 -> 0 | AM17: =SUM(AC17:AL17) -> 0 | AP17: =(AN17+AO17)*30% -> 0 | AQ17: =SUM(AN17:AP17) -> 0 | AR17: =AM17+AQ17 -> 0 | AS17: =AB17-AR17 -> 0 | BH17: =SUM(AT17:BC17) -> 0 | BS17: =SUM(BI17:BR17) -> 0 | BT17: =4898.01/10 -> 489.801 | BV17: =(BD17/$BD$116)*21083.85 -> 0 | BW17: =(BE17/$O$116)*12925.76 -> 0 | CG17: =(CE17+CF17)*30% -> 0 | CI17: =CD17+CH17 -> 0 | CJ17: =BS17-CI17 -> 0 | CY17: =SUM(CK17:CT17) -> 0 | DJ17: =SUM(CZ17:DI17) -> 0 | DM17: =(CU17/$CU$116)*24055.75 -> 0 | DN17: =(CV17/$O$116)*16258.02 -> 0 | DU17: =SUM(DK17:DT17) -> 0 | DX17: =(DV17+DW17)*30% -> 0 | DY17: =SUM(DV17:DX17) -> 0 | DZ17: =DU17+DY17 -> 0 | EA17: =DJ17-DZ17 -> 0 | EB17: 5570.24 | EC17: 4457.92 | ED17: 0 | EE17: 0 | EF17: 0 | EG17: 0 | EH17: 21250.03 | EI17: 0 | EJ17: 0 | EK17: 0 | EL17: 31278.19 | EN17: 1337 | EO17: MOVE S320 | EP17: =SUM(EB17:EK17) -> 31278.19 | EQ17: 463.67 | ER17: 3043.33 | ES17: 0 | ET17: 0 | EU17: 0 | EV17: 0 | EW17: 750 | EX17: 0 | EY17: 0 | EZ17: 0 | FA17: =SUM(EQ17:EZ17) -> 4257 | FB17: =4898.01/10 -> 489.801 | FD17: =(EL17/$EL$116)*26325.65 -> 349.12875 | FE17: =(EM17/$O$116)*14846.27 -> 0 | FG17: 20 | FH17: =14375.2/102 -> 140.93333 | FI17: 5 | FJ17: =FJ$3 -> 424.6802 | FL17: =SUM(FB17:FK17) -> 1429.5433 | FM17: =FM$3 -> 664.41902 | FO17: =(FM17+FN17)*30% -> 199.32571 | FP17: =SUM(FM17:FO17) -> 863.74473 | FQ17: =FL17+FP17 -> 2293.288 | FR17: =FA17-FQ17 -> 1963.712 | FS17: 11117.23 | FT17: 6226.81 | FU17: 0 | FV17: 0 | FW17: 0 | FX17: 0 | FY17: 32207.15 | FZ17: 0 | GA17: 0 | GB17: 0 | GC17: 49551.19 | GE17: 2074 | GF17: MOVE S320 | GG17: =SUM(FS17:GB17) -> 49551.19 | GH17: 925.41 | GI17: 4150 | GJ17: 0 | GK17: 0 | GL17: 0 | GM17: 0 | GN17: 750 | GO17: 0 | GP17: 0 | GQ17: 0 | GR17: =SUM(GH17:GQ17) -> 5825.41 | GS17: =4898.01/10 -> 489.801 | GT17: 560.74 | GU17: =(GC17/$GC$116)*30198.86 -> 549.08886 | GV17: =(GD17/$O$116)*16844.27 -> 0 | GX17: 20 | GY17: =18860.4/102 -> 184.90588 | GZ17: 5 | HA17: =HA$3 -> 358.47794 | HC17: 1665.38 | HD17: =HD$3 -> 866.9202 | HF17: =(HD17+HE17)*30% -> 260.07606 | HG17: =SUM(HD17:HF17) -> 1126.9963 | HH17: =HC17+HG17 -> 2792.3763 | HI17: =GR17-HH17 -> 3033.0337 | HJ17: 13258.66 | HK17: 5637.06 | HL17: 0 | HM17: 0 | HN17: 0 | HO17: 0 | HP17: 33031.21 | HQ17: 0 | HR17: 0 | HS17: 0 | HT17: 51926.93 | HV17: 2136 | HW17: MOVE S320 | HX17: =SUM(HJ17:HS17) -> 51926.93 | HY17: 1103.66 | HZ17: 4150 | IA17: 0 | IB17: 0 | IC17: 0 | ID17: 0 | IE17: 750 | IF17: 0 | IG17: 0 | IH17: 0 | II17: =SUM(HY17:IH17) -> 6003.66 | IJ17: =4898.01/10 -> 489.801 | IK17: 317.4 | IL17: =(HT17/$HT$116)*31846.83 -> 575.21833 | IM17: =(HU17/$O$116)*17321.85 -> 0 | IO17: 20 | IP17: =24366/105 -> 232.05714 | IQ17: 5 | IR17: =IR$3 -> 445.62857 | IT17: 1978.78 | IU17: =IU$3 -> 538.79476 | IW17: =(IU17+IV17)*30% -> 161.63843 | IY17: =IT17+IX17 -> 1978.78 | IZ17: =II17-IY17 -> 4024.88 | JA17: 16556.47 | JB17: 6416.59 | JC17: 0 | JD17: 0 | JE17: 0 | JF17: 0 | JG17: 36228.55 | JH17: 0 | JI17: 0 | JJ17: 0 | JK17: 59201.61 | JM17: 2297 | JO17: =SUM(JA17:JJ17) -> 59201.61 | JP17: 1378.17 | JQ17: 4150 | JR17: 0 | JS17: 0 | JT17: 0 | JU17: 0 | JV17: 750 | JW17: 0 | JX17: 0 | JY17: 0 | JZ17: =SUM(JP17:JY17) -> 6278.17 | KA17: =4898.01/10 -> 489.801 | KC17: =(JK17/$N$116)*39010.72 -> 1194.1372 | KD17: =(JL17/$O$116)*19244.4 -> 0 | KF17: 20 | KH17: 5 | KI17: =KI$3 -> 543.39953 | KK17: 2085.8 | KL17: =KL$3 -> 497.32093 | KN17: =(KL17+KM17)*30% -> 149.19628 | KO17: =SUM(KL17:KN17) -> 646.51721 | KP17: =KK17+KO17 -> 2732.3172 | KQ17: =JZ17-KP17 -> 3545.8528 | KR17: 15202.61 | KS17: 6767.36 | KT17: 0 | KU17: 0 | KV17: 0 | KW17: 0 | KX17: 42061.97 | KY17: 0 | KZ17: 0 | LA17: 0 | LB17: 64031.94 | LD17: 2424 | LE17: MOVE S320 | LF17: =SUM(KR17:LA17) -> 64031.94 | LG17: 1265.47 | LH17: 4150 | LI17: 0 | LJ17: 0 | LK17: 0 | LL17: 0 | LM17: 750 | LN17: 0 | LO17: 0 | LP17: 0 | LQ17: =SUM(LG17:LP17) -> 6165.47 | LR17: 1020 | LS17: 317.4 | LT17: =(LB17/$LB$116)*39133.48 -> 652.81382 | LU17: =(LC17/$O$116)*17015.75 -> 0 | LW17: 20 | LY17: 5 | LZ17: =LZ$3 -> 508.03738 | MB17: =SUM(LR17:MA17) -> 2523.2512 | MC17: =MC$3 -> 593.54907 | ME17: =(MC17+MD17)*30% -> 178.06472 | MF17: =SUM(MC17:ME17) -> 771.61379 | MG17: =MB17+MF17 -> 3294.865 | MH17: =LQ17-MG17 -> 2870.605 | MI17: 11505.68 | MJ17: 5641.3 | MK17: 0 | ML17: 0 | MM17: 0 | MN17: 0 | MO17: 35535.13 | MP17: 0 | MQ17: 0 | MR17: 0 | MS17: 52682.11 | MU17: 2187 | MV17: MOVE S320 | MW17: =SUM(MI17:MR17) -> 52682.11 | MX17: 957.74 | MY17: 4150 | MZ17: 0 | NA17: 0 | NB17: 0 | NC17: 0 | ND17: 750 | NE17: 0 | NF17: 0 | NG17: 0 | NH17: =SUM(MX17:NG17) -> 5857.74 | NI17: 1020 | NJ17: 317.4 | NK17: =(MS17/$N$116)*0 -> 0 | NL17: =(MT17/$O$116)*13804.26 -> 0 | NQ17: =NQ$3 -> 469.6789 | NT17: =78812.25/109 -> 723.04817 | NV17: =(NT17+NU17)*30% -> 216.91445 | NW17: =SUM(NT17:NV17) -> 939.96261 | NX17: =NS17+NW17 -> 939.96261 | NY17: =NH17-NX17 -> 4917.7774 | NZ17: 11501.23 | OA17: 5684.62 | OB17: 0 | OC17: 0 | OD17: 0 | OE17: 0 | OF17: 34548.06 | OG17: 0 | OH17: 0 | OI17: 0 | OJ17: 51733.91 | OK17: =ON17-OJ17 -> 0 | OL17: 2212 | OM17: MOVE S320 | ON17: =SUM(NZ17:OI17) -> 51733.91 | OO17: 957.37 | OP17: 4150 | OQ17: 0 | OR17: 0 | OS17: 0 | OT17: 0 | OU17: 750 | OV17: 0 | OW17: 0 | OX17: 0 | OY17: =SUM(OO17:OX17) -> 5857.37 | OZ17: 1020 | PA17: 317.4 | PB17: =(OJ17/$OJ$116)*56307.47 -> 1118.6558 | PC17: =(OK17/$O$116)*16757.91 -> 0 | PE17: 20 | PF17: =3288/100 -> 32.88 | PG17: 5 | PH17: =PH$3 -> 495.20491 | PJ17: =SUM(OZ17:PI17) -> 3009.1407 | PK17: =PK$3 -> 643.25573 | PM17: =(PK17+PL17)*30% -> 192.97672 | PN17: =SUM(PK17:PM17) -> 836.23245 | PO17: =PJ17+PN17 -> 3845.3732 | PP17: =OY17-PO17 -> 2011.9968 | PQ17: 12782.05 | PR17: 4325 | PS17: 0 | PT17: 0 | PU17: 0 | PV17: 0 | PW17: 30575.75 | PX17: 0 | PY17: 0 | PZ17: 0 | QA17: 47682.8 | QC17: 1982 | QD17: MOVE S320 | QE17: =SUM(PQ17:PZ17) -> 47682.8 | QF17: 1063.98 | QG17: 4150 | QH17: 0 | QI17: 0 | QJ17: 0 | QK17: 0 | QL17: 750 | QM17: 0 | QN17: 0 | QO17: 0 | QP17: =SUM(QF17:QO17) -> 5963.98 | QQ17: 1020 | QR17: 317.4 | QS17: =(QA17/$QA$116)*27743.06 -> 560.5116 | QT17: =(QB17/$O$116)*10429.01 -> 0 | QU17: =52000/60 -> 866.66667 | QV17: 20 | QW17: =2074.8/110 -> 18.861818 | QX17: 5 | QY17: =QY$3 -> 428.14773 | RA17: 1594.52 | RB17: =68119.05/110 -> 619.26409 | RD17: =(RB17+RC17)*30% -> 185.77923 | RE17: =SUM(RB17:RD17) -> 805.04332 | RF17: =RA17+RE17 -> 2399.5633 | RG17: =QP17-RF17 -> 3564.4167 | RH17: 13421.53 | RI17: 5022.78 | RJ17: 0 | RK17: 0 | RL17: 0 | RM17: 0 | RN17: 34381.17 | RO17: 0 | RP17: 0 | RQ17: 0 | RR17: 52825.48 | RT17: 2059 | RU17: MOVE S320 | RV17: 52825.48 | RW17: 1117.21 | RX17: 4150 | RY17: 0 | RZ17: 0 | SA17: 0 | SB17: 0 | SC17: 750 | SD17: 0 | SE17: 0 | SF17: 0 | SG17: 5267.21 | SH17: 1020 | SI17: 317.4 | SJ17: =(RR17/$RR$116)*25115.94 -> 519.11103 | SK17: =(RS17/$O$116)*12319.54 -> 0 | SL17: =52000/60 -> 866.66667 | SM17: 20 | SN17: =56040/113 -> 495.9292 | SO17: 5 | SP17: =SP$3 -> 428.52876 | SR17: 2073.6 | SS17: =SS$3 -> 596.28469 | SU17: =(SS17+ST17)*30% -> 178.88541 | SW17: =SR17+SV17 -> 2073.6 | SX17: =SG17-SW17 -> 3193.61 | SY17: =Q17+BH17+CY17+EP17+GG17+HX17+JO17+LF17+MW17+ON17+QE17+RV17 -> 460914.16 | SZ17: =AB17+BS17+DJ17+FA17+GR17+II17+JZ17+LQ17+NH17+OY17+QP17+SG17 -> 51476.01 | TA17: =AR17+CI17+DZ17+FQ17+HH17+IY17+KP17+MG17+NX17+PO17+RF17+SW17 -> 22350.126 | TB17: =SZ17-TA17 -> 29125.884
A18: 1116 | B18: 1116_PSZCZÓŁKI | Q18: =SUM(D18:M18) -> 0 | AB18: =SUM(R18:AA18) -> 0 | AE18: =(N18/$N$116)*21028.32 -> 0 | AM18: =SUM(AC18:AL18) -> 0 | AP18: =(AN18+AO18)*30% -> 0 | AQ18: =SUM(AN18:AP18) -> 0 | AR18: =AM18+AQ18 -> 0 | AS18: =AB18-AR18 -> 0 | BH18: =SUM(AT18:BC18) -> 0 | BS18: =SUM(BI18:BR18) -> 0 | BV18: =(BD18/$BD$116)*21083.85 -> 0 | BW18: =(BE18/$O$116)*12925.76 -> 0 | CG18: =(CE18+CF18)*30% -> 0 | CI18: =CD18+CH18 -> 0 | CJ18: =BS18-CI18 -> 0 | CY18: =SUM(CK18:CT18) -> 0 | DJ18: =SUM(CZ18:DI18) -> 0 | DM18: =(CU18/$CU$116)*24055.75 -> 0 | DN18: =(CV18/$O$116)*16258.02 -> 0 | DU18: =SUM(DK18:DT18) -> 0 | DX18: =(DV18+DW18)*30% -> 0 | DY18: =SUM(DV18:DX18) -> 0 | DZ18: =DU18+DY18 -> 0 | EA18: =DJ18-DZ18 -> 0 | EB18: 7.04 | EC18: 1307.57 | ED18: 0 | EE18: 0 | EF18: 0 | EG18: 0 | EH18: 0 | EI18: 0 | EJ18: 0 | EK18: 0 | EL18: 1314.61 | EN18: 88 | EO18: MOVE S320 | EP18: =SUM(EB18:EK18) -> 1314.61 | EQ18: 0.59 | ER18: 3500 | ES18: 0 | ET18: 0 | EU18: 0 | EV18: 0 | EW18: 0 | EX18: 0 | EY18: 0 | EZ18: 0 | FA18: =SUM(EQ18:EZ18) -> 3500.59 | FD18: =(EL18/$EL$116)*26325.65 -> 14.673744 | FE18: =(EM18/$O$116)*14846.27 -> 0 | FG18: 20 | FH18: =14375.2/102 -> 140.93333 | FI18: 5 | FJ18: =FJ$3 -> 424.6802 | FL18: =SUM(FB18:FK18) -> 605.28727 | FM18: =FM$3 -> 664.41902 | FO18: =(FM18+FN18)*30% -> 199.32571 | FP18: =SUM(FM18:FO18) -> 863.74473 | FQ18: =FL18+FP18 -> 1469.032 | FR18: =FA18-FQ18 -> 2031.558 | FS18: 0 | FT18: 1562.11 | FU18: 0 | FV18: 0 | FW18: 0 | FX18: 0 | FY18: 0 | FZ18: 0 | GA18: 0 | GB18: 0 | GC18: 1562.11 | GE18: 112 | GF18: MOVE S320 | GG18: =SUM(FS18:GB18) -> 1562.11 | GH18: 0 | GI18: 3500 | GJ18: 0 | GK18: 0 | GL18: 0 | GM18: 0 | GN18: 0 | GO18: 0 | GP18: 0 | GQ18: 0 | GR18: =SUM(GH18:GQ18) -> 3500 | GU18: =(GC18/$GC$116)*30198.86 -> 17.310123 | GV18: =(GD18/$O$116)*16844.27 -> 0 | GX18: 20 | GY18: =18860.4/102 -> 184.90588 | GZ18: 5 | HA18: =HA$3 -> 358.47794 | HC18: 916.06 | HD18: =HD$3 -> 866.9202 | HF18: =(HD18+HE18)*30% -> 260.07606 | HG18: =SUM(HD18:HF18) -> 1126.9963 | HH18: =HC18+HG18 -> 2043.0563 | HI18: =GR18-HH18 -> 1456.9437 | HJ18: 95 | HK18: 2134.24 | HL18: 0 | HM18: 0 | HN18: 0 | HO18: 0 | HP18: 0 | HQ18: 0 | HR18: 0 | HS18: 0 | HT18: 2229.24 | HV18: 180 | HW18: MOVE S320 | HX18: =SUM(HJ18:HS18) -> 2229.24 | HY18: 7.91 | HZ18: 3500 | IA18: 0 | IB18: 0 | IC18: 0 | ID18: 0 | IE18: 0 | IF18: 0 | IG18: 0 | IH18: 0 | II18: =SUM(HY18:IH18) -> 3507.91 | IL18: =(HT18/$HT$116)*31846.83 -> 24.69431 | IM18: =(HU18/$O$116)*17321.85 -> 0 | IO18: 20 | IP18: =24366/105 -> 232.05714 | IQ18: 5 | IR18: =IR$3 -> 445.62857 | IT18: 1160.43 | IU18: =IU$3 -> 538.79476 | IW18: =(IU18+IV18)*30% -> 161.63843 | IY18: =IT18+IX18 -> 1160.43 | IZ18: =II18-IY18 -> 2347.48 | JA18: 347.44 | JB18: 2519.64 | JC18: 0 | JD18: 0 | JE18: 0 | JF18: 0 | JG18: 0 | JH18: 0 | JI18: 0 | JJ18: 0 | JK18: 2867.08 | JM18: 204 | JO18: =SUM(JA18:JJ18) -> 2867.08 | JP18: 28.92 | JQ18: 3500 | JR18: 0 | JS18: 0 | JT18: 0 | JU18: 0 | JV18: 0 | JW18: 0 | JX18: 0 | JY18: 0 | JZ18: =SUM(JP18:JY18) -> 3528.92 | KC18: =(JK18/$N$116)*39010.72 -> 57.830975 | KD18: =(JL18/$O$116)*19244.4 -> 0 | KF18: 20 | KH18: 5 | KI18: =KI$3 -> 543.39953 | KK18: 949.5 | KL18: =KL$3 -> 497.32093 | KN18: =(KL18+KM18)*30% -> 149.19628 | KO18: =SUM(KL18:KN18) -> 646.51721 | KP18: =KK18+KO18 -> 1596.0172 | KQ18: =JZ18-KP18 -> 1932.9028 | KR18: 0 | KS18: 3657.36 | KT18: 0 | KU18: 0 | KV18: 0 | KW18: 0 | KX18: 0 | KY18: 0 | KZ18: 0 | LA18: 0 | LB18: 3657.36 | LD18: 275 | LE18: MOVE S320 | LF18: =SUM(KR18:LA18) -> 3657.36 | LG18: 0 | LH18: 3500 | LI18: 0 | LJ18: 0 | LK18: 0 | LL18: 0 | LM18: 0 | LN18: 0 | LO18: 0 | LP18: 0 | LQ18: =SUM(LG18:LP18) -> 3500 | LT18: =(LB18/$LB$116)*39133.48 -> 37.287253 | LU18: =(LC18/$O$116)*17015.75 -> 0 | LW18: 20 | LY18: 5 | LZ18: =LZ$3 -> 508.03738 | MB18: =SUM(LR18:MA18) -> 570.32464 | MC18: =MC$3 -> 593.54907 | ME18: =(MC18+MD18)*30% -> 178.06472 | MF18: =SUM(MC18:ME18) -> 771.61379 | MG18: =MB18+MF18 -> 1341.9384 | MH18: =LQ18-MG18 -> 2158.0616 | MI18: 0 | MJ18: 2046.33 | MK18: 0 | ML18: 0 | MM18: 0 | MN18: 0 | MO18: 0 | MP18: 0 | MQ18: 0 | MR18: 0 | MS18: 2046.33 | MU18: 163 | MV18: MOVE S320 | MW18: =SUM(MI18:MR18) -> 2046.33 | MX18: 0 | MY18: 3500 | MZ18: 0 | NA18: 0 | NB18: 0 | NC18: 0 | ND18: 0 | NE18: 0 | NF18: 0 | NG18: 0 | NH18: =SUM(MX18:NG18) -> 3500 | NK18: =(MS18/$N$116)*0 -> 0 | NL18: =(MT18/$O$116)*13804.26 -> 0 | NQ18: =NQ$3 -> 469.6789 | NT18: =78812.25/109 -> 723.04817 | NV18: =(NT18+NU18)*30% -> 216.91445 | NW18: =SUM(NT18:NV18) -> 939.96261 | NX18: =NS18+NW18 -> 939.96261 | NY18: =NH18-NX18 -> 2560.0374 | NZ18: 11.9 | OA18: 1972.96 | OB18: 0 | OC18: 0 | OD18: 0 | OE18: 0 | OF18: 0 | OG18: 0 | OH18: 0 | OI18: 0 | OJ18: 1984.86 | OK18: =ON18-OJ18 -> 0 | OL18: 172 | OM18: MOVE S320 | ON18: =SUM(NZ18:OI18) -> 1984.86 | OO18: 0.99 | OP18: 3500 | OQ18: 0 | OR18: 0 | OS18: 0 | OT18: 0 | OU18: 0 | OV18: 0 | OW18: 0 | OX18: 0 | OY18: =SUM(OO18:OX18) -> 3500.99 | PB18: =(OJ18/$OJ$116)*56307.47 -> 42.919145 | PC18: =(OK18/$O$116)*16757.91 -> 0 | PE18: 20 | PF18: =3288/100 -> 32.88 | PG18: 5 | PH18: =PH$3 -> 495.20491 | PJ18: =SUM(OZ18:PI18) -> 596.00405 | PK18: =PK$3 -> 643.25573 | PM18: =(PK18+PL18)*30% -> 192.97672 | PN18: =SUM(PK18:PM18) -> 836.23245 | PO18: =PJ18+PN18 -> 1432.2365 | PP18: =OY18-PO18 -> 2068.7535 | PQ18: 0 | PR18: 2020.13 | PS18: 0 | PT18: 0 | PU18: 0 | PV18: 0 | PW18: 0 | PX18: 0 | PY18: 0 | PZ18: 0 | QA18: 2020.13 | QC18: 162 | QD18: MOVE S320 | QE18: =SUM(PQ18:PZ18) -> 2020.13 | QF18: 0 | QG18: 3500 | QH18: 0 | QI18: 0 | QJ18: 0 | QK18: 0 | QL18: 0 | QM18: 0 | QN18: 0 | QO18: 0 | QP18: =SUM(QF18:QO18) -> 3500 | QS18: =(QA18/$QA$116)*27743.06 -> 23.74664 | QT18: =(QB18/$O$116)*10429.01 -> 0 | QV18: 20 | QW18: =2074.8/110 -> 18.861818 | QX18: 5 | QY18: =QY$3 -> 428.14773 | RA18: 939.51 | RB18: =68119.05/110 -> 619.26409 | RD18: =(RB18+RC18)*30% -> 185.77923 | RE18: =SUM(RB18:RD18) -> 805.04332 | RF18: =RA18+RE18 -> 1744.5533 | RG18: =QP18-RF18 -> 1755.4467 | RH18: 0 | RI18: 1765.7 | RJ18: 0 | RK18: 0 | RL18: 0 | RM18: 0 | RN18: 0 | RO18: 0 | RP18: 0 | RQ18: 0 | RR18: 1765.7 | RT18: 145 | RU18: MOVE S320 | RV18: 1765.7 | RW18: 0 | RX18: 3500 | RY18: 0 | RZ18: 0 | SA18: 0 | SB18: 0 | SC18: 0 | SD18: 0 | SE18: 0 | SF18: 0 | SG18: 3500 | SJ18: =(RR18/$RR$116)*25115.94 -> 17.351368 | SK18: =(RS18/$O$116)*12319.54 -> 0 | SL18: =52000/60 -> 866.66667 | SM18: 20 | SN18: =56040/113 -> 495.9292 | SO18: 5 | SP18: =SP$3 -> 428.52876 | SR18: 1410.53 | SS18: =SS$3 -> 596.28469 | SU18: =(SS18+ST18)*30% -> 178.88541 | SW18: =SR18+SV18 -> 1410.53 | SX18: =SG18-SW18 -> 2089.47 | SY18: =Q18+BH18+CY18+EP18+GG18+HX18+JO18+LF18+MW18+ON18+QE18+RV18 -> 19447.42 | SZ18: =AB18+BS18+DJ18+FA18+GR18+II18+JZ18+LQ18+NH18+OY18+QP18+SG18 -> 31538.41 | TA18: =AR18+CI18+DZ18+FQ18+HH18+IY18+KP18+MG18+NX18+PO18+RF18+SW18 -> 13137.756 | TB18: =SZ18-TA18 -> 18400.654
A19: 1117 | B19: 1117_ZAKOPANE | Q19: =SUM(D19:M19) -> 0 | AB19: =SUM(R19:AA19) -> 0 | AE19: =(N19/$N$116)*21028.32 -> 0 | AM19: =SUM(AC19:AL19) -> 0 | AP19: =(AN19+AO19)*30% -> 0 | AQ19: =SUM(AN19:AP19) -> 0 | AR19: =AM19+AQ19 -> 0 | AS19: =AB19-AR19 -> 0 | BH19: =SUM(AT19:BC19) -> 0 | BS19: =SUM(BI19:BR19) -> 0 | BV19: =(BD19/$BD$116)*21083.85 -> 0 | BW19: =(BE19/$O$116)*12925.76 -> 0 | CG19: =(CE19+CF19)*30% -> 0 | CI19: =CD19+CH19 -> 0 | CJ19: =BS19-CI19 -> 0 | CY19: =SUM(CK19:CT19) -> 0 | DJ19: =SUM(CZ19:DI19) -> 0 | DM19: =(CU19/$CU$116)*24055.75 -> 0 | DN19: =(CV19/$O$116)*16258.02 -> 0 | DU19: =SUM(DK19:DT19) -> 0 | DX19: =(DV19+DW19)*30% -> 0 | DY19: =SUM(DV19:DX19) -> 0 | DZ19: =DU19+DY19 -> 0 | EA19: =DJ19-DZ19 -> 0 | EB19: 1368.76 | EC19: 803.44 | ED19: 0 | EE19: 0 | EF19: 0 | EG19: 0 | EH19: 0 | EI19: 0 | EJ19: 0 | EK19: 0 | EL19: 2172.2 | EN19: 79 | EO19: MOVE S320 | EP19: =SUM(EB19:EK19) -> 2172.2 | EQ19: 113.93 | ER19: 3043.33 | ES19: 0 | ET19: 0 | EU19: 0 | EV19: 0 | EW19: 0 | EX19: 0 | EY19: 0 | EZ19: 0 | FA19: =SUM(EQ19:EZ19) -> 3157.26 | FD19: =(EL19/$EL$116)*26325.65 -> 24.246207 | FE19: =(EM19/$O$116)*14846.27 -> 0 | FG19: 20 | FH19: =14375.2/102 -> 140.93333 | FI19: 5 | FJ19: =FJ$3 -> 424.6802 | FL19: =SUM(FB19:FK19) -> 614.85974 | FM19: =FM$3 -> 664.41902 | FO19: =(FM19+FN19)*30% -> 199.32571 | FP19: =SUM(FM19:FO19) -> 863.74473 | FQ19: =FL19+FP19 -> 1478.6045 | FR19: =FA19-FQ19 -> 1678.6555 | FS19: 3361.31 | FT19: 2619.58 | FU19: 0 | FV19: 0 | FW19: 0 | FX19: 0 | FY19: 0 | FZ19: 0 | GA19: 0 | GB19: 0 | GC19: 5980.89 | GE19: 225 | GF19: MOVE S320 | GG19: =SUM(FS19:GB19) -> 5980.89 | GH19: 279.79 | GI19: 4150 | GJ19: 0 | GK19: 0 | GL19: 0 | GM19: 0 | GN19: 0 | GO19: 0 | GP19: 0 | GQ19: 0 | GR19: =SUM(GH19:GQ19) -> 4429.79 | GU19: =(GC19/$GC$116)*30198.86 -> 66.275705 | GV19: =(GD19/$O$116)*16844.27 -> 0 | GX19: 20 | GY19: =18860.4/102 -> 184.90588 | GZ19: 5 | HA19: =HA$3 -> 358.47794 | HC19: 985.06 | HD19: =HD$3 -> 866.9202 | HF19: =(HD19+HE19)*30% -> 260.07606 | HG19: =SUM(HD19:HF19) -> 1126.9963 | HH19: =HC19+HG19 -> 2112.0563 | HI19: =GR19-HH19 -> 2317.7337 | HJ19: 6693.8 | HK19: 2475.79 | HL19: 0 | HM19: 0 | HN19: 0 | HO19: 0 | HP19: 0 | HQ19: 0 | HR19: 0 | HS19: 0 | HT19: 9169.59 | HV19: 287 | HW19: MOVE S320 | HX19: =SUM(HJ19:HS19) -> 9169.59 | HY19: 557.19 | HZ19: 4150 | IA19: 0 | IB19: 0 | IC19: 0 | ID19: 0 | IE19: 0 | IF19: 0 | IG19: 0 | IH19: 0 | II19: =SUM(HY19:IH19) -> 4707.19 | IL19: =(HT19/$HT$116)*31846.83 -> 101.57574 | IM19: =(HU19/$O$116)*17321.85 -> 0 | IO19: 20 | IP19: =24366/105 -> 232.05714 | IQ19: 5 | IR19: =IR$3 -> 445.62857 | IT19: 1274.72 | IU19: =IU$3 -> 538.79476 | IW19: =(IU19+IV19)*30% -> 161.63843 | IY19: =IT19+IX19 -> 1274.72 | IZ19: =II19-IY19 -> 3432.47 | JA19: 10842.5 | JB19: 4613.35 | JC19: 0 | JD19: 0 | JE19: 0 | JF19: 0 | JG19: 0 | JH19: 0 | JI19: 0 | JJ19: 0 | JK19: 15455.85 | JM19: 500 | JO19: =SUM(JA19:JJ19) -> 15455.85 | JP19: 902.55 | JQ19: 4150 | JR19: 0 | JS19: 0 | JT19: 0 | JU19: 0 | JV19: 0 | JW19: 0 | JX19: 0 | JY19: 0 | JZ19: =SUM(JP19:JY19) -> 5052.55 | KC19: =(JK19/$N$116)*39010.72 -> 311.75512 | KD19: =(JL19/$O$116)*19244.4 -> 0 | KF19: 20 | KH19: 5 | KI19: =KI$3 -> 543.39953 | KK19: 1203.42 | KL19: =KL$3 -> 497.32093 | KN19: =(KL19+KM19)*30% -> 149.19628 | KO19: =SUM(KL19:KN19) -> 646.51721 | KP19: =KK19+KO19 -> 1849.9372 | KQ19: =JZ19-KP19 -> 3202.6128 | KR19: 13511.72 | KS19: 6989.85 | KT19: 0 | KU19: 0 | KV19: 0 | KW19: 0 | KX19: 0 | KY19: 0 | KZ19: 0 | LA19: 0 | LB19: 20501.57 | LD19: 663 | LE19: MOVE S320 | LF19: =SUM(KR19:LA19) -> 20501.57 | LG19: 1124.73 | LH19: 4150 | LI19: 0 | LJ19: 0 | LK19: 0 | LL19: 0 | LM19: 0 | LN19: 0 | LO19: 0 | LP19: 0 | LQ19: =SUM(LG19:LP19) -> 5274.73 | LT19: =(LB19/$LB$116)*39133.48 -> 209.01613 | LU19: =(LC19/$O$116)*17015.75 -> 0 | LW19: 20 | LY19: 5 | LZ19: =LZ$3 -> 508.03738 | MB19: =SUM(LR19:MA19) -> 742.05351 | MC19: =MC$3 -> 593.54907 | ME19: =(MC19+MD19)*30% -> 178.06472 | MF19: =SUM(MC19:ME19) -> 771.61379 | MG19: =MB19+MF19 -> 1513.6673 | MH19: =LQ19-MG19 -> 3761.0627 | MI19: 12383.63 | MJ19: 2722.25 | MK19: 0 | ML19: 0 | MM19: 0 | MN19: 0 | MO19: 0 | MP19: 0 | MQ19: 0 | MR19: 0 | MS19: 15105.88 | MU19: 427 | MV19: MOVE S320 | MW19: =SUM(MI19:MR19) -> 15105.88 | MX19: 1030.84 | MY19: 4150 | MZ19: 0 | NA19: 0 | NB19: 0 | NC19: 0 | ND19: 0 | NE19: 0 | NF19: 0 | NG19: 0 | NH19: =SUM(MX19:NG19) -> 5180.84 | NK19: =(MS19/$N$116)*0 -> 0 | NL19: =(MT19/$O$116)*13804.26 -> 0 | NQ19: =NQ$3 -> 469.6789 | NT19: =78812.25/109 -> 723.04817 | NV19: =(NT19+NU19)*30% -> 216.91445 | NW19: =SUM(NT19:NV19) -> 939.96261 | NX19: =NS19+NW19 -> 939.96261 | NY19: =NH19-NX19 -> 4240.8774 | NZ19: 6585.25 | OA19: 1674.99 | OB19: 0 | OC19: 0 | OD19: 0 | OE19: 0 | OF19: 0 | OG19: 0 | OH19: 0 | OI19: 0 | OJ19: 8260.24 | OK19: =ON19-OJ19 -> 0 | OL19: 235 | OM19: MOVE S320 | ON19: =SUM(NZ19:OI19) -> 8260.24 | OO19: 548.16 | OP19: 4150 | OQ19: 0 | OR19: 0 | OS19: 0 | OT19: 0 | OU19: 0 | OV19: 0 | OW19: 0 | OX19: 0 | OY19: =SUM(OO19:OX19) -> 4698.16 | PB19: =(OJ19/$OJ$116)*56307.47 -> 178.61332 | PC19: =(OK19/$O$116)*16757.91 -> 0 | PE19: 20 | PF19: =3288/100 -> 32.88 | PG19: 5 | PH19: =PH$3 -> 495.20491 | PJ19: =SUM(OZ19:PI19) -> 731.69823 | PK19: =PK$3 -> 643.25573 | PM19: =(PK19+PL19)*30% -> 192.97672 | PN19: =SUM(PK19:PM19) -> 836.23245 | PO19: =PJ19+PN19 -> 1567.9307 | PP19: =OY19-PO19 -> 3130.2293 | PQ19: 2892.8 | PR19: 1178.37 | PS19: 0 | PT19: 0 | PU19: 0 | PV19: 0 | PW19: 0 | PX19: 0 | PY19: 0 | PZ19: 0 | QA19: 4071.17 | QC19: 147 | QD19: MOVE S320 | QE19: =SUM(PQ19:PZ19) -> 4071.17 | QF19: 240.8 | QG19: 4150 | QH19: 0 | QI19: 0 | QJ19: 0 | QK19: 0 | QL19: 0 | QM19: 0 | QN19: 0 | QO19: 0 | QP19: =SUM(QF19:QO19) -> 4390.8 | QS19: =(QA19/$QA$116)*27743.06 -> 47.856627 | QT19: =(QB19/$O$116)*10429.01 -> 0 | QV19: 20 | QW19: =2074.8/110 -> 18.861818 | QX19: 5 | QY19: =QY$3 -> 428.14773 | RA19: 968.93 | RB19: =68119.05/110 -> 619.26409 | RD19: =(RB19+RC19)*30% -> 185.77923 | RE19: =SUM(RB19:RD19) -> 805.04332 | RF19: =RA19+RE19 -> 1773.9733 | RG19: =QP19-RF19 -> 2616.8267 | RH19: 13218.25 | RI19: 2285.93 | RJ19: 0 | RK19: 0 | RL19: 0 | RM19: 0 | RN19: 0 | RO19: 0 | RP19: 0 | RQ19: 0 | RR19: 15504.18 | RT19: 282 | RU19: MOVE S320 | RV19: 15504.18 | RW19: 1100.31 | RX19: 4150 | RY19: 0 | RZ19: 0 | SA19: 0 | SB19: 0 | SC19: 0 | SD19: 0 | SE19: 0 | SF19: 0 | SG19: 5250.31 | SJ19: =(RR19/$RR$116)*25115.94 -> 152.35812 | SK19: =(RS19/$O$116)*12319.54 -> 0 | SL19: =52000/60 -> 866.66667 | SM19: 20 | SN19: =56040/113 -> 495.9292 | SO19: 5 | SP19: =SP$3 -> 428.52876 | SR19: 1588.94 | SS19: =SS$3 -> 596.28469 | SU19: =(SS19+ST19)*30% -> 178.88541 | SW19: =SR19+SV19 -> 1588.94 | SX19: =SG19-SW19 -> 3661.37 | SY19: =Q19+BH19+CY19+EP19+GG19+HX19+JO19+LF19+MW19+ON19+QE19+RV19 -> 96221.57 | SZ19: =AB19+BS19+DJ19+FA19+GR19+II19+JZ19+LQ19+NH19+OY19+QP19+SG19 -> 42141.63 | TA19: =AR19+CI19+DZ19+FQ19+HH19+IY19+KP19+MG19+NX19+PO19+RF19+SW19 -> 14099.792 | TB19: =SZ19-TA19 -> 28041.838
A20: 1118 | B20: 1118_WROCŁAW GŁÓWNY | Q20: =SUM(D20:M20) -> 0 | AB20: =SUM(R20:AA20) -> 0 | AE20: =(N20/$N$116)*21028.32 -> 0 | AM20: =SUM(AC20:AL20) -> 0 | AP20: =(AN20+AO20)*30% -> 0 | AQ20: =SUM(AN20:AP20) -> 0 | AR20: =AM20+AQ20 -> 0 | AS20: =AB20-AR20 -> 0 | BH20: =SUM(AT20:BC20) -> 0 | BS20: =SUM(BI20:BR20) -> 0 | BV20: =(BD20/$BD$116)*21083.85 -> 0 | BW20: =(BE20/$O$116)*12925.76 -> 0 | CG20: =(CE20+CF20)*30% -> 0 | CI20: =CD20+CH20 -> 0 | CJ20: =BS20-CI20 -> 0 | CY20: =SUM(CK20:CT20) -> 0 | DJ20: =SUM(CZ20:DI20) -> 0 | DM20: =(CU20/$CU$116)*24055.75 -> 0 | DN20: =(CV20/$O$116)*16258.02 -> 0 | DU20: =SUM(DK20:DT20) -> 0 | DX20: =(DV20+DW20)*30% -> 0 | DY20: =SUM(DV20:DX20) -> 0 | DZ20: =DU20+DY20 -> 0 | EA20: =DJ20-DZ20 -> 0 | EP20: =SUM(EB20:EK20) -> 0 | FA20: =SUM(EQ20:EZ20) -> 0 | FD20: =(EL20/$EL$116)*26325.65 -> 0 | FE20: =(EM20/$O$116)*14846.27 -> 0 | FL20: =SUM(FB20:FK20) -> 0 | FO20: =(FM20+FN20)*30% -> 0 | FQ20: =FL20+FP20 -> 0 | FR20: =FA20-FQ20 -> 0 | GG20: =SUM(FS20:GB20) -> 0 | GR20: =SUM(GH20:GQ20) -> 0 | GU20: =(GC20/$GC$116)*30198.86 -> 0 | GV20: =(GD20/$O$116)*16844.27 -> 0 | HF20: =(HD20+HE20)*30% -> 0 | HG20: =SUM(HD20:HF20) -> 0 | HH20: =HC20+HG20 -> 0 | HI20: =GR20-HH20 -> 0 | HJ20: 0 | HK20: 0.17 | HL20: 0 | HM20: 0 | HN20: 0 | HO20: 0 | HP20: 0 | HQ20: 0 | HR20: 0 | HS20: 0 | HT20: 0.17 | HV20: 1 | HW20: MOVE S320 | HX20: =SUM(HJ20:HS20) -> 0.17 | HY20: 0 | HZ20: 0 | IA20: 0 | IB20: 0 | IC20: 0 | ID20: 0 | IE20: 0 | IF20: 0 | IG20: 0 | IH20: 0 | II20: =SUM(HY20:IH20) -> 0 | IL20: =(HT20/$HT$116)*31846.83 -> 0.0018831677 | IM20: =(HU20/$O$116)*17321.85 -> 0 | IW20: =(IU20+IV20)*30% -> 0 | IY20: =IT20+IX20 -> 0 | IZ20: =II20-IY20 -> 0 | JA20: 8329.67 | JB20: 10099.66 | JC20: 0 | JD20: 0 | JE20: 0 | JF20: 0 | JG20: 0 | JH20: 18128.2 | JI20: 0 | JJ20: 0 | JK20: 36557.53 | JM20: 2312 | JO20: =SUM(JA20:JJ20) -> 36557.53 | JP20: 693.38 | JQ20: 4150 | JR20: 0 | JS20: 0 | JT20: 0 | JU20: 0 | JV20: 0 | JW20: 1258.74 | JX20: 0 | JY20: 0 | JZ20: =SUM(JP20:JY20) -> 6102.12 | KC20: =(JK20/$N$116)*39010.72 -> 737.39052 | KD20: =(JL20/$O$116)*19244.4 -> 0 | KF20: 20 | KH20: 5 | KI20: =KI$3 -> 543.39953 | KK20: 1629.06 | KL20: =KL$3 -> 497.32093 | KN20: =(KL20+KM20)*30% -> 149.19628 | KO20: =SUM(KL20:KN20) -> 646.51721 | KP20: =KK20+KO20 -> 2275.5772 | KQ20: =JZ20-KP20 -> 3826.5428 | KR20: 11533.84 | KS20: 11724.68 | KT20: 40.4 | KU20: 0 | KV20: 0 | KW20: 0 | KX20: 0 | KY20: 23094.52 | KZ20: 0 | LA20: 0 | LB20: 46393.44 | LD20: 2787 | LE20: MOVE S320 | LF20: =SUM(KR20:LA20) -> 46393.44 | LG20: 960.1 | LH20: 4150 | LI20: 2.58 | LJ20: 0 | LK20: 0 | LL20: 0 | LM20: 0 | LN20: 1602.98 | LO20: 0 | LP20: 0 | LQ20: =SUM(LG20:LP20) -> 6715.66 | LT20: =(LB20/$LB$116)*39133.48 -> 472.98705 | LU20: =(LC20/$O$116)*17015.75 -> 0 | LW20: 20 | LY20: 5 | LZ20: =LZ$3 -> 508.03738 | MB20: =SUM(LR20:MA20) -> 1006.0244 | MC20: =MC$3 -> 593.54907 | ME20: =(MC20+MD20)*30% -> 178.06472 | MF20: =SUM(MC20:ME20) -> 771.61379 | MG20: =MB20+MF20 -> 1777.6382 | MH20: =LQ20-MG20 -> 4938.0218 | MI20: 6055.02 | MJ20: 8767.42 | MK20: 6.12 | ML20: 0 | MM20: 0 | MN20: 0 | MO20: 0 | MP20: 15297.47 | MQ20: 0 | MR20: 0 | MS20: 30126.03 | MU20: 1990 | MV20: MOVE S320 | MW20: =SUM(MI20:MR20) -> 30126.03 | MX20: 504.03 | MY20: 4150 | MZ20: 0.39 | NA20: 0 | NB20: 0 | NC20: 0 | ND20: 0 | NE20: 1061.58 | NF20: 0 | NG20: 0 | NH20: =SUM(MX20:NG20) -> 5716 | NK20: =(MS20/$N$116)*0 -> 0 | NL20: =(MT20/$O$116)*13804.26 -> 0 | NQ20: =NQ$3 -> 469.6789 | NT20: =78812.25/109 -> 723.04817 | NV20: =(NT20+NU20)*30% -> 216.91445 | NW20: =SUM(NT20:NV20) -> 939.96261 | NX20: =NS20+NW20 -> 939.96261 | NY20: =NH20-NX20 -> 4776.0374 | NZ20: 8055.16 | OA20: 11182.58 | OB20: 0 | OC20: 0 | OD20: 0 | OE20: 0 | OF20: 0 | OG20: 19312.46 | OH20: 0 | OI20: 0 | OJ20: 38550.2 | OK20: =ON20-OJ20 -> 0 | OL20: 2593 | OM20: MOVE S320 | ON20: =SUM(NZ20:OI20) -> 38550.2 | OO20: 670.55 | OP20: 4150 | OQ20: 0 | OR20: 0 | OS20: 0 | OT20: 0 | OU20: 0 | OV20: 1340.8 | OW20: 0 | OX20: 0 | OY20: =SUM(OO20:OX20) -> 6161.35 | PB20: =(OJ20/$OJ$116)*56307.47 -> 833.58103 | PC20: =(OK20/$O$116)*16757.91 -> 0 | PE20: 20 | PF20: =3288/100 -> 32.88 | PG20: 5 | PH20: =PH$3 -> 495.20491 | PJ20: =SUM(OZ20:PI20) -> 1386.6659 | PK20: =PK$3 -> 643.25573 | PM20: =(PK20+PL20)*30% -> 192.97672 | PN20: =SUM(PK20:PM20) -> 836.23245 | PO20: =PJ20+PN20 -> 2222.8984 | PP20: =OY20-PO20 -> 3938.4516 | PQ20: 7163.67 | PR20: 10421.19 | PS20: 23.2 | PT20: 0 | PU20: 0 | PV20: 0 | PW20: 0 | PX20: 17816.66 | PY20: 0 | PZ20: 0 | QA20: 35424.72 | QC20: 2372 | QD20: MOVE S320 | QE20: =SUM(PQ20:PZ20) -> 35424.72 | QF20: 596.32 | QG20: 4150 | QH20: 1.48 | QI20: 0 | QJ20: 0 | QK20: 0 | QL20: 0 | QM20: 1236.8 | QN20: 0 | QO20: 0 | QP20: =SUM(QF20:QO20) -> 5984.6 | QS20: =(QA20/$QA$116)*27743.06 -> 416.41779 | QT20: =(QB20/$O$116)*10429.01 -> 0 | QV20: 20 | QW20: =2074.8/110 -> 18.861818 | QX20: 5 | QY20: =QY$3 -> 428.14773 | RA20: 1418.69 | RB20: =68119.05/110 -> 619.26409 | RD20: =(RB20+RC20)*30% -> 185.77923 | RE20: =SUM(RB20:RD20) -> 805.04332 | RF20: =RA20+RE20 -> 2223.7333 | RG20: =QP20-RF20 -> 3760.8667 | RH20: 6616.95 | RI20: 9914.93 | RJ20: 0 | RK20: 0 | RL20: 0 | RM20: 0 | RN20: 0 | RO20: 18979.88 | RP20: 0 | RQ20: 0 | RR20: 35511.76 | RT20: 2262 | RU20: MOVE S320 | RV20: 35511.76 | RW20: 550.81 | RX20: 4150 | RY20: 0 | RZ20: 0 | SA20: 0 | SB20: 0 | SC20: 0 | SD20: 1318.02 | SE20: 0 | SF20: 0 | SG20: 6018.83 | SJ20: =(RR20/$RR$116)*25115.94 -> 348.97073 | SK20: =(RS20/$O$116)*12319.54 -> 0 | SL20: =52000/60 -> 866.66667 | SM20: 20 | SN20: =56040/113 -> 495.9292 | SO20: 5 | SP20: =SP$3 -> 428.52876 | SR20: 1848.76 | SS20: =SS$3 -> 596.28469 | SU20: =(SS20+ST20)*30% -> 178.88541 | SW20: =SR20+SV20 -> 1848.76 | SX20: =SG20-SW20 -> 4170.07 | SY20: =Q20+BH20+CY20+EP20+GG20+HX20+JO20+LF20+MW20+ON20+QE20+RV20 -> 222563.85 | SZ20: =AB20+BS20+DJ20+FA20+GR20+II20+JZ20+LQ20+NH20+OY20+QP20+SG20 -> 36698.56 | TA20: =AR20+CI20+DZ20+FQ20+HH20+IY20+KP20+MG20+NX20+PO20+RF20+SW20 -> 11288.57 | TB20: =SZ20-TA20 -> 25409.99
A21: 1119 | B21: 1119_GŁOGÓW | Q21: =SUM(D21:M21) -> 0 | AB21: =SUM(R21:AA21) -> 0 | AE21: =(N21/$N$116)*21028.32 -> 0 | AM21: =SUM(AC21:AL21) -> 0 | AP21: =(AN21+AO21)*30% -> 0 | AQ21: =SUM(AN21:AP21) -> 0 | AR21: =AM21+AQ21 -> 0 | AS21: =AB21-AR21 -> 0 | BH21: =SUM(AT21:BC21) -> 0 | BS21: =SUM(BI21:BR21) -> 0 | BV21: =(BD21/$BD$116)*21083.85 -> 0 | BW21: =(BE21/$O$116)*12925.76 -> 0 | CG21: =(CE21+CF21)*30% -> 0 | CI21: =CD21+CH21 -> 0 | CJ21: =BS21-CI21 -> 0 | CY21: =SUM(CK21:CT21) -> 0 | DJ21: =SUM(CZ21:DI21) -> 0 | DM21: =(CU21/$CU$116)*24055.75 -> 0 | DN21: =(CV21/$O$116)*16258.02 -> 0 | DU21: =SUM(DK21:DT21) -> 0 | DX21: =(DV21+DW21)*30% -> 0 | DY21: =SUM(DV21:DX21) -> 0 | DZ21: =DU21+DY21 -> 0 | EA21: =DJ21-DZ21 -> 0 | EP21: =SUM(EB21:EK21) -> 0 | FA21: =SUM(EQ21:EZ21) -> 0 | FD21: =(EL21/$EL$116)*26325.65 -> 0 | FE21: =(EM21/$O$116)*14846.27 -> 0 | FL21: =SUM(FB21:FK21) -> 0 | FO21: =(FM21+FN21)*30% -> 0 | FQ21: =FL21+FP21 -> 0 | FR21: =FA21-FQ21 -> 0 | GG21: =SUM(FS21:GB21) -> 0 | GR21: =SUM(GH21:GQ21) -> 0 | GU21: =(GC21/$GC$116)*30198.86 -> 0 | GV21: =(GD21/$O$116)*16844.27 -> 0 | HF21: =(HD21+HE21)*30% -> 0 | HG21: =SUM(HD21:HF21) -> 0 | HH21: =HC21+HG21 -> 0 | HI21: =GR21-HH21 -> 0 | HJ21: 0 | HK21: 0.17 | HL21: 0 | HM21: 0 | HN21: 0 | HO21: 0 | HP21: 0 | HQ21: 0 | HR21: 0 | HS21: 0 | HT21: 0.17 | HV21: 1 | HW21: MOVE S320 | HX21: =SUM(HJ21:HS21) -> 0.17 | HY21: 0 | HZ21: 0 | IA21: 0 | IB21: 0 | IC21: 0 | ID21: 0 | IE21: 0 | IF21: 0 | IG21: 0 | IH21: 0 | II21: =SUM(HY21:IH21) -> 0 | IL21: =(HT21/$HT$116)*31846.83 -> 0.0018831677 | IM21: =(HU21/$O$116)*17321.85 -> 0 | IW21: =(IU21+IV21)*30% -> 0 | IY21: =IT21+IX21 -> 0 | IZ21: =II21-IY21 -> 0 | JA21: 763.8 | JB21: 1622.36 | JC21: 3 | JD21: 0 | JE21: 0 | JF21: 0 | JG21: 0 | JH21: 2653.55 | JI21: 0 | JJ21: 0 | JK21: 5042.71 | JM21: 304 | JO21: =SUM(JA21:JJ21) -> 5042.71 | JP21: 63.58 | JQ21: 4150 | JR21: 0.19 | JS21: 0 | JT21: 0 | JU21: 0 | JV21: 0 | JW21: 184.07 | JX21: 0 | JY21: 0 | JZ21: =SUM(JP21:JY21) -> 4397.84 | KC21: =(JK21/$N$116)*39010.72 -> 101.71493 | KD21: =(JL21/$O$116)*19244.4 -> 0 | KF21: 20 | KH21: 5 | KI21: =KI$3 -> 543.39953 | KK21: 993.38 | KL21: =KL$3 -> 497.32093 | KN21: =(KL21+KM21)*30% -> 149.19628 | KO21: =SUM(KL21:KN21) -> 646.51721 | KP21: =KK21+KO21 -> 1639.8972 | KQ21: =JZ21-KP21 -> 2757.9428 | KR21: 528.22 | KS21: 2194.93 | KT21: 0 | KU21: 0 | KV21: 0 | KW21: 0 | KX21: 0 | KY21: 3814.3 | KZ21: 0 | LA21: 0 | LB21: 6537.45 | LD21: 349 | LE21: MOVE S320 | LF21: =SUM(KR21:LA21) -> 6537.45 | LG21: 43.97 | LH21: 4150 | LI21: 0 | LJ21: 0 | LK21: 0 | LL21: 0 | LM21: 0 | LN21: 264.74 | LO21: 0 | LP21: 0 | LQ21: =SUM(LG21:LP21) -> 4458.71 | LT21: =(LB21/$LB$116)*39133.48 -> 66.650139 | LU21: =(LC21/$O$116)*17015.75 -> 0 | LW21: 20 | LY21: 5 | LZ21: =LZ$3 -> 508.03738 | MB21: =SUM(LR21:MA21) -> 599.68752 | MC21: =MC$3 -> 593.54907 | ME21: =(MC21+MD21)*30% -> 178.06472 | MF21: =SUM(MC21:ME21) -> 771.61379 | MG21: =MB21+MF21 -> 1371.3013 | MH21: =LQ21-MG21 -> 3087.4087 | MI21: 695.58 | MJ21: 1036.83 | MK21: 0 | ML21: 0 | MM21: 0 | MN21: 0 | MO21: 0 | MP21: 2210.19 | MQ21: 0 | MR21: 0 | MS21: 3942.6 | MU21: 212 | MV21: MOVE S320 | MW21: =SUM(MI21:MR21) -> 3942.6 | MX21: 57.9 | MY21: 4150 | MZ21: 0 | NA21: 0 | NB21: 0 | NC21: 0 | ND21: 0 | NE21: 153.48 | NF21: 0 | NG21: 0 | NH21: =SUM(MX21:NG21) -> 4361.38 | NK21: =(MS21/$N$116)*0 -> 0 | NL21: =(MT21/$O$116)*13804.26 -> 0 | NQ21: =NQ$3 -> 469.6789 | NT21: =78812.25/109 -> 723.04817 | NV21: =(NT21+NU21)*30% -> 216.91445 | NW21: =SUM(NT21:NV21) -> 939.96261 | NX21: =NS21+NW21 -> 939.96261 | NY21: =NH21-NX21 -> 3421.4174 | NZ21: 1256.27 | OA21: 1673.02 | OB21: 0 | OC21: 0 | OD21: 0 | OE21: 0 | OF21: 0 | OG21: 4063.67 | OH21: 0 | OI21: 0 | OJ21: 6992.96 | OK21: =ON21-OJ21 -> 0 | OL21: 412 | OM21: MOVE S320 | ON21: =SUM(NZ21:OI21) -> 6992.96 | OO21: 104.57 | OP21: 4150 | OQ21: 0 | OR21: 0 | OS21: 0 | OT21: 0 | OU21: 0 | OV21: 282.13 | OW21: 0 | OX21: 0 | OY21: =SUM(OO21:OX21) -> 4536.7 | PB21: =(OJ21/$OJ$116)*56307.47 -> 151.2106 | PC21: =(OK21/$O$116)*16757.91 -> 0 | PE21: 20 | PF21: =3288/100 -> 32.88 | PG21: 5 | PH21: =PH$3 -> 495.20491 | PJ21: =SUM(OZ21:PI21) -> 704.29551 | PK21: =PK$3 -> 643.25573 | PM21: =(PK21+PL21)*30% -> 192.97672 | PN21: =SUM(PK21:PM21) -> 836.23245 | PO21: =PJ21+PN21 -> 1540.528 | PP21: =OY21-PO21 -> 2996.172 | PQ21: 903.8 | PR21: 1774.83 | PS21: 0 | PT21: 0 | PU21: 0 | PV21: 0 | PW21: 0 | PX21: 3038.38 | PY21: 0 | PZ21: 0 | QA21: 5717.01 | QC21: 307 | QD21: MOVE S320 | QE21: =SUM(PQ21:PZ21) -> 5717.01 | QF21: 75.23 | QG21: 4150 | QH21: 0 | QI21: 0 | QJ21: 0 | QK21: 0 | QL21: 0 | QM21: 211 | QN21: 0 | QO21: 0 | QP21: =SUM(QF21:QO21) -> 4436.23 | QS21: =(QA21/$QA$116)*27743.06 -> 67.203486 | QT21: =(QB21/$O$116)*10429.01 -> 0 | QV21: 20 | QW21: =2074.8/110 -> 18.861818 | QX21: 5 | QY21: =QY$3 -> 428.14773 | RA21: 992.54 | RB21: =68119.05/110 -> 619.26409 | RD21: =(RB21+RC21)*30% -> 185.77923 | RE21: =SUM(RB21:RD21) -> 805.04332 | RF21: =RA21+RE21 -> 1797.5833 | RG21: =QP21-RF21 -> 2638.6467 | RH21: 1267.42 | RI21: 1257.07 | RJ21: 16.2 | RK21: 0 | RL21: 0 | RM21: 0 | RN21: 0 | RO21: 4317.61 | RP21: 0 | RQ21: 0 | RR21: 6858.3 | RT21: 377 | RU21: MOVE S320 | RV21: 6858.3 | RW21: 105.5 | RX21: 4150 | RY21: 1.04 | RZ21: 0 | SA21: 0 | SB21: 0 | SC21: 0 | SD21: 299.75 | SE21: 0 | SF21: 0 | SG21: 4556.29 | SJ21: =(RR21/$RR$116)*25115.94 -> 67.39587 | SK21: =(RS21/$O$116)*12319.54 -> 0 | SL21: =52000/60 -> 866.66667 | SM21: 20 | SN21: =56040/113 -> 495.9292 | SO21: 5 | SP21: =SP$3 -> 428.52876 | SR21: 1476.66 | SS21: =SS$3 -> 596.28469 | SU21: =(SS21+ST21)*30% -> 178.88541 | SW21: =SR21+SV21 -> 1476.66 | SX21: =SG21-SW21 -> 3079.63 | SY21: =Q21+BH21+CY21+EP21+GG21+HX21+JO21+LF21+MW21+ON21+QE21+RV21 -> 35091.2 | SZ21: =AB21+BS21+DJ21+FA21+GR21+II21+JZ21+LQ21+NH21+OY21+QP21+SG21 -> 26747.15 | TA21: =AR21+CI21+DZ21+FQ21+HH21+IY21+KP21+MG21+NX21+PO21+RF21+SW21 -> 8765.9324 | TB21: =SZ21-TA21 -> 17981.218 | TE21: relokacja w miejsce automatu stacjonarnego?
A22: 1120 | B22: 1120_KĘDZIERZYN KOŹLE | Q22: =SUM(D22:M22) -> 0 | AB22: =SUM(R22:AA22) -> 0 | AE22: =(N22/$N$116)*21028.32 -> 0 | AM22: =SUM(AC22:AL22) -> 0 | AP22: =(AN22+AO22)*30% -> 0 | AQ22: =SUM(AN22:AP22) -> 0 | AR22: =AM22+AQ22 -> 0 | AS22: =AB22-AR22 -> 0 | BH22: =SUM(AT22:BC22) -> 0 | BS22: =SUM(BI22:BR22) -> 0 | BV22: =(BD22/$BD$116)*21083.85 -> 0 | BW22: =(BE22/$O$116)*12925.76 -> 0 | CG22: =(CE22+CF22)*30% -> 0 | CI22: =CD22+CH22 -> 0 | CJ22: =BS22-CI22 -> 0 | CY22: =SUM(CK22:CT22) -> 0 | DJ22: =SUM(CZ22:DI22) -> 0 | DM22: =(CU22/$CU$116)*24055.75 -> 0 | DN22: =(CV22/$O$116)*16258.02 -> 0 | DU22: =SUM(DK22:DT22) -> 0 | DX22: =(DV22+DW22)*30% -> 0 | DY22: =SUM(DV22:DX22) -> 0 | DZ22: =DU22+DY22 -> 0 | EA22: =DJ22-DZ22 -> 0 | EP22: =SUM(EB22:EK22) -> 0 | FA22: =SUM(EQ22:EZ22) -> 0 | FD22: =(EL22/$EL$116)*26325.65 -> 0 | FE22: =(EM22/$O$116)*14846.27 -> 0 | FL22: =SUM(FB22:FK22) -> 0 | FO22: =(FM22+FN22)*30% -> 0 | FQ22: =FL22+FP22 -> 0 | FR22: =FA22-FQ22 -> 0 | GG22: =SUM(FS22:GB22) -> 0 | GR22: =SUM(GH22:GQ22) -> 0 | GU22: =(GC22/$GC$116)*30198.86 -> 0 | GV22: =(GD22/$O$116)*16844.27 -> 0 | HF22: =(HD22+HE22)*30% -> 0 | HG22: =SUM(HD22:HF22) -> 0 | HH22: =HC22+HG22 -> 0 | HI22: =GR22-HH22 -> 0 | HW22: MOVE S320 | HX22: =SUM(HJ22:HS22) -> 0 | II22: =SUM(HY22:IH22) -> 0 | IL22: =(HT22/$HT$116)*31846.83 -> 0 | IM22: =(HU22/$O$116)*17321.85 -> 0 | IW22: =(IU22+IV22)*30% -> 0 | IY22: =IT22+IX22 -> 0 | IZ22: =II22-IY22 -> 0 | JO22: =SUM(JA22:JJ22) -> 0 | JZ22: =SUM(JP22:JY22) -> 0 | KC22: =(JK22/$N$116)*39010.72 -> 0 | KD22: =(JL22/$O$116)*19244.4 -> 0 | KN22: =(KL22+KM22)*30% -> 0 | KO22: =SUM(KL22:KN22) -> 0 | KP22: =KK22+KO22 -> 0 | KQ22: =JZ22-KP22 -> 0 | LF22: =SUM(KR22:LA22) -> 0 | LQ22: =SUM(LG22:LP22) -> 0 | LT22: =(LB22/$LB$116)*39133.48 -> 0 | LU22: =(LC22/$O$116)*17015.75 -> 0 | MB22: =SUM(LR22:MA22) -> 0 | ME22: =(MC22+MD22)*30% -> 0 | MF22: =SUM(MC22:ME22) -> 0 | MG22: =MB22+MF22 -> 0 | MH22: =LQ22-MG22 -> 0 | MI22: 938.64 | MJ22: 2130.37 | MK22: 29.3 | ML22: 0 | MM22: 0 | MN22: 0 | MO22: 0 | MP22: 0 | MQ22: 0 | MR22: 0 | MS22: 3098.31 | MU22: 210 | MV22: MOVE S320 | MW22: =SUM(MI22:MR22) -> 3098.31 | MX22: 78.13 | MY22: 3458.33 | MZ22: 1.87 | NA22: 0 | NB22: 0 | NC22: 0 | ND22: 0 | NE22: 0 | NF22: 0 | NG22: 0 | NH22: =SUM(MX22:NG22) -> 3538.33 | NK22: =(MS22/$N$116)*0 -> 0 | NL22: =(MT22/$O$116)*13804.26 -> 0 | NQ22: =NQ$3 -> 469.6789 | NT22: =78812.25/109 -> 723.04817 | NV22: =(NT22+NU22)*30% -> 216.91445 | NW22: =SUM(NT22:NV22) -> 939.96261 | NX22: =NS22+NW22 -> 939.96261 | NY22: =NH22-NX22 -> 2598.3674 | NZ22: 1837.61 | OA22: 4264.1 | OB22: 0 | OC22: 0 | OD22: 0 | OE22: 0 | OF22: 0 | OG22: 33.3 | OH22: 0 | OI22: 0 | OJ22: 6135.01 | OK22: =ON22-OJ22 -> 0 | OL22: 380 | OM22: MOVE S320 | ON22: =SUM(NZ22:OI22) -> 6135.01 | OO22: 152.96 | OP22: 4150 | OQ22: 0 | OR22: 0 | OS22: 0 | OT22: 0 | OU22: 0 | OV22: 2.31 | OW22: 0 | OX22: 0 | OY22: =SUM(OO22:OX22) -> 4305.27 | PB22: =(OJ22/$OJ$116)*56307.47 -> 132.65892 | PC22: =(OK22/$O$116)*16757.91 -> 0 | PE22: 20 | PF22: =3288/100 -> 32.88 | PG22: 5 | PH22: =PH$3 -> 495.20491 | PJ22: =SUM(OZ22:PI22) -> 685.74383 | PK22: =PK$3 -> 643.25573 | PM22: =(PK22+PL22)*30% -> 192.97672 | PN22: =SUM(PK22:PM22) -> 836.23245 | PO22: =PJ22+PN22 -> 1521.9763 | PP22: =OY22-PO22 -> 2783.2937 | PQ22: 1659.66 | PR22: 4164.58 | PS22: 0 | PT22: 0 | PU22: 0 | PV22: 0 | PW22: 0 | PX22: 0 | PY22: 0 | PZ22: 0 | QA22: 5824.24 | QC22: 342 | QD22: MOVE S320 | QE22: =SUM(PQ22:PZ22) -> 5824.24 | QF22: 138.15 | QG22: 4150 | QH22: 0 | QI22: 0 | QJ22: 0 | QK22: 0 | QL22: 0 | QM22: 0 | QN22: 0 | QO22: 0 | QP22: =SUM(QF22:QO22) -> 4288.15 | QS22: =(QA22/$QA$116)*27743.06 -> 68.463976 | QT22: =(QB22/$O$116)*10429.01 -> 0 | QV22: 20 | QW22: =2074.8/110 -> 18.861818 | QX22: 5 | QY22: =QY$3 -> 428.14773 | RA22: 994.08 | RB22: =68119.05/110 -> 619.26409 | RD22: =(RB22+RC22)*30% -> 185.77923 | RE22: =SUM(RB22:RD22) -> 805.04332 | RF22: =RA22+RE22 -> 1799.1233 | RG22: =QP22-RF22 -> 2489.0267 | RH22: 1912.35 | RI22: 3183.59 | RJ22: 0 | RK22: 0 | RL22: 0 | RM22: 0 | RN22: 0 | RO22: 25.9 | RP22: 11.31 | RQ22: 0 | RR22: 5133.15 | RT22: 325 | RU22: MOVE S320 | RV22: 5133.15 | RW22: 159.19 | RX22: 4150 | RY22: 0 | RZ22: 0 | SA22: 0 | SB22: 0 | SC22: 0 | SD22: 1.8 | SE22: 0.63 | SF22: 0 | SG22: 4311.62 | SJ22: =(RR22/$RR$116)*25115.94 -> 50.442983 | SK22: =(RS22/$O$116)*12319.54 -> 0 | SL22: =52000/60 -> 866.66667 | SM22: 20 | SN22: =56040/113 -> 495.9292 | SO22: 5 | SP22: =SP$3 -> 428.52876 | SR22: 1454.26 | SS22: =SS$3 -> 596.28469 | SU22: =(SS22+ST22)*30% -> 178.88541 | SW22: =SR22+SV22 -> 1454.26 | SX22: =SG22-SW22 -> 2857.36 | SY22: =Q22+BH22+CY22+EP22+GG22+HX22+JO22+LF22+MW22+ON22+QE22+RV22 -> 20190.71 | SZ22: =AB22+BS22+DJ22+FA22+GR22+II22+JZ22+LQ22+NH22+OY22+QP22+SG22 -> 16443.37 | TA22: =AR22+CI22+DZ22+FQ22+HH22+IY22+KP22+MG22+NX22+PO22+RF22+SW22 -> 5715.3222 | TB22: =SZ22-TA22 -> 10728.048
A23: 1121 | B23: 1121_GOGOLIN | Q23: =SUM(D23:M23) -> 0 | AB23: =SUM(R23:AA23) -> 0 | AE23: =(N23/$N$116)*21028.32 -> 0 | AM23: =SUM(AC23:AL23) -> 0 | AP23: =(AN23+AO23)*30% -> 0 | AQ23: =SUM(AN23:AP23) -> 0 | AR23: =AM23+AQ23 -> 0 | AS23: =AB23-AR23 -> 0 | BH23: =SUM(AT23:BC23) -> 0 | BS23: =SUM(BI23:BR23) -> 0 | BV23: =(BD23/$BD$116)*21083.85 -> 0 | BW23: =(BE23/$O$116)*12925.76 -> 0 | CG23: =(CE23+CF23)*30% -> 0 | CI23: =CD23+CH23 -> 0 | CJ23: =BS23-CI23 -> 0 | CY23: =SUM(CK23:CT23) -> 0 | DJ23: =SUM(CZ23:DI23) -> 0 | DM23: =(CU23/$CU$116)*24055.75 -> 0 | DN23: =(CV23/$O$116)*16258.02 -> 0 | DU23: =SUM(DK23:DT23) -> 0 | DX23: =(DV23+DW23)*30% -> 0 | DY23: =SUM(DV23:DX23) -> 0 | DZ23: =DU23+DY23 -> 0 | EA23: =DJ23-DZ23 -> 0 | EP23: =SUM(EB23:EK23) -> 0 | FA23: =SUM(EQ23:EZ23) -> 0 | FD23: =(EL23/$EL$116)*26325.65 -> 0 | FE23: =(EM23/$O$116)*14846.27 -> 0 | FL23: =SUM(FB23:FK23) -> 0 | FO23: =(FM23+FN23)*30% -> 0 | FQ23: =FL23+FP23 -> 0 | FR23: =FA23-FQ23 -> 0 | GG23: =SUM(FS23:GB23) -> 0 | GR23: =SUM(GH23:GQ23) -> 0 | GU23: =(GC23/$GC$116)*30198.86 -> 0 | GV23: =(GD23/$O$116)*16844.27 -> 0 | HF23: =(HD23+HE23)*30% -> 0 | HG23: =SUM(HD23:HF23) -> 0 | HH23: =HC23+HG23 -> 0 | HI23: =GR23-HH23 -> 0 | HW23: MOVE S320 | HX23: =SUM(HJ23:HS23) -> 0 | II23: =SUM(HY23:IH23) -> 0 | IL23: =(HT23/$HT$116)*31846.83 -> 0 | IM23: =(HU23/$O$116)*17321.85 -> 0 | IW23: =(IU23+IV23)*30% -> 0 | IY23: =IT23+IX23 -> 0 | IZ23: =II23-IY23 -> 0 | JO23: =SUM(JA23:JJ23) -> 0 | JZ23: =SUM(JP23:JY23) -> 0 | KC23: =(JK23/$N$116)*39010.72 -> 0 | KD23: =(JL23/$O$116)*19244.4 -> 0 | KN23: =(KL23+KM23)*30% -> 0 | KO23: =SUM(KL23:KN23) -> 0 | KP23: =KK23+KO23 -> 0 | KQ23: =JZ23-KP23 -> 0 | LF23: =SUM(KR23:LA23) -> 0 | LQ23: =SUM(LG23:LP23) -> 0 | LT23: =(LB23/$LB$116)*39133.48 -> 0 | LU23: =(LC23/$O$116)*17015.75 -> 0 | MB23: =SUM(LR23:MA23) -> 0 | ME23: =(MC23+MD23)*30% -> 0 | MF23: =SUM(MC23:ME23) -> 0 | MG23: =MB23+MF23 -> 0 | MH23: =LQ23-MG23 -> 0 | MI23: 745.4 | MJ23: 2882.27 | MK23: 0 | ML23: 0 | MM23: 0 | MN23: 0 | MO23: 0 | MP23: 0 | MQ23: 0 | MR23: 0 | MS23: 3627.67 | MU23: 276 | MV23: MOVE S320 | MW23: =SUM(MI23:MR23) -> 3627.67 | MX23: 62.05 | MY23: 3458.33 | MZ23: 0 | NA23: 0 | NB23: 0 | NC23: 0 | ND23: 0 | NE23: 0 | NF23: 0 | NG23: 0 | NH23: =SUM(MX23:NG23) -> 3520.38 | NK23: =(MS23/$N$116)*0 -> 0 | NL23: =(MT23/$O$116)*13804.26 -> 0 | NQ23: =NQ$3 -> 469.6789 | NT23: =78812.25/109 -> 723.04817 | NV23: =(NT23+NU23)*30% -> 216.91445 | NW23: =SUM(NT23:NV23) -> 939.96261 | NX23: =NS23+NW23 -> 939.96261 | NY23: =NH23-NX23 -> 2580.4174 | NZ23: 1250.33 | OA23: 3753.37 | OB23: 0 | OC23: 0 | OD23: 0 | OE23: 0 | OF23: 0 | OG23: 0 | OH23: 0 | OI23: 0 | OJ23: 5003.7 | OK23: =ON23-OJ23 -> 0 | OL23: 391 | OM23: MOVE S320 | ON23: =SUM(NZ23:OI23) -> 5003.7 | OO23: 104.08 | OP23: 4150 | OQ23: 0 | OR23: 0 | OS23: 0 | OT23: 0 | OU23: 0 | OV23: 0 | OW23: 0 | OX23: 0 | OY23: =SUM(OO23:OX23) -> 4254.08 | PB23: =(OJ23/$OJ$116)*56307.47 -> 108.19631 | PC23: =(OK23/$O$116)*16757.91 -> 0 | PE23: 20 | PF23: =3288/100 -> 32.88 | PG23: 5 | PH23: =PH$3 -> 495.20491 | PJ23: =SUM(OZ23:PI23) -> 661.28122 | PK23: =PK$3 -> 643.25573 | PM23: =(PK23+PL23)*30% -> 192.97672 | PN23: =SUM(PK23:PM23) -> 836.23245 | PO23: =PJ23+PN23 -> 1497.5137 | PP23: =OY23-PO23 -> 2756.5663 | PQ23: 1460.79 | PR23: 3698.85 | PS23: 0 | PT23: 0 | PU23: 0 | PV23: 0 | PW23: 0 | PX23: 75 | PY23: 0 | PZ23: 0 | QA23: 5234.64 | QC23: 375 | QD23: MOVE S320 | QE23: =SUM(PQ23:PZ23) -> 5234.64 | QF23: 121.6 | QG23: 4150 | QH23: 0 | QI23: 0 | QJ23: 0 | QK23: 0 | QL23: 0 | QM23: 5.21 | QN23: 0 | QO23: 0 | QP23: =SUM(QF23:QO23) -> 4276.81 | QS23: =(QA23/$QA$116)*27743.06 -> 61.533224 | QT23: =(QB23/$O$116)*10429.01 -> 0 | QV23: 20 | QW23: =2074.8/110 -> 18.861818 | QX23: 5 | QY23: =QY$3 -> 428.14773 | RA23: 985.62 | RB23: =68119.05/110 -> 619.26409 | RD23: =(RB23+RC23)*30% -> 185.77923 | RE23: =SUM(RB23:RD23) -> 805.04332 | RF23: =RA23+RE23 -> 1790.6633 | RG23: =QP23-RF23 -> 2486.1467 | RH23: 1055.84 | RI23: 5480.56 | RJ23: 0 | RK23: 0 | RL23: 0 | RM23: 0 | RN23: 0 | RO23: 21.7 | RP23: 0 | RQ23: 0 | RR23: 6558.1 | RT23: 472 | RU23: MOVE S320 | RV23: 6558.1 | RW23: 87.89 | RX23: 4150 | RY23: 0 | RZ23: 0 | SA23: 0 | SB23: 0 | SC23: 0 | SD23: 1.51 | SE23: 0 | SF23: 0 | SG23: 4239.4 | SJ23: =(RR23/$RR$116)*25115.94 -> 64.445833 | SK23: =(RS23/$O$116)*12319.54 -> 0 | SL23: =52000/60 -> 866.66667 | SM23: 20 | SN23: =56040/113 -> 495.9292 | SO23: 5 | SP23: =SP$3 -> 428.52876 | SR23: 1472.76 | SS23: =SS$3 -> 596.28469 | SU23: =(SS23+ST23)*30% -> 178.88541 | SW23: =SR23+SV23 -> 1472.76 | SX23: =SG23-SW23 -> 2766.64 | SY23: =Q23+BH23+CY23+EP23+GG23+HX23+JO23+LF23+MW23+ON23+QE23+RV23 -> 20424.11 | SZ23: =AB23+BS23+DJ23+FA23+GR23+II23+JZ23+LQ23+NH23+OY23+QP23+SG23 -> 16290.67 | TA23: =AR23+CI23+DZ23+FQ23+HH23+IY23+KP23+MG23+NX23+PO23+RF23+SW23 -> 5700.8996 | TB23: =SZ23-TA23 -> 10589.77
A24: 1122 | B24: 1122_ELBLĄG | Q24: =SUM(D24:M24) -> 0 | AB24: =SUM(R24:AA24) -> 0 | AE24: =(N24/$N$116)*21028.32 -> 0 | AM24: =SUM(AC24:AL24) -> 0 | AP24: =(AN24+AO24)*30% -> 0 | AQ24: =SUM(AN24:AP24) -> 0 | AR24: =AM24+AQ24 -> 0 | AS24: =AB24-AR24 -> 0 | BH24: =SUM(AT24:BC24) -> 0 | BS24: =SUM(BI24:BR24) -> 0 | BV24: =(BD24/$BD$116)*21083.85 -> 0 | BW24: =(BE24/$O$116)*12925.76 -> 0 | CG24: =(CE24+CF24)*30% -> 0 | CI24: =CD24+CH24 -> 0 | CJ24: =BS24-CI24 -> 0 | CY24: =SUM(CK24:CT24) -> 0 | DJ24: =SUM(CZ24:DI24) -> 0 | DM24: =(CU24/$CU$116)*24055.75 -> 0 | DN24: =(CV24/$O$116)*16258.02 -> 0 | DU24: =SUM(DK24:DT24) -> 0 | DX24: =(DV24+DW24)*30% -> 0 | DY24: =SUM(DV24:DX24) -> 0 | DZ24: =DU24+DY24 -> 0 | EA24: =DJ24-DZ24 -> 0 | EP24: =SUM(EB24:EK24) -> 0 | FA24: =SUM(EQ24:EZ24) -> 0 | FD24: =(EL24/$EL$116)*26325.65 -> 0 | FE24: =(EM24/$O$116)*14846.27 -> 0 | FL24: =SUM(FB24:FK24) -> 0 | FO24: =(FM24+FN24)*30% -> 0 | FQ24: =FL24+FP24 -> 0 | FR24: =FA24-FQ24 -> 0 | GG24: =SUM(FS24:GB24) -> 0 | GR24: =SUM(GH24:GQ24) -> 0 | GU24: =(GC24/$GC$116)*30198.86 -> 0 | GV24: =(GD24/$O$116)*16844.27 -> 0 | HF24: =(HD24+HE24)*30% -> 0 | HG24: =SUM(HD24:HF24) -> 0 | HH24: =HC24+HG24 -> 0 | HI24: =GR24-HH24 -> 0 | HJ24: 764.87 | HK24: 638.59 | HL24: 0 | HM24: 0 | HN24: 0 | HO24: 0 | HP24: 0 | HQ24: 0 | HR24: 0 | HS24: 0 | HT24: 1403.46 | HV24: 71 | HW24: MOVE S320 | HX24: =SUM(HJ24:HS24) -> 1403.46 | HY24: 63.67 | HZ24: 2216.67 | IA24: 0 | IB24: 0 | IC24: 0 | ID24: 0 | IE24: 0 | IF24: 0 | IG24: 0 | IH24: 0 | II24: =SUM(HY24:IH24) -> 2280.34 | IL24: =(HT24/$HT$116)*31846.83 -> 15.546768 | IM24: =(HU24/$O$116)*17321.85 -> 0 | IO24: 20 | IP24: =24366/105 -> 232.05714 | IQ24: 5 | IR24: =IR$3 -> 445.62857 | IU24: =IU$3 -> 538.79476 | IW24: =(IU24+IV24)*30% -> 161.63843 | IY24: =IT24+IX24 -> 0 | IZ24: =II24-IY24 -> 2280.34 | JA24: 1802.88 | JB24: 3243.68 | JC24: 0 | JD24: 0 | JE24: 0 | JF24: 0 | JG24: 0 | JH24: 0 | JI24: 0 | JJ24: 0 | JK24: 5046.56 | JM24: 291 | JO24: =SUM(JA24:JJ24) -> 5046.56 | JP24: 150.07 | JQ24: 3500 | JR24: 0 | JS24: 0 | JT24: 0 | JU24: 0 | JV24: 0 | JW24: 0 | JX24: 0 | JY24: 0 | JZ24: =SUM(JP24:JY24) -> 3650.07 | KC24: =(JK24/$N$116)*39010.72 -> 101.79259 | KD24: =(JL24/$O$116)*19244.4 -> 0 | KF24: 20 | KH24: 5 | KI24: =KI$3 -> 543.39953 | KK24: 993.46 | KL24: =KL$3 -> 497.32093 | KN24: =(KL24+KM24)*30% -> 149.19628 | KO24: =SUM(KL24:KN24) -> 646.51721 | KP24: =KK24+KO24 -> 1639.9772 | KQ24: =JZ24-KP24 -> 2010.0928 | KR24: 2076.75 | KS24: 3992.97 | KT24: 0 | KU24: 0 | KV24: 0 | KW24: 0 | KX24: 0 | KY24: 29.3 | KZ24: 0 | LA24: 0 | LB24: 6099.02 | LD24: 301 | LE24: MOVE S320 | LF24: =SUM(KR24:LA24) -> 6099.02 | LG24: 172.87 | LH24: 3500 | LI24: 0 | LJ24: 0 | LK24: 0 | LL24: 0 | LM24: 0 | LN24: 2.03 | LO24: 0 | LP24: 0 | LQ24: =SUM(LG24:LP24) -> 3674.9 | LT24: =(LB24/$LB$116)*39133.48 -> 62.180289 | LU24: =(LC24/$O$116)*17015.75 -> 0 | LW24: 20 | LY24: 5 | LZ24: =LZ$3 -> 508.03738 | MB24: =SUM(LR24:MA24) -> 595.21767 | MC24: =MC$3 -> 593.54907 | ME24: =(MC24+MD24)*30% -> 178.06472 | MF24: =SUM(MC24:ME24) -> 771.61379 | MG24: =MB24+MF24 -> 1366.8315 | MH24: =LQ24-MG24 -> 2308.0685 | MI24: 760.15 | MJ24: 1404.96 | MK24: 0 | ML24: 0 | MM24: 0 | MN24: 0 | MO24: 0 | MP24: 0 | MQ24: 0 | MR24: 0 | MS24: 2165.11 | MU24: 120 | MV24: MOVE S320 | MW24: =SUM(MI24:MR24) -> 2165.11 | MX24: 63.28 | MY24: 3500 | MZ24: 0 | NA24: 0 | NB24: 0 | NC24: 0 | ND24: 0 | NE24: 0 | NF24: 0 | NG24: 0 | NH24: =SUM(MX24:NG24) -> 3563.28 | NK24: =(MS24/$N$116)*0 -> 0 | NL24: =(MT24/$O$116)*13804.26 -> 0 | NQ24: =NQ$3 -> 469.6789 | NT24: =78812.25/109 -> 723.04817 | NV24: =(NT24+NU24)*30% -> 216.91445 | NW24: =SUM(NT24:NV24) -> 939.96261 | NX24: =NS24+NW24 -> 939.96261 | NY24: =NH24-NX24 -> 2623.3174 | NZ24: 3495.19 | OA24: 3538.33 | OB24: 19.4 | OC24: 0 | OD24: 0 | OE24: 0 | OF24: 0 | OG24: 0 | OH24: 0 | OI24: 0 | OJ24: 7052.92 | OK24: =ON24-OJ24 -> 0 | OL24: 370 | OM24: MOVE S320 | ON24: =SUM(NZ24:OI24) -> 7052.92 | OO24: 290.94 | OP24: 3500 | OQ24: 1.24 | OR24: 0 | OS24: 0 | OT24: 0 | OU24: 0 | OV24: 0 | OW24: 0 | OX24: 0 | OY24: =SUM(OO24:OX24) -> 3792.18 | PB24: =(OJ24/$OJ$116)*56307.47 -> 152.50713 | PC24: =(OK24/$O$116)*16757.91 -> 0 | PE24: 20 | PF24: =3288/100 -> 32.88 | PG24: 5 | PH24: =PH$3 -> 495.20491 | PJ24: =SUM(OZ24:PI24) -> 705.59204 | PK24: =PK$3 -> 643.25573 | PM24: =(PK24+PL24)*30% -> 192.97672 | PN24: =SUM(PK24:PM24) -> 836.23245 | PO24: =PJ24+PN24 -> 1541.8245 | PP24: =OY24-PO24 -> 2250.3555 | PQ24: 882.92 | PR24: 2146.46 | PS24: 0 | PT24: 0 | PU24: 0 | PV24: 0 | PW24: 0 | PX24: 0 | PY24: 0 | PZ24: 0 | QA24: 3029.38 | QC24: 179 | QD24: MOVE S320 | QE24: =SUM(PQ24:PZ24) -> 3029.38 | QF24: 73.5 | QG24: 3500 | QH24: 0 | QI24: 0 | QJ24: 0 | QK24: 0 | QL24: 0 | QM24: 0 | QN24: 0 | QO24: 0 | QP24: =SUM(QF24:QO24) -> 3573.5 | QS24: =(QA24/$QA$116)*27743.06 -> 35.61038 | QT24: =(QB24/$O$116)*10429.01 -> 0 | QV24: 20 | QW24: =2074.8/110 -> 18.861818 | QX24: 5 | QY24: =QY$3 -> 428.14773 | RA24: 953.98 | RB24: =68119.05/110 -> 619.26409 | RD24: =(RB24+RC24)*30% -> 185.77923 | RE24: =SUM(RB24:RD24) -> 805.04332 | RF24: =RA24+RE24 -> 1759.0233 | RG24: =QP24-RF24 -> 1814.4767 | RH24: 321.16 | RI24: 1260.23 | RJ24: 0 | RK24: 0 | RL24: 0 | RM24: 0 | RN24: 0 | RO24: 0 | RP24: 0 | RQ24: 0 | RR24: 1581.39 | RT24: 101 | RU24: MOVE S320 | RV24: 1581.39 | RW24: 26.73 | RX24: 3500 | RY24: 0 | RZ24: 0 | SA24: 0 | SB24: 0 | SC24: 0 | SD24: 0 | SE24: 0 | SF24: 0 | SG24: 3526.73 | SJ24: =(RR24/$RR$116)*25115.94 -> 15.540171 | SK24: =(RS24/$O$116)*12319.54 -> 0 | SL24: =52000/60 -> 866.66667 | SM24: 20 | SN24: =56040/113 -> 495.9292 | SO24: 5 | SP24: =SP$3 -> 428.52876 | SR24: 1408.13 | SS24: =SS$3 -> 596.28469 | SU24: =(SS24+ST24)*30% -> 178.88541 | SW24: =SR24+SV24 -> 1408.13 | SX24: =SG24-SW24 -> 2118.6 | SY24: =Q24+BH24+CY24+EP24+GG24+HX24+JO24+LF24+MW24+ON24+QE24+RV24 -> 26377.84 | SZ24: =AB24+BS24+DJ24+FA24+GR24+II24+JZ24+LQ24+NH24+OY24+QP24+SG24 -> 24061 | TA24: =AR24+CI24+DZ24+FQ24+HH24+IY24+KP24+MG24+NX24+PO24+RF24+SW24 -> 8655.7491 | TB24: =SZ24-TA24 -> 15405.251
A25: 1123 | B25: 1123_GDAŃSK WRZESZCZ | Q25: =SUM(D25:M25) -> 0 | AB25: =SUM(R25:AA25) -> 0 | AE25: =(N25/$N$116)*21028.32 -> 0 | AM25: =SUM(AC25:AL25) -> 0 | AP25: =(AN25+AO25)*30% -> 0 | AQ25: =SUM(AN25:AP25) -> 0 | AR25: =AM25+AQ25 -> 0 | AS25: =AB25-AR25 -> 0 | BH25: =SUM(AT25:BC25) -> 0 | BS25: =SUM(BI25:BR25) -> 0 | BV25: =(BD25/$BD$116)*21083.85 -> 0 | BW25: =(BE25/$O$116)*12925.76 -> 0 | CG25: =(CE25+CF25)*30% -> 0 | CI25: =CD25+CH25 -> 0 | CJ25: =BS25-CI25 -> 0 | CY25: =SUM(CK25:CT25) -> 0 | DJ25: =SUM(CZ25:DI25) -> 0 | DM25: =(CU25/$CU$116)*24055.75 -> 0 | DN25: =(CV25/$O$116)*16258.02 -> 0 | DU25: =SUM(DK25:DT25) -> 0 | DX25: =(DV25+DW25)*30% -> 0 | DY25: =SUM(DV25:DX25) -> 0 | DZ25: =DU25+DY25 -> 0 | EA25: =DJ25-DZ25 -> 0 | EP25: =SUM(EB25:EK25) -> 0 | FA25: =SUM(EQ25:EZ25) -> 0 | FD25: =(EL25/$EL$116)*26325.65 -> 0 | FE25: =(EM25/$O$116)*14846.27 -> 0 | FL25: =SUM(FB25:FK25) -> 0 | FO25: =(FM25+FN25)*30% -> 0 | FQ25: =FL25+FP25 -> 0 | FR25: =FA25-FQ25 -> 0 | GG25: =SUM(FS25:GB25) -> 0 | GR25: =SUM(GH25:GQ25) -> 0 | GU25: =(GC25/$GC$116)*30198.86 -> 0 | GV25: =(GD25/$O$116)*16844.27 -> 0 | HF25: =(HD25+HE25)*30% -> 0 | HG25: =SUM(HD25:HF25) -> 0 | HH25: =HC25+HG25 -> 0 | HI25: =GR25-HH25 -> 0 | HJ25: 7834.35 | HK25: 10197.76 | HL25: 0 | HM25: 0 | HN25: 0 | HO25: 4569.2 | HP25: 0 | HQ25: 0 | HR25: 0 | HS25: 0 | HT25: 22601.31 | HV25: 1634 | HW25: MOVE S320 | HX25: =SUM(HJ25:HS25) -> 22601.31 | HY25: 652.13 | HZ25: 2216.67 | IA25: 0 | IB25: 0 | IC25: 0 | ID25: 296.78 | IE25: 0 | IF25: 0 | IG25: 0 | IH25: 0 | II25: =SUM(HY25:IH25) -> 3165.58 | IL25: =(HT25/$HT$116)*31846.83 -> 250.36504 | IM25: =(HU25/$O$116)*17321.85 -> 0 | IO25: 20 | IP25: =24366/105 -> 232.05714 | IQ25: 5 | IR25: =IR$3 -> 445.62857 | IU25: =IU$3 -> 538.79476 | IW25: =(IU25+IV25)*30% -> 161.63843 | IY25: =IT25+IX25 -> 0 | IZ25: =II25-IY25 -> 3165.58 | JA25: 12730.02 | JB25: 19752.87 | JC25: 0 | JD25: 0 | JE25: 70.22 | JF25: 13647.8 | JG25: 0 | JH25: 0 | JI25: 0 | JJ25: 0 | JK25: 46200.91 | JM25: 3249 | JO25: =SUM(JA25:JJ25) -> 46200.91 | JP25: 1059.66 | JQ25: 3500 | JR25: 0 | JS25: 0 | JT25: 4.55 | JU25: 886.45 | JV25: 0 | JW25: 0 | JX25: 0 | JY25: 0 | JZ25: =SUM(JP25:JY25) -> 5450.66 | KC25: =(JK25/$N$116)*39010.72 -> 931.90413 | KD25: =(JL25/$O$116)*19244.4 -> 0 | KF25: 20 | KH25: 5 | KI25: =KI$3 -> 543.39953 | KK25: 1823.57 | KL25: =KL$3 -> 497.32093 | KN25: =(KL25+KM25)*30% -> 149.19628 | KO25: =SUM(KL25:KN25) -> 646.51721 | KP25: =KK25+KO25 -> 2470.0872 | KQ25: =JZ25-KP25 -> 2980.5728 | KR25: 13682.63 | KS25: 21616.23 | KT25: 0 | KU25: 0 | KV25: 15 | KW25: 14595.2 | KX25: 0 | KY25: 0 | KZ25: 0 | LA25: 0 | LB25: 49909.06 | LD25: 3601 | LE25: MOVE S320 | LF25: =SUM(KR25:LA25) -> 49909.06 | LG25: 1138.96 | LH25: 3500 | LI25: 0 | LJ25: 0 | LK25: 0.97 | LL25: 947.98 | LM25: 0 | LN25: 0 | LO25: 0 | LP25: 0 | LQ25: =SUM(LG25:LP25) -> 5587.91 | LT25: =(LB25/$LB$116)*39133.48 -> 508.82925 | LU25: =(LC25/$O$116)*17015.75 -> 0 | LW25: 20 | LY25: 5 | LZ25: =LZ$3 -> 508.03738 | MB25: =SUM(LR25:MA25) -> 1041.8666 | MC25: =MC$3 -> 593.54907 | ME25: =(MC25+MD25)*30% -> 178.06472 | MF25: =SUM(MC25:ME25) -> 771.61379 | MG25: =MB25+MF25 -> 1813.4804 | MH25: =LQ25-MG25 -> 3774.4296 | MI25: 7203.43 | MJ25: 15081.29 | MK25: 0 | ML25: 0 | MM25: 0 | MN25: 7802.95 | MO25: 0 | MP25: 0 | MQ25: 0 | MR25: 0 | MS25: 30087.67 | MU25: 2387 | MV25: MOVE S320 | MW25: =SUM(MI25:MR25) -> 30087.67 | MX25: 599.63 | MY25: 3500 | MZ25: 0 | NA25: 0 | NB25: 0 | NC25: 506.82 | ND25: 0 | NE25: 0 | NF25: 0 | NG25: 0 | NH25: =SUM(MX25:NG25) -> 4606.45 | NK25: =(MS25/$N$116)*0 -> 0 | NL25: =(MT25/$O$116)*13804.26 -> 0 | NQ25: =NQ$3 -> 469.6789 | NT25: =78812.25/109 -> 723.04817 | NV25: =(NT25+NU25)*30% -> 216.91445 | NW25: =SUM(NT25:NV25) -> 939.96261 | NX25: =NS25+NW25 -> 939.96261 | NY25: =NH25-NX25 -> 3666.4874 | NZ25: 6879.48 | OA25: 14177.04 | OB25: 0 | OC25: 0 | OD25: 0 | OE25: 7095 | OF25: 0 | OG25: 0 | OH25: 0 | OI25: 0 | OJ25: 28151.52 | OK25: =ON25-OJ25 -> 0 | OL25: 2269 | OM25: MOVE S320 | ON25: =SUM(NZ25:OI25) -> 28151.52 | OO25: 572.66 | OP25: 3500 | OQ25: 0 | OR25: 0 | OS25: 0 | OT25: 460.83 | OU25: 0 | OV25: 0 | OW25: 0 | OX25: 0 | OY25: =SUM(OO25:OX25) -> 4533.49 | PB25: =(OJ25/$OJ$116)*56307.47 -> 608.72766 | PC25: =(OK25/$O$116)*16757.91 -> 0 | PE25: 20 | PF25: =3288/100 -> 32.88 | PG25: 5 | PH25: =PH$3 -> 495.20491 | PJ25: =SUM(OZ25:PI25) -> 1161.8126 | PK25: =PK$3 -> 643.25573 | PM25: =(PK25+PL25)*30% -> 192.97672 | PN25: =SUM(PK25:PM25) -> 836.23245 | PO25: =PJ25+PN25 -> 1998.045 | PP25: =OY25-PO25 -> 2535.445 | PQ25: 4674.59 | PR25: 10731.3 | PS25: 0 | PT25: 0 | PU25: 0 | PV25: 5072.8 | PW25: 0 | PX25: 0 | PY25: 0 | PZ25: 0 | QA25: 20478.69 | QC25: 1743 | QD25: MOVE S320 | QE25: =SUM(PQ25:PZ25) -> 20478.69 | QF25: 389.13 | QG25: 3500 | QH25: 0 | QI25: 0 | QJ25: 0 | QK25: 329.49 | QL25: 0 | QM25: 0 | QN25: 0 | QO25: 0 | QP25: =SUM(QF25:QO25) -> 4218.62 | QS25: =(QA25/$QA$116)*27743.06 -> 240.72712 | QT25: =(QB25/$O$116)*10429.01 -> 0 | QV25: 20 | QW25: =2074.8/110 -> 18.861818 | QX25: 5 | QY25: =QY$3 -> 428.14773 | RA25: 1204.29 | RB25: =68119.05/110 -> 619.26409 | RD25: =(RB25+RC25)*30% -> 185.77923 | RE25: =SUM(RB25:RD25) -> 805.04332 | RF25: =RA25+RE25 -> 2009.3333 | RG25: =QP25-RF25 -> 2209.2867 | RH25: 6432.89 | RI25: 12891.15 | RJ25: 0 | RK25: 0 | RL25: 0 | RM25: 5758.7 | RN25: 0 | RO25: 0 | RP25: 0 | RQ25: 0 | RR25: 25082.74 | RT25: 1946 | RU25: MOVE S320 | RV25: 25082.74 | RW25: 535.48 | RX25: 3500 | RY25: 0 | RZ25: 0 | SA25: 0 | SB25: 374.04 | SC25: 0 | SD25: 0 | SE25: 0 | SF25: 0 | SG25: 4409.52 | SJ25: =(RR25/$RR$116)*25115.94 -> 246.48573 | SK25: =(RS25/$O$116)*12319.54 -> 0 | SL25: =52000/60 -> 866.66667 | SM25: 20 | SN25: =56040/113 -> 495.9292 | SO25: 5 | SP25: =SP$3 -> 428.52876 | SR25: 1713.33 | SS25: =SS$3 -> 596.28469 | SU25: =(SS25+ST25)*30% -> 178.88541 | SW25: =SR25+SV25 -> 1713.33 | SX25: =SG25-SW25 -> 2696.19 | SY25: =Q25+BH25+CY25+EP25+GG25+HX25+JO25+LF25+MW25+ON25+QE25+RV25 -> 222511.9 | SZ25: =AB25+BS25+DJ25+FA25+GR25+II25+JZ25+LQ25+NH25+OY25+QP25+SG25 -> 31972.23 | TA25: =AR25+CI25+DZ25+FQ25+HH25+IY25+KP25+MG25+NX25+PO25+RF25+SW25 -> 10944.239 | TB25: =SZ25-TA25 -> 21027.991
